Workbook

Sheet DRE
A1: Fluxos de caixa
C2: Categoria | D2: Receita de vendas | E2: Despesa com serviço de terceiros | F2: Despesa administrativa | G2: Despesa administrativa | H2: Despesa administrativa | I2: IRPJ | J2: Fluxo de caixa de financiamento | K2: Fluxo de caixa de financiamento | L2: Despesa financeira | M2: Captações de empréstimo | N2: Aquisição de ativos - usina solar | P2: DRE | Q2: DRE | R2: DRE | S2: DRE | T2: DRE | U2: DRE | V2: DRE | W2: DRE | X2: DRE | Z2: Fluxo de caixa operacional | AA2: Fluxo de caixa operacional | AB2: Fluxo de caixa investimento | AC2: Fluxo de caixa de financiamento | AD2: Fluxo de caixa de financiamento | AE2: Caixa | AF2: Caixa | AG2: Caixa
C3: Item | D3: Consórcio Zetawatts | E3: Limpeza das placas | F3: Contador | G3: Alvará | H3: JUCERJA | I3: Simples | J3: Parcela do empréstimo | K3: Amortização do empréstimo | L3: Juros | M3: Empréstimo | N3: Usina São Gonçalo I | P3: Lucro bruto | Q3: Despesas operacionais | R3: EBITDA | S3: Depreciação e amortização | T3: EBIT | U3: Despesas financeiras | V3: Lucro antes do imposto de renda | W3: IRPJ | X3: Lucro líquido | Z3: EBIDTA | AA3: Impostos pagos | AB3: Aquisição de ativos | AC3: Captação de empréstimo | AD3: Pagamento de juros e principal | AE3: Resultado líquido | AF3: Saldo inicial | AG3: Saldo final
A4: =YEAR(C4) -> 2021 | B4: ="Q"&(QUOTIENT(MONTH(C4),3.1)+1) -> Q3 | C4: 44409 | F4: 300 | J4: =K4+L4 -> 8645.2403 | K4: =Financiamento!D13 -> 3455.7915 | L4: =Financiamento!C13 -> 5189.4489 | M4: =Financiamento!$B$3 -> 331380.09 | N4: =M4 -> 331380.09 | P4: =D4 -> 0 | Q4: =-SUM(E4:H4) -> -300 | R4: =SUM(P4:Q4) -> -300 | T4: =SUM(R4:S4) -> -300 | U4: =-L4 -> -5189.4489 | V4: =SUM(T4:U4) -> -5489.4489 | W4: =-I4 -> 0 | X4: =SUM(V4:W4) -> -5489.4489 | Z4: =R4 -> -300 | AA4: =W4 -> 0 | AB4: =-N4 -> -331380.09 | AC4: =M4 -> 331380.09 | AD4: =-J4 -> -8645.2403 | AE4: =SUM(Z4:AD4) -> -8945.2403 | AF4: 0 | AG4: =AF4+AE4 -> -8945.2403
A5: =YEAR(C5) -> 2021 | B5: ="Q"&(QUOTIENT(MONTH(C5),3.1)+1) -> Q3 | C5: 44440 | F5: 300 | J5: =K5+L5 -> 8645.2403 | K5: =Financiamento!D14 -> 3509.0106 | L5: =Financiamento!C14 -> 5136.2297 | P5: =D5 -> 0 | Q5: =-SUM(E5:H5) -> -300 | R5: =SUM(P5:Q5) -> -300 | T5: =SUM(R5:S5) -> -300 | U5: =-L5 -> -5136.2297 | V5: =SUM(T5:U5) -> -5436.2297 | W5: =-I5 -> 0 | X5: =SUM(V5:W5) -> -5436.2297 | Z5: =R5 -> -300 | AA5: =W5 -> 0 | AB5: =-N5 -> 0 | AC5: =M5 -> 0 | AD5: =-J5 -> -8645.2403 | AE5: =SUM(Z5:AD5) -> -8945.2403 | AF5: =AG4 -> -8945.2403 | AG5: =AF5+AE5 -> -17890.481
A6: =YEAR(C6) -> 2021 | B6: ="Q"&(QUOTIENT(MONTH(C6),3.1)+1) -> Q4 | C6: 44470 | F6: 300 | J6: =K6+L6 -> 8645.2403 | K6: =Financiamento!D15 -> 3563.0494 | L6: =Financiamento!C15 -> 5082.1909 | P6: =D6 -> 0 | Q6: =-SUM(E6:H6) -> -300 | R6: =SUM(P6:Q6) -> -300 | T6: =SUM(R6:S6) -> -300 | U6: =-L6 -> -5082.1909 | V6: =SUM(T6:U6) -> -5382.1909 | W6: =-I6 -> 0 | X6: =SUM(V6:W6) -> -5382.1909 | Z6: =R6 -> -300 | AA6: =W6 -> 0 | AB6: =-N6 -> 0 | AC6: =M6 -> 0 | AD6: =-J6 -> -8645.2403 | AE6: =SUM(Z6:AD6) -> -8945.2403 | AF6: =AG5 -> -17890.481 | AG6: =AF6+AE6 -> -26835.721
A7: =YEAR(C7) -> 2021 | B7: ="Q"&(QUOTIENT(MONTH(C7),3.1)+1) -> Q4 | C7: 44501 | F7: 300 | J7: =K7+L7 -> 8645.2403 | K7: =Financiamento!D16 -> 3617.9204 | L7: =Financiamento!C16 -> 5027.32 | P7: =D7 -> 0 | Q7: =-SUM(E7:H7) -> -300 | R7: =SUM(P7:Q7) -> -300 | T7: =SUM(R7:S7) -> -300 | U7: =-L7 -> -5027.32 | V7: =SUM(T7:U7) -> -5327.32 | W7: =-I7 -> 0 | X7: =SUM(V7:W7) -> -5327.32 | Z7: =R7 -> -300 | AA7: =W7 -> 0 | AB7: =-N7 -> 0 | AC7: =M7 -> 0 | AD7: =-J7 -> -8645.2403 | AE7: =SUM(Z7:AD7) -> -8945.2403 | AF7: =AG6 -> -26835.721 | AG7: =AF7+AE7 -> -35780.961
A8: =YEAR(C8) -> 2021 | B8: ="Q"&(QUOTIENT(MONTH(C8),3.1)+1) -> Q4 | C8: 44531 | F8: 300 | J8: =K8+L8 -> 8645.2403 | K8: =Financiamento!D17 -> 3673.6363 | L8: =Financiamento!C17 -> 4971.604 | P8: =D8 -> 0 | Q8: =-SUM(E8:H8) -> -300 | R8: =SUM(P8:Q8) -> -300 | T8: =SUM(R8:S8) -> -300 | U8: =-L8 -> -4971.604 | V8: =SUM(T8:U8) -> -5271.604 | W8: =-I8 -> 0 | X8: =SUM(V8:W8) -> -5271.604 | Z8: =R8 -> -300 | AA8: =W8 -> 0 | AB8: =-N8 -> 0 | AC8: =M8 -> 0 | AD8: =-J8 -> -8645.2403 | AE8: =SUM(Z8:AD8) -> -8945.2403 | AF8: =AG7 -> -35780.961 | AG8: =AF8+AE8 -> -44726.202
A9: =YEAR(C9) -> 2022 | B9: ="Q"&(QUOTIENT(MONTH(C9),3.1)+1) -> Q1 | C9: 44562 | F9: 300 | J9: =K9+L9 -> 8645.2403 | K9: =Financiamento!D18 -> 3730.2103 | L9: =Financiamento!C18 -> 4915.03 | P9: =D9 -> 0 | Q9: =-SUM(E9:H9) -> -300 | R9: =SUM(P9:Q9) -> -300 | T9: =SUM(R9:S9) -> -300 | U9: =-L9 -> -4915.03 | V9: =SUM(T9:U9) -> -5215.03 | W9: =-I9 -> 0 | X9: =SUM(V9:W9) -> -5215.03 | Z9: =R9 -> -300 | AA9: =W9 -> 0 | AB9: =-N9 -> 0 | AC9: =M9 -> 0 | AD9: =-J9 -> -8645.2403 | AE9: =SUM(Z9:AD9) -> -8945.2403 | AF9: =AG8 -> -44726.202 | AG9: =AF9+AE9 -> -53671.442
A10: =YEAR(C10) -> 2022 | B10: ="Q"&(QUOTIENT(MONTH(C10),3.1)+1) -> Q1 | C10: 44593 | F10: 300 | J10: =K10+L10 -> 8645.2403 | K10: =Financiamento!D19 -> 3787.6556 | L10: =Financiamento!C19 -> 4857.5848 | P10: =D10 -> 0 | Q10: =-SUM(E10:H10) -> -300 | R10: =SUM(P10:Q10) -> -300 | T10: =SUM(R10:S10) -> -300 | U10: =-L10 -> -4857.5848 | V10: =SUM(T10:U10) -> -5157.5848 | W10: =-I10 -> 0 | X10: =SUM(V10:W10) -> -5157.5848 | Z10: =R10 -> -300 | AA10: =W10 -> 0 | AB10: =-N10 -> 0 | AC10: =M10 -> 0 | AD10: =-J10 -> -8645.2403 | AE10: =SUM(Z10:AD10) -> -8945.2403 | AF10: =AG9 -> -53671.442 | AG10: =AF10+AE10 -> -62616.682
A11: =YEAR(C11) -> 2022 | B11: ="Q"&(QUOTIENT(MONTH(C11),3.1)+1) -> Q1 | C11: 44621 | F11: 300 | J11: =K11+L11 -> 8645.2403 | K11: =Financiamento!D20 -> 3845.9855 | L11: =Financiamento!C20 -> 4799.2549 | P11: =D11 -> 0 | Q11: =-SUM(E11:H11) -> -300 | R11: =SUM(P11:Q11) -> -300 | T11: =SUM(R11:S11) -> -300 | U11: =-L11 -> -4799.2549 | V11: =SUM(T11:U11) -> -5099.2549 | W11: =-I11 -> 0 | X11: =SUM(V11:W11) -> -5099.2549 | Z11: =R11 -> -300 | AA11: =W11 -> 0 | AB11: =-N11 -> 0 | AC11: =M11 -> 0 | AD11: =-J11 -> -8645.2403 | AE11: =SUM(Z11:AD11) -> -8945.2403 | AF11: =AG10 -> -62616.682 | AG11: =AF11+AE11 -> -71561.923
A12: =YEAR(C12) -> 2022 | B12: ="Q"&(QUOTIENT(MONTH(C12),3.1)+1) -> Q2 | C12: 44652 | F12: 300 | J12: =K12+L12 -> 8645.2403 | K12: =Financiamento!D21 -> 3905.2137 | L12: =Financiamento!C21 -> 4740.0267 | P12: =D12 -> 0 | Q12: =-SUM(E12:H12) -> -300 | R12: =SUM(P12:Q12) -> -300 | T12: =SUM(R12:S12) -> -300 | U12: =-L12 -> -4740.0267 | V12: =SUM(T12:U12) -> -5040.0267 | W12: =-I12 -> 0 | X12: =SUM(V12:W12) -> -5040.0267 | Z12: =R12 -> -300 | AA12: =W12 -> 0 | AB12: =-N12 -> 0 | AC12: =M12 -> 0 | AD12: =-J12 -> -8645.2403 | AE12: =SUM(Z12:AD12) -> -8945.2403 | AF12: =AG11 -> -71561.923 | AG12: =AF12+AE12 -> -80507.163
A13: =YEAR(C13) -> 2022 | B13: ="Q"&(QUOTIENT(MONTH(C13),3.1)+1) -> Q2 | C13: 44682 | F13: 300 | J13: =K13+L13 -> 8645.2403 | K13: =Financiamento!D22 -> 3965.354 | L13: =Financiamento!C22 -> 4679.8864 | P13: =D13 -> 0 | Q13: =-SUM(E13:H13) -> -300 | R13: =SUM(P13:Q13) -> -300 | T13: =SUM(R13:S13) -> -300 | U13: =-L13 -> -4679.8864 | V13: =SUM(T13:U13) -> -4979.8864 | W13: =-I13 -> 0 | X13: =SUM(V13:W13) -> -4979.8864 | Z13: =R13 -> -300 | AA13: =W13 -> 0 | AB13: =-N13 -> 0 | AC13: =M13 -> 0 | AD13: =-J13 -> -8645.2403 | AE13: =SUM(Z13:AD13) -> -8945.2403 | AF13: =AG12 -> -80507.163 | AG13: =AF13+AE13 -> -89452.403
A14: =YEAR(C14) -> 2022 | B14: ="Q"&(QUOTIENT(MONTH(C14),3.1)+1) -> Q2 | C14: 44713 | F14: 300 | J14: =K14+L14 -> 8645.2403 | K14: =Financiamento!D23 -> 4026.4204 | L14: =Financiamento!C23 -> 4618.8199 | P14: =D14 -> 0 | Q14: =-SUM(E14:H14) -> -300 | R14: =SUM(P14:Q14) -> -300 | T14: =SUM(R14:S14) -> -300 | U14: =-L14 -> -4618.8199 | V14: =SUM(T14:U14) -> -4918.8199 | W14: =-I14 -> 0 | X14: =SUM(V14:W14) -> -4918.8199 | Z14: =R14 -> -300 | AA14: =W14 -> 0 | AB14: =-N14 -> 0 | AC14: =M14 -> 0 | AD14: =-J14 -> -8645.2403 | AE14: =SUM(Z14:AD14) -> -8945.2403 | AF14: =AG13 -> -89452.403 | AG14: =AF14+AE14 -> -98397.644
A15: =YEAR(C15) -> 2022 | B15: ="Q"&(QUOTIENT(MONTH(C15),3.1)+1) -> Q3 | C15: 44743 | F15: 300 | J15: =K15+L15 -> 8645.2403 | K15: =Financiamento!D24 -> 4088.4273 | L15: =Financiamento!C24 -> 4556.8131 | P15: =D15 -> 0 | Q15: =-SUM(E15:H15) -> -300 | R15: =SUM(P15:Q15) -> -300 | T15: =SUM(R15:S15) -> -300 | U15: =-L15 -> -4556.8131 | V15: =SUM(T15:U15) -> -4856.8131 | W15: =-I15 -> 0 | X15: =SUM(V15:W15) -> -4856.8131 | Z15: =R15 -> -300 | AA15: =W15 -> 0 | AB15: =-N15 -> 0 | AC15: =M15 -> 0 | AD15: =-J15 -> -8645.2403 | AE15: =SUM(Z15:AD15) -> -8945.2403 | AF15: =AG14 -> -98397.644 | AG15: =AF15+AE15 -> -107342.88
A16: =YEAR(C16) -> 2022 | B16: ="Q"&(QUOTIENT(MONTH(C16),3.1)+1) -> Q3 | C16: 44774 | F16: 300 | J16: =K16+L16 -> 8645.2403 | K16: =Financiamento!D25 -> 4151.3891 | L16: =Financiamento!C25 -> 4493.8513 | P16: =D16 -> 0 | Q16: =-SUM(E16:H16) -> -300 | R16: =SUM(P16:Q16) -> -300 | T16: =SUM(R16:S16) -> -300 | U16: =-L16 -> -4493.8513 | V16: =SUM(T16:U16) -> -4793.8513 | W16: =-I16 -> 0 | X16: =SUM(V16:W16) -> -4793.8513 | Z16: =R16 -> -300 | AA16: =W16 -> 0 | AB16: =-N16 -> 0 | AC16: =M16 -> 0 | AD16: =-J16 -> -8645.2403 | AE16: =SUM(Z16:AD16) -> -8945.2403 | AF16: =AG15 -> -107342.88 | AG16: =AF16+AE16 -> -116288.12
... A22: =YEAR(C22) -> 2023 | B22: ="Q"&(QUOTIENT(MONTH(C22),3.1)+1) -> Q1 | C22: 44958 | F22: 300 | J22: =K22+L22 -> 8645.2403 | K22: =Financiamento!D31 -> 4550.0523 | L22: =Financiamento!C31 -> 4095.188 | P22: =D22 -> 0 | Q22: =-SUM(E22:H22) -> -300 | R22: =SUM(P22:Q22) -> -300 | T22: =SUM(R22:S22) -> -300 | U22: =-L22 -> -4095.188 | V22: =SUM(T22:U22) -> -4395.188 | W22: =-I22 -> 0 | X22: =SUM(V22:W22) -> -4395.188 | Z22: =R22 -> -300 | AA22: =W22 -> 0 | AB22: =-N22 -> 0 | AC22: =M22 -> 0 | AD22: =-J22 -> -8645.2403 | AE22: =SUM(Z22:AD22) -> -8945.2403 | AF22: =AG21 -> -161014.33 | AG22: =AF22+AE22 -> -169959.57
A23: =YEAR(C23) -> 2023 | B23: ="Q"&(QUOTIENT(MONTH(C23),3.1)+1) -> Q1 | C23: 44986 | D23: ='Faturamento 235'!P4+'Faturamento Itaipu'!L2+'Faturamento Icaraí'!P2 -> 6633.93 | F23: 300 | I23: =D23*6% -> 398.0358 | J23: =K23+L23 -> 8645.2403 | K23: =Financiamento!D32 -> 4620.1231 | L23: =Financiamento!C32 -> 4025.1172 | P23: =D23 -> 6633.93 | Q23: =-SUM(E23:H23) -> -300 | R23: =SUM(P23:Q23) -> 6333.93 | T23: =SUM(R23:S23) -> 6333.93 | U23: =-L23 -> -4025.1172 | V23: =SUM(T23:U23) -> 2308.8127 | W23: =-I23 -> -398.0358 | X23: =SUM(V23:W23) -> 1910.777 | Z23: =R23 -> 6333.93 | AA23: =W23 -> -398.0358 | AB23: =-N23 -> 0 | AC23: =M23 -> 0 | AD23: =-J23 -> -8645.2403 | AE23: =SUM(Z23:AD23) -> -2709.3462 | AF23: =AG22 -> -169959.57 | AG23: =AF23+AE23 -> -172668.91
A24: =YEAR(C24) -> 2023 | B24: ="Q"&(QUOTIENT(MONTH(C24),3.1)+1) -> Q2 | C24: 45017 | D24: ='Faturamento 235'!P5+'Faturamento Itaipu'!L3+'Faturamento Icaraí'!P3 -> 4801.7427 | F24: 300 | I24: =D24*6% -> 288.10456 | J24: =K24+L24 -> 8645.2403 | K24: =Financiamento!D33 -> 4691.273 | L24: =Financiamento!C33 -> 3953.9673 | P24: =D24 -> 4801.7427 | Q24: =-SUM(E24:H24) -> -300 | R24: =SUM(P24:Q24) -> 4501.7427 | T24: =SUM(R24:S24) -> 4501.7427 | U24: =-L24 -> -3953.9673 | V24: =SUM(T24:U24) -> 547.77538 | W24: =-I24 -> -288.10456 | X24: =SUM(V24:W24) -> 259.67081 | Z24: =R24 -> 4501.7427 | AA24: =W24 -> -288.10456 | AB24: =-N24 -> 0 | AC24: =M24 -> 0 | AD24: =-J24 -> -8645.2403 | AE24: =SUM(Z24:AD24) -> -4431.6022 | AF24: =AG23 -> -172668.91 | AG24: =AF24+AE24 -> -177100.51
A25: =YEAR(C25) -> 2023 | B25: ="Q"&(QUOTIENT(MONTH(C25),3.1)+1) -> Q2 | C25: 45047 | D25: ='Faturamento 235'!P6+'Faturamento Itaipu'!L4+'Faturamento Icaraí'!P4 -> 5583.9064 | F25: 300 | I25: =D25*6% -> 335.03438 | J25: =K25+L25 -> 8645.2403 | K25: =Financiamento!D34 -> 4763.5186 | L25: =Financiamento!C34 -> 3881.7217 | P25: =D25 -> 5583.9064 | Q25: =-SUM(E25:H25) -> -300 | R25: =SUM(P25:Q25) -> 5283.9064 | T25: =SUM(R25:S25) -> 5283.9064 | U25: =-L25 -> -3881.7217 | V25: =SUM(T25:U25) -> 1402.1847 | W25: =-I25 -> -335.03438 | X25: =SUM(V25:W25) -> 1067.1503 | Z25: =R25 -> 5283.9064 | AA25: =W25 -> -335.03438 | AB25: =-N25 -> 0 | AC25: =M25 -> 0 | AD25: =-J25 -> -8645.2403 | AE25: =SUM(Z25:AD25) -> -3696.3683 | AF25: =AG24 -> -177100.51 | AG25: =AF25+AE25 -> -180796.88
A26: =YEAR(C26) -> 2023 | B26: ="Q"&(QUOTIENT(MONTH(C26),3.1)+1) -> Q2 | C26: 45078 | D26: ='Faturamento 235'!P7+'Faturamento Itaipu'!L5+'Faturamento Icaraí'!P5 -> 4018.4622 | F26: 300 | I26: =D26*6% -> 241.10773 | J26: =K26+L26 -> 8645.2403 | K26: =Financiamento!D35 -> 4836.8768 | L26: =Financiamento!C35 -> 3808.3635 | P26: =D26 -> 4018.4622 | Q26: =-SUM(E26:H26) -> -300 | R26: =SUM(P26:Q26) -> 3718.4622 | T26: =SUM(R26:S26) -> 3718.4622 | U26: =-L26 -> -3808.3635 | V26: =SUM(T26:U26) -> -89.901362 | W26: =-I26 -> -241.10773 | X26: =SUM(V26:W26) -> -331.00909 | Z26: =R26 -> 3718.4622 | AA26: =W26 -> -241.10773 | AB26: =-N26 -> 0 | AC26: =M26 -> 0 | AD26: =-J26 -> -8645.2403 | AE26: =SUM(Z26:AD26) -> -5167.8859 | AF26: =AG25 -> -180796.88 | AG26: =AF26+AE26 -> -185964.77
A27: =YEAR(C27) -> 2023 | B27: ="Q"&(QUOTIENT(MONTH(C27),3.1)+1) -> Q3 | C27: 45108 | D27: ='Faturamento 235'!P8+'Faturamento Itaipu'!L6+'Faturamento Icaraí'!P6 -> 3394.6012 | F27: 300 | I27: =D27*6% -> 203.67607 | J27: =K27+L27 -> 8645.2403 | K27: =Financiamento!D36 -> 4911.3647 | L27: =Financiamento!C36 -> 3733.8756 | P27: =D27 -> 3394.6012 | Q27: =-SUM(E27:H27) -> -300 | R27: =SUM(P27:Q27) -> 3094.6012 | T27: =SUM(R27:S27) -> 3094.6012 | U27: =-L27 -> -3733.8756 | V27: =SUM(T27:U27) -> -639.27447 | W27: =-I27 -> -203.67607 | X27: =SUM(V27:W27) -> -842.95054 | Z27: =R27 -> 3094.6012 | AA27: =W27 -> -203.67607 | AB27: =-N27 -> 0 | AC27: =M27 -> 0 | AD27: =-J27 -> -8645.2403 | AE27: =SUM(Z27:AD27) -> -5754.3153 | AF27: =AG26 -> -185964.77 | AG27: =AF27+AE27 -> -191719.08
A28: =YEAR(C28) -> 2023 | B28: ="Q"&(QUOTIENT(MONTH(C28),3.1)+1) -> Q3 | C28: 45139 | D28: ='Faturamento 235'!P9+'Faturamento Itaipu'!L7+'Faturamento Icaraí'!P7 -> 3812.6327 | E28: 1700 | F28: 300 | G28: 236.27 | I28: =D28*6% -> 228.75796 | J28: =K28+L28 -> 8645.2403 | K28: =Financiamento!D37 -> 4986.9997 | L28: =Financiamento!C37 -> 3658.2406 | P28: =D28 -> 3812.6327 | Q28: =-SUM(E28:H28) -> -2236.27 | R28: =SUM(P28:Q28) -> 1576.3627 | T28: =SUM(R28:S28) -> 1576.3627 | U28: =-L28 -> -3658.2406 | V28: =SUM(T28:U28) -> -2081.8779 | W28: =-I28 -> -228.75796 | X28: =SUM(V28:W28) -> -2310.6358 | Z28: =R28 -> 1576.3627 | AA28: =W28 -> -228.75796 | AB28: =-N28 -> 0 | AC28: =M28 -> 0 | AD28: =-J28 -> -8645.2403 | AE28: =SUM(Z28:AD28) -> -7297.6356 | AF28: =AG27 -> -191719.08 | AG28: =AF28+AE28 -> -199016.72
A29: =YEAR(C29) -> 2023 | B29: ="Q"&(QUOTIENT(MONTH(C29),3.1)+1) -> Q3 | C29: 45170 | D29: ='Faturamento 235'!P10+'Faturamento Itaipu'!L8+'Faturamento Icaraí'!P8 -> 4381.9087 | F29: 300 | I29: =D29*6% -> 262.91452 | J29: =K29+L29 -> 8645.2403 | K29: =Financiamento!D38 -> 5063.7995 | L29: =Financiamento!C38 -> 3581.4408 | P29: =D29 -> 4381.9087 | Q29: =-SUM(E29:H29) -> -300 | R29: =SUM(P29:Q29) -> 4081.9087 | T29: =SUM(R29:S29) -> 4081.9087 | U29: =-L29 -> -3581.4408 | V29: =SUM(T29:U29) -> 500.46784 | W29: =-I29 -> -262.91452 | X29: =SUM(V29:W29) -> 237.55332 | Z29: =R29 -> 4081.9087 | AA29: =W29 -> -262.91452 | AB29: =-N29 -> 0 | AC29: =M29 -> 0 | AD29: =-J29 -> -8645.2403 | AE29: =SUM(Z29:AD29) -> -4826.2462 | AF29: =AG28 -> -199016.72 | AG29: =AF29+AE29 -> -203842.97
A30: =YEAR(C30) -> 2023 | B30: ="Q"&(QUOTIENT(MONTH(C30),3.1)+1) -> Q4 | C30: 45200 | D30: ='Faturamento 235'!P11+'Faturamento Itaipu'!L9+'Faturamento Icaraí'!P9 -> 4485.1539 | F30: 300 | I30: =D30*6% -> 269.10923 | J30: =K30+L30 -> 8645.2403 | K30: =Financiamento!D39 -> 5141.782 | L30: =Financiamento!C39 -> 3503.4583 | P30: =D30 -> 4485.1539 | Q30: =-SUM(E30:H30) -> -300 | R30: =SUM(P30:Q30) -> 4185.1539 | T30: =SUM(R30:S30) -> 4185.1539 | U30: =-L30 -> -3503.4583 | V30: =SUM(T30:U30) -> 681.69556 | W30: =-I30 -> -269.10923 | X30: =SUM(V30:W30) -> 412.58633 | Z30: =R30 -> 4185.1539 | AA30: =W30 -> -269.10923 | AB30: =-N30 -> 0 | AC30: =M30 -> 0 | AD30: =-J30 -> -8645.2403 | AE30: =SUM(Z30:AD30) -> -4729.1957 | AF30: =AG29 -> -203842.97 | AG30: =AF30+AE30 -> -208572.16
A31: =YEAR(C31) -> 2023 | B31: ="Q"&(QUOTIENT(MONTH(C31),3.1)+1) -> Q4 | C31: 45231 | D31: ='Faturamento 235'!P12+'Faturamento Itaipu'!L10+'Faturamento Icaraí'!P10 -> 5180.3796 | F31: 300 | I31: =D31*6% -> 310.82278 | J31: =K31+L31 -> 8645.2403 | K31: =Financiamento!D40 -> 5220.9655 | L31: =Financiamento!C40 -> 3424.2749 | P31: =D31 -> 5180.3796 | Q31: =-SUM(E31:H31) -> -300 | R31: =SUM(P31:Q31) -> 4880.3796 | T31: =SUM(R31:S31) -> 4880.3796 | U31: =-L31 -> -3424.2749 | V31: =SUM(T31:U31) -> 1456.1048 | W31: =-I31 -> -310.82278 | X31: =SUM(V31:W31) -> 1145.282 | Z31: =R31 -> 4880.3796 | AA31: =W31 -> -310.82278 | AB31: =-N31 -> 0 | AC31: =M31 -> 0 | AD31: =-J31 -> -8645.2403 | AE31: =SUM(Z31:AD31) -> -4075.6835 | AF31: =AG30 -> -208572.16 | AG31: =AF31+AE31 -> -212647.85
A32: =YEAR(C32) -> 2023 | B32: ="Q"&(QUOTIENT(MONTH(C32),3.1)+1) -> Q4 | C32: 45261 | D32: ='Faturamento 235'!P13+'Faturamento Itaipu'!L11+'Faturamento Icaraí'!P11 -> 4679.9759 | F32: 300 | G32: 1129.75 | H32: 720 | I32: =D32*6% -> 280.79855 | J32: =K32+L32 -> 8645.2403 | K32: =Financiamento!D41 -> 5301.3684 | L32: =Financiamento!C41 -> 3343.872 | P32: =D32 -> 4679.9759 | Q32: =-SUM(E32:H32) -> -2149.75 | R32: =SUM(P32:Q32) -> 2530.2259 | T32: =SUM(R32:S32) -> 2530.2259 | U32: =-L32 -> -3343.872 | V32: =SUM(T32:U32) -> -813.64614 | W32: =-I32 -> -280.79855 | X32: =SUM(V32:W32) -> -1094.4447 | Z32: =R32 -> 2530.2259 | AA32: =W32 -> -280.79855 | AB32: =-N32 -> 0 | AC32: =M32 -> 0 | AD32: =-J32 -> -8645.2403 | AE32: =SUM(Z32:AD32) -> -6395.813 | AF32: =AG31 -> -212647.85 | AG32: =AF32+AE32 -> -219043.66
A33: =YEAR(C33) -> 2024 | B33: ="Q"&(QUOTIENT(MONTH(C33),3.1)+1) -> Q1 | C33: 45292 | D33: ='Faturamento 235'!P14+'Faturamento Itaipu'!L12+'Faturamento Icaraí'!P12 -> 4204.0459 | F33: 300 | I33: =D33*6% -> 252.24275 | J33: =K33+L33 -> 8645.2403 | K33: =Financiamento!D42 -> 5383.0094 | L33: =Financiamento!C42 -> 3262.2309 | P33: =D33 -> 4204.0459 | Q33: =-SUM(E33:H33) -> -300 | R33: =SUM(P33:Q33) -> 3904.0459 | T33: =SUM(R33:S33) -> 3904.0459 | U33: =-L33 -> -3262.2309 | V33: =SUM(T33:U33) -> 641.81497 | W33: =-I33 -> -252.24275 | X33: =SUM(V33:W33) -> 389.57222 | Z33: =R33 -> 3904.0459 | AA33: =W33 -> -252.24275 | AB33: =-N33 -> 0 | AC33: =M33 -> 0 | AD33: =-J33 -> -8645.2403 | AE33: =SUM(Z33:AD33) -> -4993.4372 | AF33: =AG32 -> -219043.66 | AG33: =AF33+AE33 -> -224037.1
A34: =YEAR(C34) -> 2024 | B34: ="Q"&(QUOTIENT(MONTH(C34),3.1)+1) -> Q1 | C34: 45323 | D34: ='Faturamento 235'!P15+'Faturamento Itaipu'!L13+'Faturamento Icaraí'!P13+'Faturamento Laura Jardim'!L2 -> 5809.9943 | F34: 300 | I34: =D34*6% -> 348.59966 | J34: =K34+L34 -> 8645.2403 | K34: =Financiamento!D43 -> 5465.9078 | L34: =Financiamento!C43 -> 3179.3326 | P34: =D34 -> 5809.9943 | Q34: =-SUM(E34:H34) -> -300 | R34: =SUM(P34:Q34) -> 5509.9943 | T34: =SUM(R34:S34) -> 5509.9943 | U34: =-L34 -> -3179.3326 | V34: =SUM(T34:U34) -> 2330.6617 | W34: =-I34 -> -348.59966 | X34: =SUM(V34:W34) -> 1982.0621 | Z34: =R34 -> 5509.9943 | AA34: =W34 -> -348.59966 | AB34: =-N34 -> 0 | AC34: =M34 -> 0 | AD34: =-J34 -> -8645.2403 | AE34: =SUM(Z34:AD34) -> -3483.8457 | AF34: =AG33 -> -224037.1 | AG34: =AF34+AE34 -> -227520.94
A35: =YEAR(C35) -> 2024 | B35: ="Q"&(QUOTIENT(MONTH(C35),3.1)+1) -> Q1 | C35: 45352 | D35: ='Faturamento 235'!P16+'Faturamento Itaipu'!L14+'Faturamento Icaraí'!P14+'Faturamento Laura Jardim'!L3 -> 6923.6927 | F35: 300 | I35: =D35*6% -> 415.42156 | J35: =K35+L35 -> 8645.2403 | K35: =Financiamento!D44 -> 5550.0827 | L35: =Financiamento!C44 -> 3095.1576 | P35: =D35 -> 6923.6927 | Q35: =-SUM(E35:H35) -> -300 | R35: =SUM(P35:Q35) -> 6623.6927 | T35: =SUM(R35:S35) -> 6623.6927 | U35: =-L35 -> -3095.1576 | V35: =SUM(T35:U35) -> 3528.5351 | W35: =-I35 -> -415.42156 | X35: =SUM(V35:W35) -> 3113.1136 | Z35: =R35 -> 6623.6927 | AA35: =W35 -> -415.42156 | AB35: =-N35 -> 0 | AC35: =M35 -> 0 | AD35: =-J35 -> -8645.2403 | AE35: =SUM(Z35:AD35) -> -2436.9692 | AF35: =AG34 -> -227520.94 | AG35: =AF35+AE35 -> -229957.91
A36: =YEAR(C36) -> 2024 | B36: ="Q"&(QUOTIENT(MONTH(C36),3.1)+1) -> Q2 | C36: 45383 | D36: ='Faturamento 235'!P17+'Faturamento Itaipu'!L15+'Faturamento Icaraí'!P15+'Faturamento Laura Jardim'!L4 -> 5791.3046 | F36: 300 | I36: =D36*6% -> 347.47828 | J36: =K36+L36 -> 8645.2403 | K36: =Financiamento!D45 -> 5635.554 | L36: =Financiamento!C45 -> 3009.6863 | P36: =D36 -> 5791.3046 | Q36: =-SUM(E36:H36) -> -300 | R36: =SUM(P36:Q36) -> 5491.3046 | T36: =SUM(R36:S36) -> 5491.3046 | U36: =-L36 -> -3009.6863 | V36: =SUM(T36:U36) -> 2481.6183 | W36: =-I36 -> -347.47828 | X36: =SUM(V36:W36) -> 2134.14 | Z36: =R36 -> 5491.3046 | AA36: =W36 -> -347.47828 | AB36: =-N36 -> 0 | AC36: =M36 -> 0 | AD36: =-J36 -> -8645.2403 | AE36: =SUM(Z36:AD36) -> -3501.414 | AF36: =AG35 -> -229957.91 | AG36: =AF36+AE36 -> -233459.32
A37: =YEAR(C37) -> 2024 | B37: ="Q"&(QUOTIENT(MONTH(C37),3.1)+1) -> Q2 | C37: 45413 | D37: ='Faturamento 235'!P18+'Faturamento Itaipu'!L16+'Faturamento Icaraí'!P16+'Faturamento Laura Jardim'!L5 -> 6448.4677 | F37: 300 | H37: 754 | I37: =D37*6% -> 386.90806 | J37: =K37+L37 -> 8645.2403 | K37: =Financiamento!D46 -> 5722.3416 | L37: =Financiamento!C46 -> 2922.8988 | P37: =D37 -> 6448.4677 | Q37: =-SUM(E37:H37) -> -1054 | R37: =SUM(P37:Q37) -> 5394.4677 | T37: =SUM(R37:S37) -> 5394.4677 | U37: =-L37 -> -2922.8988 | V37: =SUM(T37:U37) -> 2471.5689 | W37: =-I37 -> -386.90806 | X37: =SUM(V37:W37) -> 2084.6608 | Z37: =R37 -> 5394.4677 | AA37: =W37 -> -386.90806 | AB37: =-N37 -> 0 | AC37: =M37 -> 0 | AD37: =-J37 -> -8645.2403 | AE37: =SUM(Z37:AD37) -> -3637.6807 | AF37: =AG36 -> -233459.32 | AG37: =AF37+AE37 -> -237097.01
A38: =YEAR(C38) -> 2024 | B38: ="Q"&(QUOTIENT(MONTH(C38),3.1)+1) -> Q2 | C38: 45444 | D38: ='Faturamento 235'!P19+'Faturamento Itaipu'!L17+'Faturamento Icaraí'!P17+'Faturamento Laura Jardim'!L6 -> 4421.3115 | F38: 300 | I38: =D38*6% -> 265.27869 | J38: =K38+L38 -> 8645.2403 | K38: =Financiamento!D47 -> 5810.4656 | L38: =Financiamento!C47 -> 2834.7747 | P38: =D38 -> 4421.3115 | Q38: =-SUM(E38:H38) -> -300 | R38: =SUM(P38:Q38) -> 4121.3115 | T38: =SUM(R38:S38) -> 4121.3115 | U38: =-L38 -> -2834.7747 | V38: =SUM(T38:U38) -> 1286.5367 | W38: =-I38 -> -265.27869 | X38: =SUM(V38:W38) -> 1021.258 | Z38: =R38 -> 4121.3115 | AA38: =W38 -> -265.27869 | AB38: =-N38 -> 0 | AC38: =M38 -> 0 | AD38: =-J38 -> -8645.2403 | AE38: =SUM(Z38:AD38) -> -4789.2076 | AF38: =AG37 -> -237097.01 | AG38: =AF38+AE38 -> -241886.21
A39: =YEAR(C39) -> 2024 | B39: ="Q"&(QUOTIENT(MONTH(C39),3.1)+1) -> Q3 | C39: 45474 | D39: ='Faturamento 235'!P20+'Faturamento Itaipu'!L18+'Faturamento Icaraí'!P18+'Faturamento Laura Jardim'!L7 -> 3192.3306 | F39: 300 | I39: =D39*6% -> 191.53984 | J39: =K39+L39 -> 8645.2403 | K39: =Financiamento!D48 -> 5899.9468 | L39: =Financiamento!C48 -> 2745.2936 | P39: =D39 -> 3192.3306 | Q39: =-SUM(E39:H39) -> -300 | R39: =SUM(P39:Q39) -> 2892.3306 | T39: =SUM(R39:S39) -> 2892.3306 | U39: =-L39 -> -2745.2936 | V39: =SUM(T39:U39) -> 147.03709 | W39: =-I39 -> -191.53984 | X39: =SUM(V39:W39) -> -44.502746 | Z39: =R39 -> 2892.3306 | AA39: =W39 -> -191.53984 | AB39: =-N39 -> 0 | AC39: =M39 -> 0 | AD39: =-J39 -> -8645.2403 | AE39: =SUM(Z39:AD39) -> -5944.4495 | AF39: =AG38 -> -241886.21 | AG39: =AF39+AE39 -> -247830.66
A40: =YEAR(C40) -> 2024 | B40: ="Q"&(QUOTIENT(MONTH(C40),3.1)+1) -> Q3 | C40: 45505 | D40: ='Faturamento 235'!P21+'Faturamento Itaipu'!L19+'Faturamento Icaraí'!P19+'Faturamento Laura Jardim'!L8+'Faturamento Essencial'!L4 -> 4415.5447 | F40: 300 | I40: =D40*6% -> 264.93268 | J40: =K40+L40 -> 8645.2403 | K40: =Financiamento!D49 -> 5990.806 | L40: =Financiamento!C49 -> 2654.4344 | P40: =D40 -> 4415.5447 | Q40: =-SUM(E40:H40) -> -300 | R40: =SUM(P40:Q40) -> 4115.5447 | T40: =SUM(R40:S40) -> 4115.5447 | U40: =-L40 -> -2654.4344 | V40: =SUM(T40:U40) -> 1461.1103 | W40: =-I40 -> -264.93268 | X40: =SUM(V40:W40) -> 1196.1776 | Z40: =R40 -> 4115.5447 | AA40: =W40 -> -264.93268 | AB40: =-N40 -> 0 | AC40: =M40 -> 0 | AD40: =-J40 -> -8645.2403 | AE40: =SUM(Z40:AD40) -> -4794.6283 | AF40: =AG39 -> -247830.66 | AG40: =AF40+AE40 -> -252625.29
A41: =YEAR(C41) -> 2024 | B41: ="Q"&(QUOTIENT(MONTH(C41),3.1)+1) -> Q3 | C41: 45536 | D41: ='Faturamento 235'!P22+'Faturamento Itaipu'!L20+'Faturamento Icaraí'!P20+'Faturamento Laura Jardim'!L9+'Faturamento Essencial'!L5 -> 6035.7282 | F41: 300 | I41: =D41*6% -> 362.14369 | J41: =K41+L41 -> 8645.2403 | K41: =Financiamento!D50 -> 6083.0644 | L41: =Financiamento!C50 -> 2562.176 | P41: =D41 -> 6035.7282 | Q41: =-SUM(E41:H41) -> -300 | R41: =SUM(P41:Q41) -> 5735.7282 | T41: =SUM(R41:S41) -> 5735.7282 | U41: =-L41 -> -2562.176 | V41: =SUM(T41:U41) -> 3173.5523 | W41: =-I41 -> -362.14369 | X41: =SUM(V41:W41) -> 2811.4086 | Z41: =R41 -> 5735.7282 | AA41: =W41 -> -362.14369 | AB41: =-N41 -> 0 | AC41: =M41 -> 0 | AD41: =-J41 -> -8645.2403 | AE41: =SUM(Z41:AD41) -> -3271.6558 | AF41: =AG40 -> -252625.29 | AG41: =AF41+AE41 -> -255896.95
A42: =YEAR(C42) -> 2024 | B42: ="Q"&(QUOTIENT(MONTH(C42),3.1)+1) -> Q4 | C42: 45566 | D42: ='Faturamento 235'!P23+'Faturamento Itaipu'!L21+'Faturamento Icaraí'!P21+'Faturamento Laura Jardim'!L10+'Faturamento Essencial'!L6 -> 5693.1627 | F42: 300 | I42: =D42*6% -> 341.58976 | J42: =K42+L42 -> 8645.2403 | K42: =Financiamento!D51 -> 6176.7436 | L42: =Financiamento!C51 -> 2468.4968 | P42: =D42 -> 5693.1627 | Q42: =-SUM(E42:H42) -> -300 | R42: =SUM(P42:Q42) -> 5393.1627 | T42: =SUM(R42:S42) -> 5393.1627 | U42: =-L42 -> -2468.4968 | V42: =SUM(T42:U42) -> 2924.666 | W42: =-I42 -> -341.58976 | X42: =SUM(V42:W42) -> 2583.0762 | Z42: =R42 -> 5393.1627 | AA42: =W42 -> -341.58976 | AB42: =-N42 -> 0 | AC42: =M42 -> 0 | AD42: =-J42 -> -8645.2403 | AE42: =SUM(Z42:AD42) -> -3593.6674 | AF42: =AG41 -> -255896.95 | AG42: =AF42+AE42 -> -259490.61
A43: =YEAR(C43) -> 2024 | B43: ="Q"&(QUOTIENT(MONTH(C43),3.1)+1) -> Q4 | C43: 45597 | D43: ='Faturamento 235'!P24+'Faturamento Itaipu'!L22+'Faturamento Icaraí'!P22+'Faturamento Laura Jardim'!L11+'Faturamento Essencial'!L7+'Faturamento 281'!N24 -> 8410.5282 | F43: 300 | I43: =D43*6% -> 504.63169 | J43: =K43+L43 -> 8645.2403 | K43: =Financiamento!D52 -> 6271.8654 | L43: =Financiamento!C52 -> 2373.3749 | P43: =D43 -> 8410.5282 | Q43: =-SUM(E43:H43) -> -300 | R43: =SUM(P43:Q43) -> 8110.5282 | T43: =SUM(R43:S43) -> 8110.5282 | U43: =-L43 -> -2373.3749 | V43: =SUM(T43:U43) -> 5737.1533 | W43: =-I43 -> -504.63169 | X43: =SUM(V43:W43) -> 5232.5216 | Z43: =R43 -> 8110.5282 | AA43: =W43 -> -504.63169 | AB43: =-N43 -> 0 | AC43: =M43 -> 0 | AD43: =-J43 -> -8645.2403 | AE43: =SUM(Z43:AD43) -> -1039.3438 | AF43: =AG42 -> -259490.61 | AG43: =AF43+AE43 -> -260529.96
A44: =YEAR(C44) -> 2024 | B44: ="Q"&(QUOTIENT(MONTH(C44),3.1)+1) -> Q4 | C44: 45627 | D44: ='Faturamento 235'!P25+'Faturamento Itaipu'!L23+'Faturamento Icaraí'!P23+'Faturamento Laura Jardim'!L12+'Faturamento Essencial'!L8+'Faturamento 281'!N25 -> 6666.4636 | F44: 300 | I44: =D44*6% -> 399.98782 | J44: =K44+L44 -> 8645.2403 | K44: =Financiamento!D53 -> 6368.4521 | L44: =Financiamento!C53 -> 2276.7882 | P44: =D44 -> 6666.4636 | Q44: =-SUM(E44:H44) -> -300 | R44: =SUM(P44:Q44) -> 6366.4636 | T44: =SUM(R44:S44) -> 6366.4636 | U44: =-L44 -> -2276.7882 | V44: =SUM(T44:U44) -> 4089.6754 | W44: =-I44 -> -399.98782 | X44: =SUM(V44:W44) -> 3689.6876 | Z44: =R44 -> 6366.4636 | AA44: =W44 -> -399.98782 | AB44: =-N44 -> 0 | AC44: =M44 -> 0 | AD44: =-J44 -> -8645.2403 | AE44: =SUM(Z44:AD44) -> -2678.7645 | AF44: =AG43 -> -260529.96 | AG44: =AF44+AE44 -> -263208.72
A45: =YEAR(C45) -> 2025 | B45: ="Q"&(QUOTIENT(MONTH(C45),3.1)+1) -> Q1 | C45: 45658 | D45: ='Faturamento 235'!P26+'Faturamento Itaipu'!L24+'Faturamento Icaraí'!P24+'Faturamento Laura Jardim'!L13+'Faturamento Essencial'!L9+'Faturamento 281'!N26 -> 7369.6552 | F45: 300 | I45: =D45*6% -> 442.17931 | J45: =K45+L45 -> 8645.2403 | K45: =Financiamento!D54 -> 6466.5263 | L45: =Financiamento!C54 -> 2178.714 | P45: =D45 -> 7369.6552 | Q45: =-SUM(E45:H45) -> -300 | R45: =SUM(P45:Q45) -> 7069.6552 | T45: =SUM(R45:S45) -> 7069.6552 | U45: =-L45 -> -2178.714 | V45: =SUM(T45:U45) -> 4890.9412 | W45: =-I45 -> -442.17931 | X45: =SUM(V45:W45) -> 4448.7618 | Z45: =R45 -> 7069.6552 | AA45: =W45 -> -442.17931 | AB45: =-N45 -> 0 | AC45: =M45 -> 0 | AD45: =-J45 -> -8645.2403 | AE45: =SUM(Z45:AD45) -> -2017.7645 | AF45: =AG44 -> -263208.72 | AG45: =AF45+AE45 -> -265226.49
A46: =YEAR(C46) -> 2025 | B46: ="Q"&(QUOTIENT(MONTH(C46),3.1)+1) -> Q1 | C46: 45689 | D46: ='Faturamento 235'!P27+'Faturamento Itaipu'!L25+'Faturamento Icaraí'!P25+'Faturamento Laura Jardim'!L14+'Faturamento Essencial'!L10+'Faturamento 281'!N27 -> 9711.5085 | F46: 300 | I46: =D46*6% -> 582.69051 | J46: =K46+L46 -> 8645.2403 | K46: =Financiamento!D55 -> 6566.1108 | L46: =Financiamento!C55 -> 2079.1295 | P46: =D46 -> 9711.5085 | Q46: =-SUM(E46:H46) -> -300 | R46: =SUM(P46:Q46) -> 9411.5085 | T46: =SUM(R46:S46) -> 9411.5085 | U46: =-L46 -> -2079.1295 | V46: =SUM(T46:U46) -> 7332.379 | W46: =-I46 -> -582.69051 | X46: =SUM(V46:W46) -> 6749.6885 | Z46: =R46 -> 9411.5085 | AA46: =W46 -> -582.69051 | AB46: =-N46 -> 0 | AC46: =M46 -> 0 | AD46: =-J46 -> -8645.2403 | AE46: =SUM(Z46:AD46) -> 183.57764 | AF46: =AG45 -> -265226.49 | AG46: =AF46+AE46 -> -265042.91
A47: =YEAR(C47) -> 2025 | B47: ="Q"&(QUOTIENT(MONTH(C47),3.1)+1) -> Q1 | C47: 45717 | D47: ='Faturamento 235'!P28+'Faturamento Itaipu'!L26+'Faturamento Icaraí'!P26+'Faturamento Laura Jardim'!L15+'Faturamento Essencial'!L11+'Faturamento 281'!N28 -> 8151.3258 | F47: 300 | I47: =D47*6% -> 489.07955 | J47: =K47+L47 -> 8645.2403 | K47: =Financiamento!D56 -> 6667.2289 | L47: =Financiamento!C56 -> 1978.0114 | P47: =D47 -> 8151.3258 | Q47: =-SUM(E47:H47) -> -300 | R47: =SUM(P47:Q47) -> 7851.3258 | T47: =SUM(R47:S47) -> 7851.3258 | U47: =-L47 -> -1978.0114 | V47: =SUM(T47:U47) -> 5873.3143 | W47: =-I47 -> -489.07955 | X47: =SUM(V47:W47) -> 5384.2348 | Z47: =R47 -> 7851.3258 | AA47: =W47 -> -489.07955 | AB47: =-N47 -> 0 | AC47: =M47 -> 0 | AD47: =-J47 -> -8645.2403 | AE47: =SUM(Z47:AD47) -> -1282.9941 | AF47: =AG46 -> -265042.91 | AG47: =AF47+AE47 -> -266325.9
A48: =YEAR(C48) -> 2025 | B48: ="Q"&(QUOTIENT(MONTH(C48),3.1)+1) -> Q2 | C48: 45748 | D48: ='Faturamento 235'!P29+'Faturamento Itaipu'!L27+'Faturamento Icaraí'!P27+'Faturamento Laura Jardim'!L16+'Faturamento Essencial'!L12+'Faturamento 281'!N29 -> 4025.7988 | F48: 300 | I48: =D48*6% -> 241.54793 | J48: =K48+L48 -> 8645.2403 | K48: =Financiamento!D57 -> 6769.9042 | L48: =Financiamento!C57 -> 1875.3361 | P48: =D48 -> 4025.7988 | Q48: =-SUM(E48:H48) -> -300 | R48: =SUM(P48:Q48) -> 3725.7988 | T48: =SUM(R48:S48) -> 3725.7988 | U48: =-L48 -> -1875.3361 | V48: =SUM(T48:U48) -> 1850.4627 | W48: =-I48 -> -241.54793 | X48: =SUM(V48:W48) -> 1608.9148 | Z48: =R48 -> 3725.7988 | AA48: =W48 -> -241.54793 | AB48: =-N48 -> 0 | AC48: =M48 -> 0 | AD48: =-J48 -> -8645.2403 | AE48: =SUM(Z48:AD48) -> -5160.9894 | AF48: =AG47 -> -266325.9 | AG48: =AF48+AE48 -> -271486.89
A49: =YEAR(C49) -> 2025 | B49: ="Q"&(QUOTIENT(MONTH(C49),3.1)+1) -> Q2 | C49: 45778 | D49: ='Faturamento 235'!P30+'Faturamento Itaipu'!L28+'Faturamento Icaraí'!P28+'Faturamento Laura Jardim'!L17+'Faturamento Essencial'!L13+'Faturamento 281'!N30 -> 5868.5959 | F49: 300 | I49: =D49*6% -> 352.11575 | J49: =K49+L49 -> 8645.2403 | K49: =Financiamento!D58 -> 6874.1608 | L49: =Financiamento!C58 -> 1771.0796 | P49: =D49 -> 5868.5959 | Q49: =-SUM(E49:H49) -> -300 | R49: =SUM(P49:Q49) -> 5568.5959 | T49: =SUM(R49:S49) -> 5568.5959 | U49: =-L49 -> -1771.0796 | V49: =SUM(T49:U49) -> 3797.5163 | W49: =-I49 -> -352.11575 | X49: =SUM(V49:W49) -> 3445.4006 | Z49: =R49 -> 5568.5959 | AA49: =W49 -> -352.11575 | AB49: =-N49 -> 0 | AC49: =M49 -> 0 | AD49: =-J49 -> -8645.2403 | AE49: =SUM(Z49:AD49) -> -3428.7602 | AF49: =AG48 -> -271486.89 | AG49: =AF49+AE49 -> -274915.65
A50: =YEAR(C50) -> 2025 | B50: ="Q"&(QUOTIENT(MONTH(C50),3.1)+1) -> Q2 | C50: 45809 | D50: ='Faturamento 235'!P31+'Faturamento Itaipu'!L29+'Faturamento Icaraí'!P29+'Faturamento Laura Jardim'!L18+'Faturamento Essencial'!L14+'Faturamento 281'!N31 -> 6262.4166 | F50: 300 | I50: =D50*6% -> 375.74499 | J50: =K50+L50 -> 8645.2403 | K50: =Financiamento!D59 -> 6980.0229 | L50: =Financiamento!C59 -> 1665.2175 | P50: =D50 -> 6262.4166 | Q50: =-SUM(E50:H50) -> -300 | R50: =SUM(P50:Q50) -> 5962.4166 | T50: =SUM(R50:S50) -> 5962.4166 | U50: =-L50 -> -1665.2175 | V50: =SUM(T50:U50) -> 4297.1991 | W50: =-I50 -> -375.74499 | X50: =SUM(V50:W50) -> 3921.4541 | Z50: =R50 -> 5962.4166 | AA50: =W50 -> -375.74499 | AB50: =-N50 -> 0 | AC50: =M50 -> 0 | AD50: =-J50 -> -8645.2403 | AE50: =SUM(Z50:AD50) -> -3058.5688 | AF50: =AG49 -> -274915.65 | AG50: =AF50+AE50 -> -277974.22
A51: =YEAR(C51) -> 2025 | B51: ="Q"&(QUOTIENT(MONTH(C51),3.1)+1) -> Q3 | C51: 45839 | D51: ='Faturamento 235'!P32+'Faturamento Itaipu'!L30+'Faturamento Icaraí'!P30+'Faturamento Laura Jardim'!L19+'Faturamento Essencial'!L15+'Faturamento 281'!N32 -> 6013.1159 | F51: 300 | I51: =D51*6% -> 360.78695 | J51: =K51+L51 -> 8645.2403 | K51: =Financiamento!D60 -> 7087.5152 | L51: =Financiamento!C60 -> 1557.7251 | P51: =D51 -> 6013.1159 | Q51: =-SUM(E51:H51) -> -300 | R51: =SUM(P51:Q51) -> 5713.1159 | T51: =SUM(R51:S51) -> 5713.1159 | U51: =-L51 -> -1557.7251 | V51: =SUM(T51:U51) -> 4155.3907 | W51: =-I51 -> -360.78695 | X51: =SUM(V51:W51) -> 3794.6038 | Z51: =R51 -> 5713.1159 | AA51: =W51 -> -360.78695 | AB51: =-N51 -> 0 | AC51: =M51 -> 0 | AD51: =-J51 -> -8645.2403 | AE51: =SUM(Z51:AD51) -> -3292.9114 | AF51: =AG50 -> -277974.22 | AG51: =AF51+AE51 -> -281267.13
A52: =YEAR(C52) -> 2025 | B52: ="Q"&(QUOTIENT(MONTH(C52),3.1)+1) -> Q3 | C52: 45870 | D52: ='Faturamento 235'!P33+'Faturamento Itaipu'!L31+'Faturamento Icaraí'!P31+'Faturamento Laura Jardim'!L20+'Faturamento Essencial'!L16+'Faturamento 281'!N33 -> 6234.2217 | F52: 300 | I52: =D52*6% -> 374.0533 | J52: =K52+L52 -> 8645.2403 | K52: =Financiamento!D61 -> 7196.6629 | L52: =Financiamento!C61 -> 1448.5774 | P52: =D52 -> 6234.2217 | Q52: =-SUM(E51:H51) -> -300 | R52: =SUM(P52:Q52) -> 5934.2217 | T52: =SUM(R52:S52) -> 5934.2217 | U52: =-L51 -> -1557.7251 | V52: =SUM(T52:U52) -> 4376.4965 | W52: =-I51 -> -360.78695 | X52: =SUM(V52:W52) -> 4015.7096 | Z52: =R52 -> 5934.2217 | AA52: =W52 -> -360.78695 | AB52: =-N51 -> 0 | AC52: =M52 -> 0 | AD52: =-J51 -> -8645.2403 | AE52: =SUM(Z52:AD52) -> -3071.8056 | AF52: =AG51 -> -281267.13 | AG52: =AF52+AE52 -> -284338.94
A53: =YEAR(C53) -> 2025 | B53: ="Q"&(QUOTIENT(MONTH(C53),3.1)+1) -> Q3 | C53: 45901 | D53: ='Faturamento 235'!P34+'Faturamento Itaipu'!L32+'Faturamento Icaraí'!P32+'Faturamento Laura Jardim'!L21+'Faturamento Essencial'!L17+'Faturamento 281'!N34 -> 9274.0665 | F53: 300 | I53: =D53*6% -> 556.44399 | J53: =K53+L53 -> 8645.2403 | K53: =Financiamento!D62 -> 7307.4915 | L53: =Financiamento!C62 -> 1337.7488 | P53: =D53 -> 9274.0665 | Q53: =-SUM(E51:H51) -> -300 | R53: =SUM(P53:Q53) -> 8974.0665 | T53: =SUM(R53:S53) -> 8974.0665 | U53: =-L51 -> -1557.7251 | V53: =SUM(T53:U53) -> 7416.3414 | W53: =-I51 -> -360.78695 | X53: =SUM(V53:W53) -> 7055.5544 | Z53: =R53 -> 8974.0665 | AA53: =W53 -> -360.78695 | AB53: =-N51 -> 0 | AC53: =M53 -> 0 | AD53: =-J51 -> -8645.2403 | AE53: =SUM(Z53:AD53) -> -31.960785 | AF53: =AG52 -> -284338.94 | AG53: =AF53+AE53 -> -284370.9
A54: =YEAR(C54) -> 2025 | B54: ="Q"&(QUOTIENT(MONTH(C54),3.1)+1) -> Q4 | C54: 45931 | D54: ='Faturamento 235'!P35+'Faturamento Itaipu'!L33+'Faturamento Icaraí'!P33+'Faturamento Laura Jardim'!L22+'Faturamento Essencial'!L18+'Faturamento 281'!N35 -> 6975.2469 | F54: 300 | I54: =D54*6% -> 418.51481 | J54: =K54+L54 -> 8645.2403 | K54: =Financiamento!D63 -> 7420.0269 | L54: =Financiamento!C63 -> 1225.2134 | P54: =D54 -> 6975.2469 | Q54: =-SUM(E51:H51) -> -300 | R54: =SUM(P54:Q54) -> 6675.2469 | T54: =SUM(R54:S54) -> 6675.2469 | U54: =-L51 -> -1557.7251 | V54: =SUM(T54:U54) -> 5117.5217 | W54: =-I51 -> -360.78695 | X54: =SUM(V54:W54) -> 4756.7348 | Z54: =R54 -> 6675.2469 | AA54: =W54 -> -360.78695 | AB54: =-N51 -> 0 | AC54: =M54 -> 0 | AD54: =-J51 -> -8645.2403 | AE54: =SUM(Z54:AD54) -> -2330.7804 | AF54: =AG53 -> -284370.9 | AG54: =AF54+AE54 -> -286701.68
A55: =YEAR(C55) -> 2025 | B55: ="Q"&(QUOTIENT(MONTH(C55),3.1)+1) -> Q4 | C55: 45962 | D55: ='Faturamento 235'!P36+'Faturamento Itaipu'!L34+'Faturamento Icaraí'!P34+'Faturamento Laura Jardim'!L23+'Faturamento Essencial'!L19+'Faturamento 281'!N36 -> 8258.9165 | F55: 300 | I55: =D55*6% -> 495.53499 | J55: =K55+L55 -> 8645.2403 | K55: =Financiamento!D64 -> 7534.2953 | L55: =Financiamento!C64 -> 1110.945 | P55: =D55 -> 8258.9165 | Q55: =-SUM(E51:H51) -> -300 | R55: =SUM(P55:Q55) -> 7958.9165 | T55: =SUM(R55:S55) -> 7958.9165 | U55: =-L51 -> -1557.7251 | V55: =SUM(T55:U55) -> 6401.1913 | W55: =-I51 -> -360.78695 | X55: =SUM(V55:W55) -> 6040.4044 | Z55: =R55 -> 7958.9165 | AA55: =W55 -> -360.78695 | AB55: =-N51 -> 0 | AC55: =M55 -> 0 | AD55: =-J51 -> -8645.2403 | AE55: =SUM(Z55:AD55) -> -1047.1108 | AF55: =AG54 -> -286701.68 | AG55: =AF55+AE55 -> -287748.79
A56: =YEAR(C56) -> 2025 | B56: ="Q"&(QUOTIENT(MONTH(C56),3.1)+1) -> Q4 | C56: 45992 | D56: ='Faturamento 235'!P37+'Faturamento Itaipu'!L35+'Faturamento Icaraí'!P35+'Faturamento Laura Jardim'!L24+'Faturamento Essencial'!L20+'Faturamento 281'!N37 -> 9620.5779 | F56: 300 | I56: =D56*6% -> 577.23467 | J56: =K56+L56 -> 8645.2403 | K56: =Financiamento!D65 -> 7650.3235 | L56: =Financiamento!C65 -> 994.91686 | P56: =D56 -> 9620.5779 | Q56: =-SUM(E51:H51) -> -300 | R56: =SUM(P56:Q56) -> 9320.5779 | T56: =SUM(R56:S56) -> 9320.5779 | U56: =-L51 -> -1557.7251 | V56: =SUM(T56:U56) -> 7762.8527 | W56: =-I51 -> -360.78695 | X56: =SUM(V56:W56) -> 7402.0658 | Z56: =R56 -> 9320.5779 | AA56: =W56 -> -360.78695 | AB56: =-N51 -> 0 | AC56: =M56 -> 0 | AD56: =-J51 -> -8645.2403 | AE56: =SUM(Z56:AD56) -> 314.55059 | AF56: =AG55 -> -287748.79 | AG56: =AF56+AE56 -> -287434.24
A57: =YEAR(C57) -> 2026 | B57: ="Q"&(QUOTIENT(MONTH(C57),3.1)+1) -> Q1 | C57: 46023 | D57: ='Faturamento 235'!P38+'Faturamento Itaipu'!L36+'Faturamento Icaraí'!P36+'Faturamento Laura Jardim'!L25+'Faturamento Essencial'!L21+'Faturamento 281'!N38 -> 9504.8005 | F57: 300 | I57: =D57*6% -> 570.28803 | J57: =K57+L57 -> 8645.2403 | K57: =Financiamento!D66 -> 7768.1385 | L57: =Financiamento!C66 -> 877.10188 | P57: =D57 -> 9504.8005 | Q57: =-SUM(E51:H51) -> -300 | R57: =SUM(P57:Q57) -> 9204.8005 | T57: =SUM(R57:S57) -> 9204.8005 | U57: =-L51 -> -1557.7251 | V57: =SUM(T57:U57) -> 7647.0754 | W57: =-I51 -> -360.78695 | X57: =SUM(V57:W57) -> 7286.2884 | Z57: =R57 -> 9204.8005 | AA57: =W57 -> -360.78695 | AB57: =-N51 -> 0 | AC57: =M57 -> 0 | AD57: =-J51 -> -8645.2403 | AE57: =SUM(Z57:AD57) -> 198.77324 | AF57: =AG56 -> -287434.24 | AG57: =AF57+AE57 -> -287235.47
A58: =YEAR(C58) -> 2026 | B58: ="Q"&(QUOTIENT(MONTH(C58),3.1)+1) -> Q1 | C58: 46054 | D58: ='Faturamento 235'!P39+'Faturamento Itaipu'!L37+'Faturamento Icaraí'!P37+'Faturamento Laura Jardim'!L26+'Faturamento Essencial'!L22+'Faturamento 281'!N39 -> 6937.4225 | F58: 300 | I58: =D58*6% -> 416.24535 | J58: =K58+L58 -> 8645.2403 | K58: =Financiamento!D67 -> 7887.7678 | L58: =Financiamento!C67 -> 757.47255 | P58: =D58 -> 6937.4225 | Q58: =-SUM(E51:H51) -> -300 | R58: =SUM(P58:Q58) -> 6637.4225 | T58: =SUM(R58:S58) -> 6637.4225 | U58: =-L51 -> -1557.7251 | V58: =SUM(T58:U58) -> 5079.6974 | W58: =-I51 -> -360.78695 | X58: =SUM(V58:W58) -> 4718.9104 | Z58: =R58 -> 6637.4225 | AA58: =W58 -> -360.78695 | AB58: =-N51 -> 0 | AC58: =M58 -> 0 | AD58: =-J51 -> -8645.2403 | AE58: =SUM(Z58:AD58) -> -2368.6048 | AF58: =AG57 -> -287235.47 | AG58: =AF58+AE58 -> -289604.07
A59: =YEAR(C59) -> 2026 | B59: ="Q"&(QUOTIENT(MONTH(C59),3.1)+1) -> Q1 | C59: 46082 | D59: ='Faturamento 235'!P40+'Faturamento Itaipu'!L38+'Faturamento Icaraí'!P38+'Faturamento Laura Jardim'!L27+'Faturamento Essencial'!L23+'Faturamento 281'!N40 -> 8057.9808 | F59: 300 | I59: =D59*6% -> 483.47885 | J59: =K59+L59 -> 8645.2403 | K59: =Financiamento!D68 -> 8009.2394 | L59: =Financiamento!C68 -> 636.00093 | P59: =D59 -> 8057.9808 | Q59: =-SUM(E52:H52) -> -300 | R59: =SUM(P59:Q59) -> 7757.9808 | T59: =SUM(R59:S59) -> 7757.9808 | U59: =-L52 -> -1448.5774 | V59: =SUM(T59:U59) -> 6309.4034 | W59: =-I52 -> -374.0533 | X59: =SUM(V59:W59) -> 5935.3501 | Z59: =R59 -> 7757.9808 | AA59: =W59 -> -374.0533 | AB59: =-N52 -> 0 | AC59: =M59 -> 0 | AD59: =-J52 -> -8645.2403 | AE59: =SUM(Z59:AD59) -> -1261.3129 | AF59: =AG58 -> -289604.07 | AG59: =AF59+AE59 -> -290865.38
A60: =YEAR(C60) -> 2026 | B60: ="Q"&(QUOTIENT(MONTH(C60),3.1)+1) -> Q2 | C60: 46113 | D60: ='Faturamento 235'!P41+'Faturamento Itaipu'!L39+'Faturamento Icaraí'!P39+'Faturamento Laura Jardim'!L28+'Faturamento Essencial'!L24+'Faturamento 281'!N41 -> 8785.963 | F60: 300 | I60: =D60*6% -> 527.15778 | J60: =K60+L60 -> 8645.2403 | K60: =Financiamento!D69 -> 8132.5817 | L60: =Financiamento!C69 -> 512.65864 | P60: =D60 -> 8785.963 | Q60: =-SUM(E53:H53) -> -300 | R60: =SUM(P60:Q60) -> 8485.963 | T60: =SUM(R60:S60) -> 8485.963 | U60: =-L53 -> -1337.7488 | V60: =SUM(T60:U60) -> 7148.2142 | W60: =-I53 -> -556.44399 | X60: =SUM(V60:W60) -> 6591.7702 | Z60: =R60 -> 8485.963 | AA60: =W60 -> -556.44399 | AB60: =-N53 -> 0 | AC60: =M60 -> 0 | AD60: =-J53 -> -8645.2403 | AE60: =SUM(Z60:AD60) -> -715.72137 | AF60: =AG59 -> -290865.38 | AG60: =AF60+AE60 -> -291581.11
A61: =YEAR(C61) -> 2026 | B61: ="Q"&(QUOTIENT(MONTH(C61),3.1)+1) -> Q2 | C61: 46143 | D61: ='Faturamento 235'!P42+'Faturamento Itaipu'!L40+'Faturamento Icaraí'!P40+'Faturamento Laura Jardim'!L29+'Faturamento Essencial'!L25+'Faturamento 281'!N42 -> 7035.692 | F61: 300 | I61: =D61*6% -> 422.14152 | J61: =K61+L61 -> 8645.2403 | K61: =Financiamento!D70 -> 8257.8235 | L61: =Financiamento!C70 -> 387.41688 | P61: =D61 -> 7035.692 | Q61: =-SUM(E54:H54) -> -300 | R61: =SUM(P61:Q61) -> 6735.692 | T61: =SUM(R61:S61) -> 6735.692 | U61: =-L54 -> -1225.2134 | V61: =SUM(T61:U61) -> 5510.4785 | W61: =-I54 -> -418.51481 | X61: =SUM(V61:W61) -> 5091.9637 | Z61: =R61 -> 6735.692 | AA61: =W61 -> -418.51481 | AB61: =-N54 -> 0 | AC61: =M61 -> 0 | AD61: =-J54 -> -8645.2403 | AE61: =SUM(Z61:AD61) -> -2328.0632 | AF61: =AG60 -> -291581.11 | AG61: =AF61+AE61 -> -293909.17
A62: =YEAR(C62) -> 2026 | B62: ="Q"&(QUOTIENT(MONTH(C62),3.1)+1) -> Q2 | C62: 46174 | D62: ='Faturamento 235'!P43+'Faturamento Itaipu'!L41+'Faturamento Icaraí'!P41+'Faturamento Laura Jardim'!L30+'Faturamento Essencial'!L26+'Faturamento 281'!N43 -> 3518.3935 | F62: 300 | I62: =D62*6% -> 211.10361 | J62: =K62+L62 -> 8645.2403 | K62: =Financiamento!D71 -> 8384.9939 | L62: =Financiamento!C71 -> 260.2464 | P62: =D62 -> 3518.3935 | Q62: =-SUM(E55:H55) -> -300 | R62: =SUM(P62:Q62) -> 3218.3935 | T62: =SUM(R62:S62) -> 3218.3935 | U62: =-L55 -> -1110.945 | V62: =SUM(T62:U62) -> 2107.4484 | W62: =-I55 -> -495.53499 | X62: =SUM(V62:W62) -> 1611.9135 | Z62: =R62 -> 3218.3935 | AA62: =W62 -> -495.53499 | AB62: =-N55 -> 0 | AC62: =M62 -> 0 | AD62: =-J55 -> -8645.2403 | AE62: =SUM(Z62:AD62) -> -5922.3819 | AF62: =AG61 -> -293909.17 | AG62: =AF62+AE62 -> -299831.55
A63: =YEAR(C63) -> 2026 | B63: ="Q"&(QUOTIENT(MONTH(C63),3.1)+1) -> Q3 | C63: 46204 | D63: ='Faturamento 235'!P44+'Faturamento Itaipu'!L42+'Faturamento Icaraí'!P42+'Faturamento Laura Jardim'!L31+'Faturamento Essencial'!L27+'Faturamento 281'!N44 -> 4580.2315 | F63: 300 | I63: =D63*6% -> 274.81389 | J63: =K63+L63 -> 8645.2403 | K63: =Financiamento!D72 -> 8514.1228 | L63: =Financiamento!C72 -> 131.11749 | P63: =D63 -> 4580.2315 | Q63: =-SUM(E56:H56) -> -300 | R63: =SUM(P63:Q63) -> 4280.2315 | T63: =SUM(R63:S63) -> 4280.2315 | U63: =-L56 -> -994.91686 | V63: =SUM(T63:U63) -> 3285.3146 | W63: =-I56 -> -577.23467 | X63: =SUM(V63:W63) -> 2708.0799 | Z63: =R63 -> 4280.2315 | AA63: =W63 -> -577.23467 | AB63: =-N56 -> 0 | AC63: =M63 -> 0 | AD63: =-J56 -> -8645.2403 | AE63: =SUM(Z63:AD63) -> -4942.2435 | AF63: =AG62 -> -299831.55 | AG63: =AF63+AE63 -> -304773.79

Sheet Projeção
A1: Fluxos de caixa | Q1: DRE | AA1: Fluxo de caixa
C2: Categoria | D2: Receita de vendas | E2: Receita de vendas | F2: Despesa com serviço de terceiros | G2: Despesa administrativa | H2: Despesa administrativa | I2: Despesa administrativa | J2: IRPJ | M2: Despesa financeira | N2: Captações de empréstimo | O2: Aquisição de ativos | AA2: Fluxo de caixa operacional | AB2: Fluxo de caixa investimento | AC2: Fluxo de caixa de financiamento | AD2: Fluxo de caixa de financiamento | AE2: Caixa | AF2: Caixa | AG2: Caixa
C3: Item | D3: Consórcio Zetawatts | E3: BOT P Kennedy | F3: Limpeza das placas | G3: Contador | H3: Alvará | I3: JUCERJA | J3: Simples | K3: Parcela do empréstimo | L3: Amortização do empréstimo | M3: Juros | N3: Empréstimo | O3: Usinas solares | Q3: Receitas | R3: Despesas operacionais | S3: EBITDA | T3: Depreciação e amortização | U3: EBIT | V3: Despesas financeiras | W3: Lucro antes do imposto de renda | X3: IRPJ | Y3: Lucro líquido | AA3: EBIDTA | AB3: Aquisição de ativos | AC3: Captação de empréstimo | AD3: Pagamento de juros e principal | AE3: Resultado líquido | AF3: Saldo inicial | AG3: Saldo final | AJ3: Receita | AK3: Lucro líquido | AL3: EBITDA | AM3: Fluxo de caixa líquido | AN3: Saldo em caixa | AQ3: Fluxo de Caixa - APAGAR | AR3: Fluxo de Caixa Ideal
A4: =YEAR(C4) -> 2021 | B4: ="Q"&(QUOTIENT(MONTH(C4),3.1)+1) -> Q3 | C4: 44409 | G4: 300 | K4: =L4+M4 -> 8645.2403 | L4: =Financiamento!D13 -> 3455.7915 | M4: =Financiamento!C13 -> 5189.4489 | N4: =Financiamento!$B$3 -> 331380.09 | O4: =N4 -> 331380.09 | Q4: =D4 -> 0 | R4: =-SUM(F4:I4) -> -300 | S4: =SUM(Q4:R4) -> -300 | U4: =SUM(S4:T4) -> -300 | V4: =-M4 -> -5189.4489 | W4: =SUM(U4:V4) -> -5489.4489 | X4: =-J4 -> 0 | Y4: =SUM(W4:X4) -> -5489.4489 | AA4: =S4 -> -300 | AB4: =-O4 -> -331380.09 | AC4: =N4 -> 331380.09 | AD4: =-K4 -> -8645.2403 | AE4: =SUM(AA4:AD4) -> -8945.2403 | AF4: 0 | AG4: =AF4+AE4 -> -8945.2403 | AI4: 2021 | AJ4: =SUMIFS($Q$4:$Q$176,$A$4:$A$176,$AI4) -> 0 | AK4: =SUMIFS($Y$4:$Y$176,$A$4:$A$176,$AI4) -> -26906.793 | AL4: =SUMIFS($S$4:$S$176,$A$4:$A$176,$AI4) -> -1500 | AM4: =SUMIFS($AE$4:$AE$176,$A$4:$A$176,$AI4) -> -44726.202 | AN4: {=XLOOKUP(AI4&12,$A$4:$A$176&MONTH($C$4:$C$176),$AG$4:$AG$176)} -> #NAME? | AQ4: =AE4 -> -8945.2403 | AR4: =AQ4 -> -8945.2403
A5: =YEAR(C5) -> 2021 | B5: ="Q"&(QUOTIENT(MONTH(C5),3.1)+1) -> Q3 | C5: 44440 | G5: 300 | K5: =L5+M5 -> 8645.2403 | L5: =Financiamento!D14 -> 3509.0106 | M5: =Financiamento!C14 -> 5136.2297 | Q5: =D5 -> 0 | R5: =-SUM(F5:I5) -> -300 | S5: =SUM(Q5:R5) -> -300 | U5: =SUM(S5:T5) -> -300 | V5: =-M5 -> -5136.2297 | W5: =SUM(U5:V5) -> -5436.2297 | X5: =-J5 -> 0 | Y5: =SUM(W5:X5) -> -5436.2297 | AA5: =S5 -> -300 | AB5: =-O5 -> 0 | AC5: =N5 -> 0 | AD5: =-K5 -> -8645.2403 | AE5: =SUM(AA5:AD5) -> -8945.2403 | AF5: =AG4 -> -8945.2403 | AG5: =AF5+AE5 -> -17890.481 | AI5: 2022 | AJ5: =SUMIFS($Q$4:$Q$176,$A$4:$A$176,$AI5) -> 0 | AK5: =SUMIFS($Y$4:$Y$176,$A$4:$A$176,$AI5) -> -58587.437 | AL5: =SUMIFS($S$4:$S$176,$A$4:$A$176,$AI5) -> -3600 | AM5: =SUMIFS($AE$4:$AE$176,$A$4:$A$176,$AI5) -> -107342.88 | AN5: {=XLOOKUP(AI5&12,$A$4:$A$176&MONTH($C$4:$C$176),$AG$4:$AG$176)} -> #NAME? | AQ5: =AE5 -> -8945.2403 | AR5: =AQ5 -> -8945.2403
A6: =YEAR(C6) -> 2021 | B6: ="Q"&(QUOTIENT(MONTH(C6),3.1)+1) -> Q4 | C6: 44470 | G6: 300 | K6: =L6+M6 -> 8645.2403 | L6: =Financiamento!D15 -> 3563.0494 | M6: =Financiamento!C15 -> 5082.1909 | Q6: =D6 -> 0 | R6: =-SUM(F6:I6) -> -300 | S6: =SUM(Q6:R6) -> -300 | U6: =SUM(S6:T6) -> -300 | V6: =-M6 -> -5082.1909 | W6: =SUM(U6:V6) -> -5382.1909 | X6: =-J6 -> 0 | Y6: =SUM(W6:X6) -> -5382.1909 | AA6: =S6 -> -300 | AB6: =-O6 -> 0 | AC6: =N6 -> 0 | AD6: =-K6 -> -8645.2403 | AE6: =SUM(AA6:AD6) -> -8945.2403 | AF6: =AG5 -> -17890.481 | AG6: =AF6+AE6 -> -26835.721 | AI6: 2023 | AJ6: =SUMIFS($Q$4:$Q$176,$A$4:$A$176,$AI6) -> 46972.693 | AK6: =SUMIFS($Y$4:$Y$176,$A$4:$A$176,$AI6) -> -8405.4046 | AL6: =SUMIFS($S$4:$S$176,$A$4:$A$176,$AI6) -> 39586.673 | AM6: =SUMIFS($AE$4:$AE$176,$A$4:$A$176,$AI6) -> -64156.211 | AN6: {=XLOOKUP(AI6&12,$A$4:$A$176&MONTH($C$4:$C$176),$AG$4:$AG$176)} -> #NAME? | AQ6: =AE6 -> -8945.2403 | AR6: =AQ6 -> -8945.2403
A7: =YEAR(C7) -> 2021 | B7: ="Q"&(QUOTIENT(MONTH(C7),3.1)+1) -> Q4 | C7: 44501 | G7: 300 | K7: =L7+M7 -> 8645.2403 | L7: =Financiamento!D16 -> 3617.9204 | M7: =Financiamento!C16 -> 5027.32 | Q7: =D7 -> 0 | R7: =-SUM(F7:I7) -> -300 | S7: =SUM(Q7:R7) -> -300 | U7: =SUM(S7:T7) -> -300 | V7: =-M7 -> -5027.32 | W7: =SUM(U7:V7) -> -5327.32 | X7: =-J7 -> 0 | Y7: =SUM(W7:X7) -> -5327.32 | AA7: =S7 -> -300 | AB7: =-O7 -> 0 | AC7: =N7 -> 0 | AD7: =-K7 -> -8645.2403 | AE7: =SUM(AA7:AD7) -> -8945.2403 | AF7: =AG6 -> -26835.721 | AG7: =AF7+AE7 -> -35780.961 | AI7: 2024 | AJ7: =SUMIFS($Q$4:$Q$176,$A$4:$A$176,$AI7) -> 68012.575 | AK7: =SUMIFS($Y$4:$Y$176,$A$4:$A$176,$AI7) -> 26193.176 | AL7: =SUMIFS($S$4:$S$176,$A$4:$A$176,$AI7) -> 63658.575 | AM7: =SUMIFS($AE$4:$AE$176,$A$4:$A$176,$AI7) -> -40084.309 | AN7: {=XLOOKUP(AI7&12,$A$4:$A$176&MONTH($C$4:$C$176),$AG$4:$AG$176)} -> #NAME? | AQ7: =AE7 -> -8945.2403 | AR7: =AQ7 -> -8945.2403
A8: =YEAR(C8) -> 2021 | B8: ="Q"&(QUOTIENT(MONTH(C8),3.1)+1) -> Q4 | C8: 44531 | G8: 300 | K8: =L8+M8 -> 8645.2403 | L8: =Financiamento!D17 -> 3673.6363 | M8: =Financiamento!C17 -> 4971.604 | Q8: =D8 -> 0 | R8: =-SUM(F8:I8) -> -300 | S8: =SUM(Q8:R8) -> -300 | U8: =SUM(S8:T8) -> -300 | V8: =-M8 -> -4971.604 | W8: =SUM(U8:V8) -> -5271.604 | X8: =-J8 -> 0 | Y8: =SUM(W8:X8) -> -5271.604 | AA8: =S8 -> -300 | AB8: =-O8 -> 0 | AC8: =N8 -> 0 | AD8: =-K8 -> -8645.2403 | AE8: =SUM(AA8:AD8) -> -8945.2403 | AF8: =AG7 -> -35780.961 | AG8: =AF8+AE8 -> -44726.202 | AI8: 2025 | AJ8: =SUMIFS($Q$4:$Q$176,$A$4:$A$176,$AI8) -> 97270.247 | AK8: =SUMIFS($Y$4:$Y$176,$A$4:$A$176,$AI8) -> 64451.602 | AL8: =SUMIFS($S$4:$S$176,$A$4:$A$176,$AI8) -> 93370.247 | AM8: =SUMIFS($AE$4:$AE$176,$A$4:$A$176,$AI8) -> -19017.878 | AN8: {=XLOOKUP(AI8&12,$A$4:$A$176&MONTH($C$4:$C$176),$AG$4:$AG$176)} -> #NAME? | AQ8: =AE8 -> -8945.2403 | AR8: =AQ8 -> -8945.2403
A9: =YEAR(C9) -> 2022 | B9: ="Q"&(QUOTIENT(MONTH(C9),3.1)+1) -> Q1 | C9: 44562 | G9: 300 | K9: =L9+M9 -> 8645.2403 | L9: =Financiamento!D18 -> 3730.2103 | M9: =Financiamento!C18 -> 4915.03 | Q9: =D9 -> 0 | R9: =-SUM(F9:I9) -> -300 | S9: =SUM(Q9:R9) -> -300 | U9: =SUM(S9:T9) -> -300 | V9: =-M9 -> -4915.03 | W9: =SUM(U9:V9) -> -5215.03 | X9: =-J9 -> 0 | Y9: =SUM(W9:X9) -> -5215.03 | AA9: =S9 -> -300 | AB9: =-O9 -> 0 | AC9: =N9 -> 0 | AD9: =-K9 -> -8645.2403 | AE9: =SUM(AA9:AD9) -> -8945.2403 | AF9: =AG8 -> -44726.202 | AG9: =AF9+AE9 -> -53671.442 | AI9: 2026 | AJ9: =SUMIFS($Q$4:$Q$176,$A$4:$A$176,$AI9) -> #NAME? | AK9: =SUMIFS($Y$4:$Y$176,$A$4:$A$176,$AI9) -> #NAME? | AL9: =SUMIFS($S$4:$S$176,$A$4:$A$176,$AI9) -> #NAME? | AM9: =SUMIFS($AE$4:$AE$176,$A$4:$A$176,$AI9) -> #NAME? | AN9: {=XLOOKUP(AI9&12,$A$4:$A$176&MONTH($C$4:$C$176),$AG$4:$AG$176)} -> #NAME? | AQ9: =AE9 -> -8945.2403 | AR9: =AQ9 -> -8945.2403
A10: =YEAR(C10) -> 2022 | B10: ="Q"&(QUOTIENT(MONTH(C10),3.1)+1) -> Q1 | C10: 44593 | G10: 300 | K10: =L10+M10 -> 8645.2403 | L10: =Financiamento!D19 -> 3787.6556 | M10: =Financiamento!C19 -> 4857.5848 | Q10: =D10 -> 0 | R10: =-SUM(F10:I10) -> -300 | S10: =SUM(Q10:R10) -> -300 | U10: =SUM(S10:T10) -> -300 | V10: =-M10 -> -4857.5848 | W10: =SUM(U10:V10) -> -5157.5848 | X10: =-J10 -> 0 | Y10: =SUM(W10:X10) -> -5157.5848 | AA10: =S10 -> -300 | AB10: =-O10 -> 0 | AC10: =N10 -> 0 | AD10: =-K10 -> -8645.2403 | AE10: =SUM(AA10:AD10) -> -8945.2403 | AF10: =AG9 -> -53671.442 | AG10: =AF10+AE10 -> -62616.682 | AI10: 2027 | AJ10: =SUMIFS($Q$4:$Q$176,$A$4:$A$176,$AI10) -> #NAME? | AK10: =SUMIFS($Y$4:$Y$176,$A$4:$A$176,$AI10) -> #NAME? | AL10: =SUMIFS($S$4:$S$176,$A$4:$A$176,$AI10) -> #NAME? | AM10: =SUMIFS($AE$4:$AE$176,$A$4:$A$176,$AI10) -> #NAME? | AN10: {=XLOOKUP(AI10&12,$A$4:$A$176&MONTH($C$4:$C$176),$AG$4:$AG$176)} -> #NAME? | AQ10: =AE10 -> -8945.2403 | AR10: =AQ10 -> -8945.2403
A11: =YEAR(C11) -> 2022 | B11: ="Q"&(QUOTIENT(MONTH(C11),3.1)+1) -> Q1 | C11: 44621 | G11: 300 | K11: =L11+M11 -> 8645.2403 | L11: =Financiamento!D20 -> 3845.9855 | M11: =Financiamento!C20 -> 4799.2549 | Q11: =D11 -> 0 | R11: =-SUM(F11:I11) -> -300 | S11: =SUM(Q11:R11) -> -300 | U11: =SUM(S11:T11) -> -300 | V11: =-M11 -> -4799.2549 | W11: =SUM(U11:V11) -> -5099.2549 | X11: =-J11 -> 0 | Y11: =SUM(W11:X11) -> -5099.2549 | AA11: =S11 -> -300 | AB11: =-O11 -> 0 | AC11: =N11 -> 0 | AD11: =-K11 -> -8645.2403 | AE11: =SUM(AA11:AD11) -> -8945.2403 | AF11: =AG10 -> -62616.682 | AG11: =AF11+AE11 -> -71561.923 | AI11: 2028 | AJ11: =SUMIFS($Q$4:$Q$176,$A$4:$A$176,$AI11) -> #NAME? | AK11: =SUMIFS($Y$4:$Y$176,$A$4:$A$176,$AI11) -> #NAME? | AL11: =SUMIFS($S$4:$S$176,$A$4:$A$176,$AI11) -> #NAME? | AM11: =SUMIFS($AE$4:$AE$176,$A$4:$A$176,$AI11) -> #NAME? | AN11: {=XLOOKUP(AI11&12,$A$4:$A$176&MONTH($C$4:$C$176),$AG$4:$AG$176)} -> #NAME? | AQ11: =AE11 -> -8945.2403 | AR11: =AQ11 -> -8945.2403
A12: =YEAR(C12) -> 2022 | B12: ="Q"&(QUOTIENT(MONTH(C12),3.1)+1) -> Q2 | C12: 44652 | G12: 300 | K12: =L12+M12 -> 8645.2403 | L12: =Financiamento!D21 -> 3905.2137 | M12: =Financiamento!C21 -> 4740.0267 | Q12: =D12 -> 0 | R12: =-SUM(F12:I12) -> -300 | S12: =SUM(Q12:R12) -> -300 | U12: =SUM(S12:T12) -> -300 | V12: =-M12 -> -4740.0267 | W12: =SUM(U12:V12) -> -5040.0267 | X12: =-J12 -> 0 | Y12: =SUM(W12:X12) -> -5040.0267 | AA12: =S12 -> -300 | AB12: =-O12 -> 0 | AC12: =N12 -> 0 | AD12: =-K12 -> -8645.2403 | AE12: =SUM(AA12:AD12) -> -8945.2403 | AF12: =AG11 -> -71561.923 | AG12: =AF12+AE12 -> -80507.163 | AI12: 2029 | AJ12: =SUMIFS($Q$4:$Q$176,$A$4:$A$176,$AI12) -> #NAME? | AK12: =SUMIFS($Y$4:$Y$176,$A$4:$A$176,$AI12) -> #NAME? | AL12: =SUMIFS($S$4:$S$176,$A$4:$A$176,$AI12) -> #NAME? | AM12: =SUMIFS($AE$4:$AE$176,$A$4:$A$176,$AI12) -> #NAME? | AN12: {=XLOOKUP(AI12&12,$A$4:$A$176&MONTH($C$4:$C$176),$AG$4:$AG$176)} -> #NAME? | AQ12: =AE12 -> -8945.2403 | AR12: =AQ12 -> -8945.2403
A13: =YEAR(C13) -> 2022 | B13: ="Q"&(QUOTIENT(MONTH(C13),3.1)+1) -> Q2 | C13: 44682 | G13: 300 | K13: =L13+M13 -> 8645.2403 | L13: =Financiamento!D22 -> 3965.354 | M13: =Financiamento!C22 -> 4679.8864 | Q13: =D13 -> 0 | R13: =-SUM(F13:I13) -> -300 | S13: =SUM(Q13:R13) -> -300 | U13: =SUM(S13:T13) -> -300 | V13: =-M13 -> -4679.8864 | W13: =SUM(U13:V13) -> -4979.8864 | X13: =-J13 -> 0 | Y13: =SUM(W13:X13) -> -4979.8864 | AA13: =S13 -> -300 | AB13: =-O13 -> 0 | AC13: =N13 -> 0 | AD13: =-K13 -> -8645.2403 | AE13: =SUM(AA13:AD13) -> -8945.2403 | AF13: =AG12 -> -80507.163 | AG13: =AF13+AE13 -> -89452.403 | AI13: 2030 | AJ13: =SUMIFS($Q$4:$Q$176,$A$4:$A$176,$AI13) -> #NAME? | AK13: =SUMIFS($Y$4:$Y$176,$A$4:$A$176,$AI13) -> #NAME? | AL13: =SUMIFS($S$4:$S$176,$A$4:$A$176,$AI13) -> #NAME? | AM13: =SUMIFS($AE$4:$AE$176,$A$4:$A$176,$AI13) -> #NAME? | AN13: {=XLOOKUP(AI13&12,$A$4:$A$176&MONTH($C$4:$C$176),$AG$4:$AG$176)} -> #NAME? | AQ13: =AE13 -> -8945.2403 | AR13: =AQ13 -> -8945.2403
A14: =YEAR(C14) -> 2022 | B14: ="Q"&(QUOTIENT(MONTH(C14),3.1)+1) -> Q2 | C14: 44713 | G14: 300 | K14: =L14+M14 -> 8645.2403 | L14: =Financiamento!D23 -> 4026.4204 | M14: =Financiamento!C23 -> 4618.8199 | Q14: =D14 -> 0 | R14: =-SUM(F14:I14) -> -300 | S14: =SUM(Q14:R14) -> -300 | U14: =SUM(S14:T14) -> -300 | V14: =-M14 -> -4618.8199 | W14: =SUM(U14:V14) -> -4918.8199 | X14: =-J14 -> 0 | Y14: =SUM(W14:X14) -> -4918.8199 | AA14: =S14 -> -300 | AB14: =-O14 -> 0 | AC14: =N14 -> 0 | AD14: =-K14 -> -8645.2403 | AE14: =SUM(AA14:AD14) -> -8945.2403 | AF14: =AG13 -> -89452.403 | AG14: =AF14+AE14 -> -98397.644 | AI14: 2031 | AJ14: =SUMIFS($Q$4:$Q$176,$A$4:$A$176,$AI14) -> #NAME? | AK14: =SUMIFS($Y$4:$Y$176,$A$4:$A$176,$AI14) -> #NAME? | AL14: =SUMIFS($S$4:$S$176,$A$4:$A$176,$AI14) -> #NAME? | AM14: =SUMIFS($AE$4:$AE$176,$A$4:$A$176,$AI14) -> #NAME? | AN14: {=XLOOKUP(AI14&12,$A$4:$A$176&MONTH($C$4:$C$176),$AG$4:$AG$176)} -> #NAME? | AQ14: =AE14 -> -8945.2403 | AR14: =AQ14 -> -8945.2403
A15: =YEAR(C15) -> 2022 | B15: ="Q"&(QUOTIENT(MONTH(C15),3.1)+1) -> Q3 | C15: 44743 | G15: 300 | K15: =L15+M15 -> 8645.2403 | L15: =Financiamento!D24 -> 4088.4273 | M15: =Financiamento!C24 -> 4556.8131 | Q15: =D15 -> 0 | R15: =-SUM(F15:I15) -> -300 | S15: =SUM(Q15:R15) -> -300 | U15: =SUM(S15:T15) -> -300 | V15: =-M15 -> -4556.8131 | W15: =SUM(U15:V15) -> -4856.8131 | X15: =-J15 -> 0 | Y15: =SUM(W15:X15) -> -4856.8131 | AA15: =S15 -> -300 | AB15: =-O15 -> 0 | AC15: =N15 -> 0 | AD15: =-K15 -> -8645.2403 | AE15: =SUM(AA15:AD15) -> -8945.2403 | AF15: =AG14 -> -98397.644 | AG15: =AF15+AE15 -> -107342.88 | AI15: 2032 | AJ15: =SUMIFS($Q$4:$Q$176,$A$4:$A$176,$AI15) -> #NAME? | AK15: =SUMIFS($Y$4:$Y$176,$A$4:$A$176,$AI15) -> #NAME? | AL15: =SUMIFS($S$4:$S$176,$A$4:$A$176,$AI15) -> #NAME? | AM15: =SUMIFS($AE$4:$AE$176,$A$4:$A$176,$AI15) -> #NAME? | AN15: {=XLOOKUP(AI15&12,$A$4:$A$176&MONTH($C$4:$C$176),$AG$4:$AG$176)} -> #NAME? | AQ15: =AE15 -> -8945.2403 | AR15: =AQ15 -> -8945.2403
A16: =YEAR(C16) -> 2022 | B16: ="Q"&(QUOTIENT(MONTH(C16),3.1)+1) -> Q3 | C16: 44774 | G16: 300 | K16: =L16+M16 -> 8645.2403 | L16: =Financiamento!D25 -> 4151.3891 | M16: =Financiamento!C25 -> 4493.8513 | Q16: =D16 -> 0 | R16: =-SUM(F16:I16) -> -300 | S16: =SUM(Q16:R16) -> -300 | U16: =SUM(S16:T16) -> -300 | V16: =-M16 -> -4493.8513 | W16: =SUM(U16:V16) -> -4793.8513 | X16: =-J16 -> 0 | Y16: =SUM(W16:X16) -> -4793.8513 | AA16: =S16 -> -300 | AB16: =-O16 -> 0 | AC16: =N16 -> 0 | AD16: =-K16 -> -8645.2403 | AE16: =SUM(AA16:AD16) -> -8945.2403 | AF16: =AG15 -> -107342.88 | AG16: =AF16+AE16 -> -116288.12 | AI16: 2033 | AJ16: =SUMIFS($Q$4:$Q$176,$A$4:$A$176,$AI16) -> #NAME? | AK16: =SUMIFS($Y$4:$Y$176,$A$4:$A$176,$AI16) -> #NAME? | AL16: =SUMIFS($S$4:$S$176,$A$4:$A$176,$AI16) -> #NAME? | AM16: =SUMIFS($AE$4:$AE$176,$A$4:$A$176,$AI16) -> #NAME? | AN16: {=XLOOKUP(AI16&12,$A$4:$A$176&MONTH($C$4:$C$176),$AG$4:$AG$176)} -> #NAME? | AQ16: =AE16 -> -8945.2403 | AR16: =AQ16 -> -8945.2403
... A18: =YEAR(C18) -> 2022 | B18: ="Q"&(QUOTIENT(MONTH(C18),3.1)+1) -> Q4 | C18: 44835 | G18: 300 | K18: =L18+M18 -> 8645.2403 | L18: =Financiamento!D27 -> 4280.2364 | M18: =Financiamento!C27 -> 4365.004 | Q18: =D18 -> 0 | R18: =-SUM(F18:I18) -> -300 | S18: =SUM(Q18:R18) -> -300 | U18: =SUM(S18:T18) -> -300 | V18: =-M18 -> -4365.004 | W18: =SUM(U18:V18) -> -4665.004 | X18: =-J18 -> 0 | Y18: =SUM(W18:X18) -> -4665.004 | AA18: =S18 -> -300 | AB18: =-O18 -> 0 | AC18: =N18 -> 0 | AD18: =-K18 -> -8645.2403 | AE18: =SUM(AA18:AD18) -> -8945.2403 | AF18: =AG17 -> -125233.36 | AG18: =AF18+AE18 -> -134178.61 | AI18: 2035 | AJ18: =SUMIFS($Q$4:$Q$176,$A$4:$A$176,$AI18) -> #NAME? | AK18: =SUMIFS($Y$4:$Y$176,$A$4:$A$176,$AI18) -> #NAME? | AL18: =SUMIFS($S$4:$S$176,$A$4:$A$176,$AI18) -> #NAME? | AM18: =SUMIFS($AE$4:$AE$176,$A$4:$A$176,$AI18) -> #NAME? | AN18: {=XLOOKUP(AI18&12,$A$4:$A$176&MONTH($C$4:$C$176),$AG$4:$AG$176)} -> #NAME? | AQ18: =AE18 -> -8945.2403 | AR18: =AQ18 -> -8945.2403
A19: =YEAR(C19) -> 2022 | B19: ="Q"&(QUOTIENT(MONTH(C19),3.1)+1) -> Q4 | C19: 44866 | G19: 300 | K19: =L19+M19 -> 8645.2403 | L19: =Financiamento!D28 -> 4346.152 | M19: =Financiamento!C28 -> 4299.0883 | Q19: =D19 -> 0 | R19: =-SUM(F19:I19) -> -300 | S19: =SUM(Q19:R19) -> -300 | U19: =SUM(S19:T19) -> -300 | V19: =-M19 -> -4299.0883 | W19: =SUM(U19:V19) -> -4599.0883 | X19: =-J19 -> 0 | Y19: =SUM(W19:X19) -> -4599.0883 | AA19: =S19 -> -300 | AB19: =-O19 -> 0 | AC19: =N19 -> 0 | AD19: =-K19 -> -8645.2403 | AE19: =SUM(AA19:AD19) -> -8945.2403 | AF19: =AG18 -> -134178.61 | AG19: =AF19+AE19 -> -143123.85 | AQ19: =AE19 -> -8945.2403 | AR19: =AQ19 -> -8945.2403
A20: =YEAR(C20) -> 2022 | B20: ="Q"&(QUOTIENT(MONTH(C20),3.1)+1) -> Q4 | C20: 44896 | G20: 300 | K20: =L20+M20 -> 8645.2403 | L20: =Financiamento!D29 -> 4413.0828 | M20: =Financiamento!C29 -> 4232.1576 | Q20: =D20 -> 0 | R20: =-SUM(F20:I20) -> -300 | S20: =SUM(Q20:R20) -> -300 | U20: =SUM(S20:T20) -> -300 | V20: =-M20 -> -4232.1576 | W20: =SUM(U20:V20) -> -4532.1576 | X20: =-J20 -> 0 | Y20: =SUM(W20:X20) -> -4532.1576 | AA20: =S20 -> -300 | AB20: =-O20 -> 0 | AC20: =N20 -> 0 | AD20: =-K20 -> -8645.2403 | AE20: =SUM(AA20:AD20) -> -8945.2403 | AF20: =AG19 -> -143123.85 | AG20: =AF20+AE20 -> -152069.09 | AQ20: =AE20 -> -8945.2403 | AR20: =AQ20 -> -8945.2403
A21: =YEAR(C21) -> 2023 | B21: ="Q"&(QUOTIENT(MONTH(C21),3.1)+1) -> Q1 | C21: 44927 | G21: 300 | K21: =L21+M21 -> 8645.2403 | L21: =Financiamento!D30 -> 4481.0442 | M21: =Financiamento!C30 -> 4164.1961 | Q21: =D21 -> 0 | R21: =-SUM(F21:I21) -> -300 | S21: =SUM(Q21:R21) -> -300 | U21: =SUM(S21:T21) -> -300 | V21: =-M21 -> -4164.1961 | W21: =SUM(U21:V21) -> -4464.1961 | X21: =-J21 -> 0 | Y21: =SUM(W21:X21) -> -4464.1961 | AA21: =S21 -> -300 | AB21: =-O21 -> 0 | AC21: =N21 -> 0 | AD21: =-K21 -> -8645.2403 | AE21: =SUM(AA21:AD21) -> -8945.2403 | AF21: =AG20 -> -152069.09 | AG21: =AF21+AE21 -> -161014.33 | AQ21: =AE21 -> -8945.2403 | AR21: =AQ21 -> -8945.2403
A22: =YEAR(C22) -> 2023 | B22: ="Q"&(QUOTIENT(MONTH(C22),3.1)+1) -> Q1 | C22: 44958 | G22: 300 | K22: =L22+M22 -> 8645.2403 | L22: =Financiamento!D31 -> 4550.0523 | M22: =Financiamento!C31 -> 4095.188 | Q22: =D22 -> 0 | R22: =-SUM(F22:I22) -> -300 | S22: =SUM(Q22:R22) -> -300 | U22: =SUM(S22:T22) -> -300 | V22: =-M22 -> -4095.188 | W22: =SUM(U22:V22) -> -4395.188 | X22: =-J22 -> 0 | Y22: =SUM(W22:X22) -> -4395.188 | AA22: =S22 -> -300 | AB22: =-O22 -> 0 | AC22: =N22 -> 0 | AD22: =-K22 -> -8645.2403 | AE22: =SUM(AA22:AD22) -> -8945.2403 | AF22: =AG21 -> -161014.33 | AG22: =AF22+AE22 -> -169959.57 | AQ22: =AE22 -> -8945.2403 | AR22: =AQ22 -> -8945.2403
A23: =YEAR(C23) -> 2023 | B23: ="Q"&(QUOTIENT(MONTH(C23),3.1)+1) -> Q1 | C23: 44986 | D23: =DRE!D23 -> 6633.93 | G23: 300 | J23: =D23*6% -> 398.0358 | K23: =L23+M23 -> 8645.2403 | L23: =Financiamento!D32 -> 4620.1231 | M23: =Financiamento!C32 -> 4025.1172 | Q23: =D23 -> 6633.93 | R23: =-SUM(F23:I23) -> -300 | S23: =SUM(Q23:R23) -> 6333.93 | U23: =SUM(S23:T23) -> 6333.93 | V23: =-M23 -> -4025.1172 | W23: =SUM(U23:V23) -> 2308.8127 | X23: =-J23 -> -398.0358 | Y23: =SUM(W23:X23) -> 1910.777 | AA23: =S23 -> 6333.93 | AB23: =-O23 -> 0 | AC23: =N23 -> 0 | AD23: =-K23 -> -8645.2403 | AE23: =SUM(AA23:AD23) -> -2311.3104 | AF23: =AG22 -> -169959.57 | AG23: =AF23+AE23 -> -172270.88 | AQ23: =AE23 -> -2311.3104 | AR23: =AQ23 -> -2311.3104
A24: =YEAR(C24) -> 2023 | B24: ="Q"&(QUOTIENT(MONTH(C24),3.1)+1) -> Q2 | C24: 45017 | D24: =DRE!D24 -> 4801.7427 | G24: 300 | J24: =D24*6% -> 288.10456 | K24: =L24+M24 -> 8645.2403 | L24: =Financiamento!D33 -> 4691.273 | M24: =Financiamento!C33 -> 3953.9673 | Q24: =D24 -> 4801.7427 | R24: =-SUM(F24:I24) -> -300 | S24: =SUM(Q24:R24) -> 4501.7427 | U24: =SUM(S24:T24) -> 4501.7427 | V24: =-M24 -> -3953.9673 | W24: =SUM(U24:V24) -> 547.77538 | X24: =-J24 -> -288.10456 | Y24: =SUM(W24:X24) -> 259.67081 | AA24: =S24 -> 4501.7427 | AB24: =-O24 -> 0 | AC24: =N24 -> 0 | AD24: =-K24 -> -8645.2403 | AE24: =SUM(AA24:AD24) -> -4143.4976 | AF24: =AG23 -> -172270.88 | AG24: =AF24+AE24 -> -176414.37 | AQ24: =AE24 -> -4143.4976 | AR24: =AQ24 -> -4143.4976
A25: =YEAR(C25) -> 2023 | B25: ="Q"&(QUOTIENT(MONTH(C25),3.1)+1) -> Q2 | C25: 45047 | D25: =DRE!D25 -> 5583.9064 | G25: 300 | J25: =D25*6% -> 335.03438 | K25: =L25+M25 -> 8645.2403 | L25: =Financiamento!D34 -> 4763.5186 | M25: =Financiamento!C34 -> 3881.7217 | Q25: =D25 -> 5583.9064 | R25: =-SUM(F25:I25) -> -300 | S25: =SUM(Q25:R25) -> 5283.9064 | U25: =SUM(S25:T25) -> 5283.9064 | V25: =-M25 -> -3881.7217 | W25: =SUM(U25:V25) -> 1402.1847 | X25: =-J25 -> -335.03438 | Y25: =SUM(W25:X25) -> 1067.1503 | AA25: =S25 -> 5283.9064 | AB25: =-O25 -> 0 | AC25: =N25 -> 0 | AD25: =-K25 -> -8645.2403 | AE25: =SUM(AA25:AD25) -> -3361.334 | AF25: =AG24 -> -176414.37 | AG25: =AF25+AE25 -> -179775.71 | AQ25: =AE25 -> -3361.334 | AR25: =AQ25 -> -3361.334
A26: =YEAR(C26) -> 2023 | B26: ="Q"&(QUOTIENT(MONTH(C26),3.1)+1) -> Q2 | C26: 45078 | D26: =DRE!D26 -> 4018.4622 | G26: 300 | J26: =D26*6% -> 241.10773 | K26: =L26+M26 -> 8645.2403 | L26: =Financiamento!D35 -> 4836.8768 | M26: =Financiamento!C35 -> 3808.3635 | Q26: =D26 -> 4018.4622 | R26: =-SUM(F26:I26) -> -300 | S26: =SUM(Q26:R26) -> 3718.4622 | U26: =SUM(S26:T26) -> 3718.4622 | V26: =-M26 -> -3808.3635 | W26: =SUM(U26:V26) -> -89.901362 | X26: =-J26 -> -241.10773 | Y26: =SUM(W26:X26) -> -331.00909 | AA26: =S26 -> 3718.4622 | AB26: =-O26 -> 0 | AC26: =N26 -> 0 | AD26: =-K26 -> -8645.2403 | AE26: =SUM(AA26:AD26) -> -4926.7782 | AF26: =AG25 -> -179775.71 | AG26: =AF26+AE26 -> -184702.49 | AQ26: =AE26 -> -4926.7782 | AR26: =AQ26 -> -4926.7782
A27: =YEAR(C27) -> 2023 | B27: ="Q"&(QUOTIENT(MONTH(C27),3.1)+1) -> Q3 | C27: 45108 | D27: =DRE!D27 -> 3394.6012 | G27: 300 | J27: =D27*6% -> 203.67607 | K27: =L27+M27 -> 8645.2403 | L27: =Financiamento!D36 -> 4911.3647 | M27: =Financiamento!C36 -> 3733.8756 | Q27: =D27 -> 3394.6012 | R27: =-SUM(F27:I27) -> -300 | S27: =SUM(Q27:R27) -> 3094.6012 | U27: =SUM(S27:T27) -> 3094.6012 | V27: =-M27 -> -3733.8756 | W27: =SUM(U27:V27) -> -639.27447 | X27: =-J27 -> -203.67607 | Y27: =SUM(W27:X27) -> -842.95054 | AA27: =S27 -> 3094.6012 | AB27: =-O27 -> 0 | AC27: =N27 -> 0 | AD27: =-K27 -> -8645.2403 | AE27: =SUM(AA27:AD27) -> -5550.6392 | AF27: =AG26 -> -184702.49 | AG27: =AF27+AE27 -> -190253.13 | AQ27: =AE27 -> -5550.6392 | AR27: =AQ27 -> -5550.6392
A28: =YEAR(C28) -> 2023 | B28: ="Q"&(QUOTIENT(MONTH(C28),3.1)+1) -> Q3 | C28: 45139 | D28: =DRE!D28 -> 3812.6327 | F28: 1700 | G28: 300 | H28: 236.27 | J28: =D28*6% -> 228.75796 | K28: =L28+M28 -> 8645.2403 | L28: =Financiamento!D37 -> 4986.9997 | M28: =Financiamento!C37 -> 3658.2406 | Q28: =D28 -> 3812.6327 | R28: =-SUM(F28:I28) -> -2236.27 | S28: =SUM(Q28:R28) -> 1576.3627 | U28: =SUM(S28:T28) -> 1576.3627 | V28: =-M28 -> -3658.2406 | W28: =SUM(U28:V28) -> -2081.8779 | X28: =-J28 -> -228.75796 | Y28: =SUM(W28:X28) -> -2310.6358 | AA28: =S28 -> 1576.3627 | AB28: =-O28 -> 0 | AC28: =N28 -> 0 | AD28: =-K28 -> -8645.2403 | AE28: =SUM(AA28:AD28) -> -7068.8776 | AF28: =AG27 -> -190253.13 | AG28: =AF28+AE28 -> -197322 | AQ28: =AE28 -> -7068.8776 | AR28: =AQ28 -> -7068.8776
A29: =YEAR(C29) -> 2023 | B29: ="Q"&(QUOTIENT(MONTH(C29),3.1)+1) -> Q3 | C29: 45170 | D29: =DRE!D29 -> 4381.9087 | G29: 300 | J29: =D29*6% -> 262.91452 | K29: =L29+M29 -> 8645.2403 | L29: =Financiamento!D38 -> 5063.7995 | M29: =Financiamento!C38 -> 3581.4408 | Q29: =D29 -> 4381.9087 | R29: =-SUM(F29:I29) -> -300 | S29: =SUM(Q29:R29) -> 4081.9087 | U29: =SUM(S29:T29) -> 4081.9087 | V29: =-M29 -> -3581.4408 | W29: =SUM(U29:V29) -> 500.46784 | X29: =-J29 -> -262.91452 | Y29: =SUM(W29:X29) -> 237.55332 | AA29: =S29 -> 4081.9087 | AB29: =-O29 -> 0 | AC29: =N29 -> 0 | AD29: =-K29 -> -8645.2403 | AE29: =SUM(AA29:AD29) -> -4563.3317 | AF29: =AG28 -> -197322 | AG29: =AF29+AE29 -> -201885.34 | AQ29: =AE29 -> -4563.3317 | AR29: =AQ29 -> -4563.3317
A30: =YEAR(C30) -> 2023 | B30: ="Q"&(QUOTIENT(MONTH(C30),3.1)+1) -> Q4 | C30: 45200 | D30: =DRE!D30 -> 4485.1539 | G30: 300 | J30: =D30*6% -> 269.10923 | K30: =L30+M30 -> 8645.2403 | L30: =Financiamento!D39 -> 5141.782 | M30: =Financiamento!C39 -> 3503.4583 | Q30: =D30 -> 4485.1539 | R30: =-SUM(F30:I30) -> -300 | S30: =SUM(Q30:R30) -> 4185.1539 | U30: =SUM(S30:T30) -> 4185.1539 | V30: =-M30 -> -3503.4583 | W30: =SUM(U30:V30) -> 681.69556 | X30: =-J30 -> -269.10923 | Y30: =SUM(W30:X30) -> 412.58633 | AA30: =S30 -> 4185.1539 | AB30: =-O30 -> 0 | AC30: =N30 -> 0 | AD30: =-K30 -> -8645.2403 | AE30: =SUM(AA30:AD30) -> -4460.0865 | AF30: =AG29 -> -201885.34 | AG30: =AF30+AE30 -> -206345.42 | AQ30: =AE30 -> -4460.0865 | AR30: =AQ30 -> -4460.0865
A31: =YEAR(C31) -> 2023 | B31: ="Q"&(QUOTIENT(MONTH(C31),3.1)+1) -> Q4 | C31: 45231 | D31: =DRE!D31 -> 5180.3796 | G31: 300 | J31: =D31*6% -> 310.82278 | K31: =L31+M31 -> 8645.2403 | L31: =Financiamento!D40 -> 5220.9655 | M31: =Financiamento!C40 -> 3424.2749 | Q31: =D31 -> 5180.3796 | R31: =-SUM(F31:I31) -> -300 | S31: =SUM(Q31:R31) -> 4880.3796 | U31: =SUM(S31:T31) -> 4880.3796 | V31: =-M31 -> -3424.2749 | W31: =SUM(U31:V31) -> 1456.1048 | X31: =-J31 -> -310.82278 | Y31: =SUM(W31:X31) -> 1145.282 | AA31: =S31 -> 4880.3796 | AB31: =-O31 -> 0 | AC31: =N31 -> 0 | AD31: =-K31 -> -8645.2403 | AE31: =SUM(AA31:AD31) -> -3764.8607 | AF31: =AG30 -> -206345.42 | AG31: =AF31+AE31 -> -210110.28 | AQ31: =AE31 -> -3764.8607 | AR31: =AQ31 -> -3764.8607
A32: =YEAR(C32) -> 2023 | B32: ="Q"&(QUOTIENT(MONTH(C32),3.1)+1) -> Q4 | C32: 45261 | D32: =DRE!D32 -> 4679.9759 | G32: 300 | H32: 1129.75 | I32: 720 | J32: =D32*6% -> 280.79855 | K32: =L32+M32 -> 8645.2403 | L32: =Financiamento!D41 -> 5301.3684 | M32: =Financiamento!C41 -> 3343.872 | Q32: =D32 -> 4679.9759 | R32: =-SUM(F32:I32) -> -2149.75 | S32: =SUM(Q32:R32) -> 2530.2259 | U32: =SUM(S32:T32) -> 2530.2259 | V32: =-M32 -> -3343.872 | W32: =SUM(U32:V32) -> -813.64614 | X32: =-J32 -> -280.79855 | Y32: =SUM(W32:X32) -> -1094.4447 | AA32: =S32 -> 2530.2259 | AB32: =-O32 -> 0 | AC32: =N32 -> 0 | AD32: =-K32 -> -8645.2403 | AE32: =SUM(AA32:AD32) -> -6115.0145 | AF32: =AG31 -> -210110.28 | AG32: =AF32+AE32 -> -216225.3 | AQ32: =AE32 -> -6115.0145 | AR32: =AQ32 -> -6115.0145
A33: =YEAR(C33) -> 2024 | B33: ="Q"&(QUOTIENT(MONTH(C33),3.1)+1) -> Q1 | C33: 45292 | D33: =DRE!D33 -> 4204.0459 | G33: 300 | J33: =D33*6% -> 252.24275 | K33: =L33+M33 -> 8645.2403 | L33: =Financiamento!D42 -> 5383.0094 | M33: =Financiamento!C42 -> 3262.2309 | Q33: =D33 -> 4204.0459 | R33: =-SUM(F33:I33) -> -300 | S33: =SUM(Q33:R33) -> 3904.0459 | U33: =SUM(S33:T33) -> 3904.0459 | V33: =-M33 -> -3262.2309 | W33: =SUM(U33:V33) -> 641.81497 | X33: =-J33 -> -252.24275 | Y33: =SUM(W33:X33) -> 389.57222 | AA33: =S33 -> 3904.0459 | AB33: =-O33 -> 0 | AC33: =N33 -> 0 | AD33: =-K33 -> -8645.2403 | AE33: =SUM(AA33:AD33) -> -4741.1945 | AF33: =AG32 -> -216225.3 | AG33: =AF33+AE33 -> -220966.49 | AQ33: =AE33 -> -4741.1945 | AR33: =AQ33 -> -4741.1945
A34: =YEAR(C34) -> 2024 | B34: ="Q"&(QUOTIENT(MONTH(C34),3.1)+1) -> Q1 | C34: 45323 | D34: =DRE!D34 -> 5809.9943 | G34: 300 | J34: =D34*6% -> 348.59966 | K34: =L34+M34 -> 8645.2403 | L34: =Financiamento!D43 -> 5465.9078 | M34: =Financiamento!C43 -> 3179.3326 | Q34: =D34 -> 5809.9943 | R34: =-SUM(F34:I34) -> -300 | S34: =SUM(Q34:R34) -> 5509.9943 | U34: =SUM(S34:T34) -> 5509.9943 | V34: =-M34 -> -3179.3326 | W34: =SUM(U34:V34) -> 2330.6617 | X34: =-J34 -> -348.59966 | Y34: =SUM(W34:X34) -> 1982.0621 | AA34: =S34 -> 5509.9943 | AB34: =-O34 -> 0 | AC34: =N34 -> 0 | AD34: =-K34 -> -8645.2403 | AE34: =SUM(AA34:AD34) -> -3135.246 | AF34: =AG33 -> -220966.49 | AG34: =AF34+AE34 -> -224101.74 | AQ34: =AE34 -> -3135.246 | AR34: =AQ34 -> -3135.246
A35: =YEAR(C35) -> 2024 | B35: ="Q"&(QUOTIENT(MONTH(C35),3.1)+1) -> Q1 | C35: 45352 | D35: =DRE!D35 -> 6923.6927 | G35: 300 | J35: =D35*6% -> 415.42156 | K35: =L35+M35 -> 8645.2403 | L35: =Financiamento!D44 -> 5550.0827 | M35: =Financiamento!C44 -> 3095.1576 | Q35: =D35 -> 6923.6927 | R35: =-SUM(F35:I35) -> -300 | S35: =SUM(Q35:R35) -> 6623.6927 | U35: =SUM(S35:T35) -> 6623.6927 | V35: =-M35 -> -3095.1576 | W35: =SUM(U35:V35) -> 3528.5351 | X35: =-J35 -> -415.42156 | Y35: =SUM(W35:X35) -> 3113.1136 | AA35: =S35 -> 6623.6927 | AB35: =-O35 -> 0 | AC35: =N35 -> 0 | AD35: =-K35 -> -8645.2403 | AE35: =SUM(AA35:AD35) -> -2021.5476 | AF35: =AG34 -> -224101.74 | AG35: =AF35+AE35 -> -226123.28 | AQ35: =AE35 -> -2021.5476 | AR35: =AQ35 -> -2021.5476
A36: =YEAR(C36) -> 2024 | B36: ="Q"&(QUOTIENT(MONTH(C36),3.1)+1) -> Q2 | C36: 45383 | D36: =DRE!D36 -> 5791.3046 | G36: 300 | J36: =D36*6% -> 347.47828 | K36: =L36+M36 -> 8645.2403 | L36: =Financiamento!D45 -> 5635.554 | M36: =Financiamento!C45 -> 3009.6863 | Q36: =D36 -> 5791.3046 | R36: =-SUM(F36:I36) -> -300 | S36: =SUM(Q36:R36) -> 5491.3046 | U36: =SUM(S36:T36) -> 5491.3046 | V36: =-M36 -> -3009.6863 | W36: =SUM(U36:V36) -> 2481.6183 | X36: =-J36 -> -347.47828 | Y36: =SUM(W36:X36) -> 2134.14 | AA36: =S36 -> 5491.3046 | AB36: =-O36 -> 0 | AC36: =N36 -> 0 | AD36: =-K36 -> -8645.2403 | AE36: =SUM(AA36:AD36) -> -3153.9357 | AF36: =AG35 -> -226123.28 | AG36: =AF36+AE36 -> -229277.22 | AQ36: =AE36 -> -3153.9357 | AR36: =AQ36 -> -3153.9357
A37: =YEAR(C37) -> 2024 | B37: ="Q"&(QUOTIENT(MONTH(C37),3.1)+1) -> Q2 | C37: 45413 | D37: =DRE!D37 -> 6448.4677 | G37: 300 | I37: 754 | J37: =D37*6% -> 386.90806 | K37: =L37+M37 -> 8645.2403 | L37: =Financiamento!D46 -> 5722.3416 | M37: =Financiamento!C46 -> 2922.8988 | Q37: =D37 -> 6448.4677 | R37: =-SUM(F37:I37) -> -1054 | S37: =SUM(Q37:R37) -> 5394.4677 | U37: =SUM(S37:T37) -> 5394.4677 | V37: =-M37 -> -2922.8988 | W37: =SUM(U37:V37) -> 2471.5689 | X37: =-J37 -> -386.90806 | Y37: =SUM(W37:X37) -> 2084.6608 | AA37: =S37 -> 5394.4677 | AB37: =-O37 -> 0 | AC37: =N37 -> 0 | AD37: =-K37 -> -8645.2403 | AE37: =SUM(AA37:AD37) -> -3250.7727 | AF37: =AG36 -> -229277.22 | AG37: =AF37+AE37 -> -232527.99 | AQ37: =AE37 -> -3250.7727 | AR37: =AQ37 -> -3250.7727
A38: =YEAR(C38) -> 2024 | B38: ="Q"&(QUOTIENT(MONTH(C38),3.1)+1) -> Q2 | C38: 45444 | D38: =DRE!D38 -> 4421.3115 | G38: 300 | J38: =D38*6% -> 265.27869 | K38: =L38+M38 -> 8645.2403 | L38: =Financiamento!D47 -> 5810.4656 | M38: =Financiamento!C47 -> 2834.7747 | Q38: =D38 -> 4421.3115 | R38: =-SUM(F38:I38) -> -300 | S38: =SUM(Q38:R38) -> 4121.3115 | U38: =SUM(S38:T38) -> 4121.3115 | V38: =-M38 -> -2834.7747 | W38: =SUM(U38:V38) -> 1286.5367 | X38: =-J38 -> -265.27869 | Y38: =SUM(W38:X38) -> 1021.258 | AA38: =S38 -> 4121.3115 | AB38: =-O38 -> 0 | AC38: =N38 -> 0 | AD38: =-K38 -> -8645.2403 | AE38: =SUM(AA38:AD38) -> -4523.9289 | AF38: =AG37 -> -232527.99 | AG38: =AF38+AE38 -> -237051.92 | AQ38: =AE38 -> -4523.9289 | AR38: =AQ38 -> -4523.9289
A39: =YEAR(C39) -> 2024 | B39: ="Q"&(QUOTIENT(MONTH(C39),3.1)+1) -> Q3 | C39: 45474 | D39: =DRE!D39 -> 3192.3306 | G39: 300 | J39: =D39*6% -> 191.53984 | K39: =L39+M39 -> 8645.2403 | L39: =Financiamento!D48 -> 5899.9468 | M39: =Financiamento!C48 -> 2745.2936 | Q39: =D39 -> 3192.3306 | R39: =-SUM(F39:I39) -> -300 | S39: =SUM(Q39:R39) -> 2892.3306 | U39: =SUM(S39:T39) -> 2892.3306 | V39: =-M39 -> -2745.2936 | W39: =SUM(U39:V39) -> 147.03709 | X39: =-J39 -> -191.53984 | Y39: =SUM(W39:X39) -> -44.502746 | AA39: =S39 -> 2892.3306 | AB39: =-O39 -> 0 | AC39: =N39 -> 0 | AD39: =-K39 -> -8645.2403 | AE39: =SUM(AA39:AD39) -> -5752.9097 | AF39: =AG38 -> -237051.92 | AG39: =AF39+AE39 -> -242804.83 | AQ39: =AE39 -> -5752.9097 | AR39: =AQ39 -> -5752.9097
A40: =YEAR(C40) -> 2024 | B40: ="Q"&(QUOTIENT(MONTH(C40),3.1)+1) -> Q3 | C40: 45505 | D40: =DRE!D40 -> 4415.5447 | G40: 300 | J40: =D40*6% -> 264.93268 | K40: =L40+M40 -> 8645.2403 | L40: =Financiamento!D49 -> 5990.806 | M40: =Financiamento!C49 -> 2654.4344 | Q40: =D40 -> 4415.5447 | R40: =-SUM(F40:I40) -> -300 | S40: =SUM(Q40:R40) -> 4115.5447 | U40: =SUM(S40:T40) -> 4115.5447 | V40: =-M40 -> -2654.4344 | W40: =SUM(U40:V40) -> 1461.1103 | X40: =-J40 -> -264.93268 | Y40: =SUM(W40:X40) -> 1196.1776 | AA40: =S40 -> 4115.5447 | AB40: =-O40 -> 0 | AC40: =N40 -> 0 | AD40: =-K40 -> -8645.2403 | AE40: =SUM(AA40:AD40) -> -4529.6957 | AF40: =AG39 -> -242804.83 | AG40: =AF40+AE40 -> -247334.53 | AQ40: =AE40 -> -4529.6957 | AR40: =AQ40 -> -4529.6957
A41: =YEAR(C41) -> 2024 | B41: ="Q"&(QUOTIENT(MONTH(C41),3.1)+1) -> Q3 | C41: 45536 | D41: =DRE!D41 -> 6035.7282 | G41: 300 | J41: =D41*6% -> 362.14369 | K41: =L41+M41 -> 8645.2403 | L41: =Financiamento!D50 -> 6083.0644 | M41: =Financiamento!C50 -> 2562.176 | Q41: =D41 -> 6035.7282 | R41: =-SUM(F41:I41) -> -300 | S41: =SUM(Q41:R41) -> 5735.7282 | U41: =SUM(S41:T41) -> 5735.7282 | V41: =-M41 -> -2562.176 | W41: =SUM(U41:V41) -> 3173.5523 | X41: =-J41 -> -362.14369 | Y41: =SUM(W41:X41) -> 2811.4086 | AA41: =S41 -> 5735.7282 | AB41: =-O41 -> 0 | AC41: =N41 -> 0 | AD41: =-K41 -> -8645.2403 | AE41: =SUM(AA41:AD41) -> -2909.5121 | AF41: =AG40 -> -247334.53 | AG41: =AF41+AE41 -> -250244.04 | AQ41: =AE41 -> -2909.5121 | AR41: =AQ41 -> -2909.5121
A42: =YEAR(C42) -> 2024 | B42: ="Q"&(QUOTIENT(MONTH(C42),3.1)+1) -> Q4 | C42: 45566 | D42: =DRE!D42 -> 5693.1627 | G42: 300 | J42: =D42*6% -> 341.58976 | K42: =L42+M42 -> 8645.2403 | L42: =Financiamento!D51 -> 6176.7436 | M42: =Financiamento!C51 -> 2468.4968 | Q42: =D42 -> 5693.1627 | R42: =-SUM(F42:I42) -> -300 | S42: =SUM(Q42:R42) -> 5393.1627 | U42: =SUM(S42:T42) -> 5393.1627 | V42: =-M42 -> -2468.4968 | W42: =SUM(U42:V42) -> 2924.666 | X42: =-J42 -> -341.58976 | Y42: =SUM(W42:X42) -> 2583.0762 | AA42: =S42 -> 5393.1627 | AB42: =-O42 -> 0 | AC42: =N42 -> 0 | AD42: =-K42 -> -8645.2403 | AE42: =SUM(AA42:AD42) -> -3252.0776 | AF42: =AG41 -> -250244.04 | AG42: =AF42+AE42 -> -253496.12 | AQ42: =AE42 -> -3252.0776 | AR42: =AQ42 -> -3252.0776
A43: =YEAR(C43) -> 2024 | B43: ="Q"&(QUOTIENT(MONTH(C43),3.1)+1) -> Q4 | C43: 45597 | D43: =DRE!D43 -> 8410.5282 | G43: 300 | J43: =D43*6% -> 504.63169 | K43: =L43+M43 -> 8645.2403 | L43: =Financiamento!D52 -> 6271.8654 | M43: =Financiamento!C52 -> 2373.3749 | Q43: =D43 -> 8410.5282 | R43: =-SUM(F43:I43) -> -300 | S43: =SUM(Q43:R43) -> 8110.5282 | U43: =SUM(S43:T43) -> 8110.5282 | V43: =-M43 -> -2373.3749 | W43: =SUM(U43:V43) -> 5737.1533 | X43: =-J43 -> -504.63169 | Y43: =SUM(W43:X43) -> 5232.5216 | AA43: =S43 -> 8110.5282 | AB43: =-O43 -> 0 | AC43: =N43 -> 0 | AD43: =-K43 -> -8645.2403 | AE43: =SUM(AA43:AD43) -> -534.71214 | AF43: =AG42 -> -253496.12 | AG43: =AF43+AE43 -> -254030.83 | AQ43: =AE43 -> -534.71214 | AR43: =AQ43 -> -534.71214
A44: =YEAR(C44) -> 2024 | B44: ="Q"&(QUOTIENT(MONTH(C44),3.1)+1) -> Q4 | C44: 45627 | D44: =DRE!D44 -> 6666.4636 | G44: 300 | J44: =D44*6% -> 399.98782 | K44: =L44+M44 -> 8645.2403 | L44: =Financiamento!D53 -> 6368.4521 | M44: =Financiamento!C53 -> 2276.7882 | Q44: =D44 -> 6666.4636 | R44: =-SUM(F44:I44) -> -300 | S44: =SUM(Q44:R44) -> 6366.4636 | U44: =SUM(S44:T44) -> 6366.4636 | V44: =-M44 -> -2276.7882 | W44: =SUM(U44:V44) -> 4089.6754 | X44: =-J44 -> -399.98782 | Y44: =SUM(W44:X44) -> 3689.6876 | AA44: =S44 -> 6366.4636 | AB44: =-O44 -> 0 | AC44: =N44 -> 0 | AD44: =-K44 -> -8645.2403 | AE44: =SUM(AA44:AD44) -> -2278.7767 | AF44: =AG43 -> -254030.83 | AG44: =AF44+AE44 -> -256309.61 | AQ44: =AE44 -> -2278.7767 | AR44: =AQ44 -> -2278.7767
A45: =YEAR(C45) -> 2025 | B45: ="Q"&(QUOTIENT(MONTH(C45),3.1)+1) -> Q1 | C45: 45658 | D45: =DRE!D45 -> 7369.6552 | G45: 300 | J45: =D45*6% -> 442.17931 | K45: =L45+M45 -> 8645.2403 | L45: =Financiamento!D54 -> 6466.5263 | M45: =Financiamento!C54 -> 2178.714 | Q45: =D45 -> 7369.6552 | R45: =-SUM(F45:I45) -> -300 | S45: =SUM(Q45:R45) -> 7069.6552 | U45: =SUM(S45:T45) -> 7069.6552 | V45: =-M45 -> -2178.714 | W45: =SUM(U45:V45) -> 4890.9412 | X45: =-J45 -> -442.17931 | Y45: =SUM(W45:X45) -> 4448.7618 | AA45: =S45 -> 7069.6552 | AB45: =-O45 -> 0 | AC45: =N45 -> 0 | AD45: =-K45 -> -8645.2403 | AE45: =SUM(AA45:AD45) -> -1575.5852 | AF45: =AG44 -> -256309.61 | AG45: =AF45+AE45 -> -257885.19 | AQ45: =AE45 -> -1575.5852 | AR45: =AQ45 -> -1575.5852
A46: =YEAR(C46) -> 2025 | B46: ="Q"&(QUOTIENT(MONTH(C46),3.1)+1) -> Q1 | C46: 45689 | D46: =DRE!D46 -> 9711.5085 | G46: 300 | J46: =D46*6% -> 582.69051 | K46: =L46+M46 -> 8645.2403 | L46: =Financiamento!D55 -> 6566.1108 | M46: =Financiamento!C55 -> 2079.1295 | Q46: =D46 -> 9711.5085 | R46: =-SUM(F46:I46) -> -300 | S46: =SUM(Q46:R46) -> 9411.5085 | U46: =SUM(S46:T46) -> 9411.5085 | V46: =-M46 -> -2079.1295 | W46: =SUM(U46:V46) -> 7332.379 | X46: =-J46 -> -582.69051 | Y46: =SUM(W46:X46) -> 6749.6885 | AA46: =S46 -> 9411.5085 | AB46: =-O46 -> 0 | AC46: =N46 -> 0 | AD46: =-K46 -> -8645.2403 | AE46: =SUM(AA46:AD46) -> 766.26815 | AF46: =AG45 -> -257885.19 | AG46: =AF46+AE46 -> -257118.92 | AQ46: =AE46 -> 766.26815 | AR46: =AQ46 -> 766.26815
A47: =YEAR(C47) -> 2025 | B47: ="Q"&(QUOTIENT(MONTH(C47),3.1)+1) -> Q1 | C47: 45717 | D47: =DRE!D47 -> 8151.3258 | G47: 300 | J47: =D47*6% -> 489.07955 | K47: =L47+M47 -> 8645.2403 | L47: =Financiamento!D56 -> 6667.2289 | M47: =Financiamento!C56 -> 1978.0114 | Q47: =D47 -> 8151.3258 | R47: =-SUM(F47:I47) -> -300 | S47: =SUM(Q47:R47) -> 7851.3258 | U47: =SUM(S47:T47) -> 7851.3258 | V47: =-M47 -> -1978.0114 | W47: =SUM(U47:V47) -> 5873.3143 | X47: =-J47 -> -489.07955 | Y47: =SUM(W47:X47) -> 5384.2348 | AA47: =S47 -> 7851.3258 | AB47: =-O47 -> 0 | AC47: =N47 -> 0 | AD47: =-K47 -> -8645.2403 | AE47: =SUM(AA47:AD47) -> -793.91459 | AF47: =AG46 -> -257118.92 | AG47: =AF47+AE47 -> -257912.84 | AQ47: =AE47 -> -793.91459 | AR47: =AQ47 -> -793.91459
A48: =YEAR(C48) -> 2025 | B48: ="Q"&(QUOTIENT(MONTH(C48),3.1)+1) -> Q2 | C48: 45748 | D48: =DRE!D48 -> 4025.7988 | G48: 300 | J48: =D48*6% -> 241.54793 | K48: =L48+M48 -> 8645.2403 | L48: =Financiamento!D57 -> 6769.9042 | M48: =Financiamento!C57 -> 1875.3361 | Q48: =D48 -> 4025.7988 | R48: =-SUM(F48:I48) -> -300 | S48: =SUM(Q48:R48) -> 3725.7988 | U48: =SUM(S48:T48) -> 3725.7988 | V48: =-M48 -> -1875.3361 | W48: =SUM(U48:V48) -> 1850.4627 | X48: =-J48 -> -241.54793 | Y48: =SUM(W48:X48) -> 1608.9148 | AA48: =S48 -> 3725.7988 | AB48: =-O48 -> 0 | AC48: =N48 -> 0 | AD48: =-K48 -> -8645.2403 | AE48: =SUM(AA48:AD48) -> -4919.4415 | AF48: =AG47 -> -257912.84 | AG48: =AF48+AE48 -> -262832.28 | AQ48: =AE48 -> -4919.4415 | AR48: =AQ48 -> -4919.4415
A49: =YEAR(C49) -> 2025 | B49: ="Q"&(QUOTIENT(MONTH(C49),3.1)+1) -> Q2 | C49: 45749 | D49: =DRE!D49 -> 5868.5959 | G49: 300 | J49: =D49*6% -> 352.11575 | K49: =L49+M49 -> 8645.2403 | L49: =Financiamento!D58 -> 6874.1608 | M49: =Financiamento!C58 -> 1771.0796 | Q49: =D49 -> 5868.5959 | R49: =-SUM(F48:I48) -> -300 | S49: =SUM(Q49:R49) -> 5568.5959 | U49: =SUM(S49:T49) -> 5568.5959 | V49: =-M48 -> -1875.3361 | W49: =SUM(U49:V49) -> 3693.2598 | X49: =-J48 -> -241.54793 | Y49: =SUM(W49:X49) -> 3451.7119 | AA49: =S49 -> 5568.5959 | AB49: =-O48 -> 0 | AC49: =N49 -> 0 | AD49: =-K48 -> -8645.2403 | AE49: =SUM(AA49:AD49) -> -3076.6444 | AF49: =AG48 -> -262832.28 | AG49: =AF49+AE49 -> -265908.92 | AQ49: =AE49 -> -3076.6444 | AR49: =AQ49 -> -3076.6444
A50: =YEAR(C50) -> 2025 | B50: ="Q"&(QUOTIENT(MONTH(C50),3.1)+1) -> Q2 | C50: 45750 | D50: =DRE!D50 -> 6262.4166 | G50: 300 | J50: =D50*6% -> 375.74499 | K50: =L50+M50 -> 8645.2403 | L50: =Financiamento!D59 -> 6980.0229 | M50: =Financiamento!C59 -> 1665.2175 | Q50: =D50 -> 6262.4166 | R50: =-SUM(F48:I48) -> -300 | S50: =SUM(Q50:R50) -> 5962.4166 | U50: =SUM(S50:T50) -> 5962.4166 | V50: =-M48 -> -1875.3361 | W50: =SUM(U50:V50) -> 4087.0805 | X50: =-J48 -> -241.54793 | Y50: =SUM(W50:X50) -> 3845.5325 | AA50: =S50 -> 5962.4166 | AB50: =-O48 -> 0 | AC50: =N50 -> 0 | AD50: =-K48 -> -8645.2403 | AE50: =SUM(AA50:AD50) -> -2682.8238 | AF50: =AG49 -> -265908.92 | AG50: =AF50+AE50 -> -268591.75 | AQ50: =AE50 -> -2682.8238 | AR50: =AQ50 -> -2682.8238
A51: =YEAR(C51) -> 2025 | B51: ="Q"&(QUOTIENT(MONTH(C51),3.1)+1) -> Q2 | C51: 45751 | D51: =DRE!D51 -> 6013.1159 | G51: 300 | J51: =D51*6% -> 360.78695 | K51: =L51+M51 -> 8645.2403 | L51: =Financiamento!D60 -> 7087.5152 | M51: =Financiamento!C60 -> 1557.7251 | Q51: =D51 -> 6013.1159 | R51: =-SUM(F48:I48) -> -300 | S51: =SUM(Q51:R51) -> 5713.1159 | U51: =SUM(S51:T51) -> 5713.1159 | V51: =-M48 -> -1875.3361 | W51: =SUM(U51:V51) -> 3837.7798 | X51: =-J48 -> -241.54793 | Y51: =SUM(W51:X51) -> 3596.2318 | AA51: =S51 -> 5713.1159 | AB51: =-O48 -> 0 | AC51: =N51 -> 0 | AD51: =-K48 -> -8645.2403 | AE51: =SUM(AA51:AD51) -> -2932.1245 | AF51: =AG50 -> -268591.75 | AG51: =AF51+AE51 -> -271523.87 | AQ51: =AE51 -> -2932.1245 | AR51: =AQ51 -> -2932.1245
A52: =YEAR(C52) -> 2025 | B52: ="Q"&(QUOTIENT(MONTH(C52),3.1)+1) -> Q2 | C52: 45752 | D52: =DRE!D52 -> 6234.2217 | G52: 300 | J52: =D52*6% -> 374.0533 | K52: =L52+M52 -> 8645.2403 | L52: =Financiamento!D61 -> 7196.6629 | M52: =Financiamento!C61 -> 1448.5774 | Q52: =D52 -> 6234.2217 | R52: =-SUM(F48:I48) -> -300 | S52: =SUM(Q52:R52) -> 5934.2217 | U52: =SUM(S52:T52) -> 5934.2217 | V52: =-M48 -> -1875.3361 | W52: =SUM(U52:V52) -> 4058.8856 | X52: =-J48 -> -241.54793 | Y52: =SUM(W52:X52) -> 3817.3377 | AA52: =S52 -> 5934.2217 | AB52: =-O48 -> 0 | AC52: =N52 -> 0 | AD52: =-K48 -> -8645.2403 | AE52: =SUM(AA52:AD52) -> -2711.0187 | AF52: =AG51 -> -271523.87 | AG52: =AF52+AE52 -> -274234.89 | AQ52: =AE52 -> -2711.0187 | AR52: =AQ52 -> -2711.0187
A53: =YEAR(C53) -> 2025 | B53: ="Q"&(QUOTIENT(MONTH(C53),3.1)+1) -> Q2 | C53: 45753 | D53: =DRE!D53 -> 9274.0665 | G53: 300 | J53: =D53*6% -> 556.44399 | K53: =L53+M53 -> 8645.2403 | L53: =Financiamento!D62 -> 7307.4915 | M53: =Financiamento!C62 -> 1337.7488 | Q53: =D53 -> 9274.0665 | R53: =-SUM(F48:I48) -> -300 | S53: =SUM(Q53:R53) -> 8974.0665 | U53: =SUM(S53:T53) -> 8974.0665 | V53: =-M48 -> -1875.3361 | W53: =SUM(U53:V53) -> 7098.7304 | X53: =-J48 -> -241.54793 | Y53: =SUM(W53:X53) -> 6857.1825 | AA53: =S53 -> 8974.0665 | AB53: =-O48 -> 0 | AC53: =N53 -> 0 | AD53: =-K48 -> -8645.2403 | AE53: =SUM(AA53:AD53) -> 328.82617 | AF53: =AG52 -> -274234.89 | AG53: =AF53+AE53 -> -273906.06 | AQ53: =AE53 -> 328.82617 | AR53: =AQ53 -> 328.82617
A54: =YEAR(C54) -> 2025 | B54: ="Q"&(QUOTIENT(MONTH(C54),3.1)+1) -> Q2 | C54: 45754 | D54: =DRE!D54 -> 6975.2469 | G54: 300 | J54: =D54*6% -> 418.51481 | K54: =L54+M54 -> 8645.2403 | L54: =Financiamento!D63 -> 7420.0269 | M54: =Financiamento!C63 -> 1225.2134 | Q54: =D54 -> 6975.2469 | R54: =-SUM(F48:I48) -> -300 | S54: =SUM(Q54:R54) -> 6675.2469 | U54: =SUM(S54:T54) -> 6675.2469 | V54: =-M48 -> -1875.3361 | W54: =SUM(U54:V54) -> 4799.9108 | X54: =-J48 -> -241.54793 | Y54: =SUM(W54:X54) -> 4558.3628 | AA54: =S54 -> 6675.2469 | AB54: =-O48 -> 0 | AC54: =N54 -> 0 | AD54: =-K48 -> -8645.2403 | AE54: =SUM(AA54:AD54) -> -1969.9935 | AF54: =AG53 -> -273906.06 | AG54: =AF54+AE54 -> -275876.06 | AQ54: =AE54 -> -1969.9935 | AR54: =AQ54 -> -1969.9935
A55: =YEAR(C55) -> 2025 | B55: ="Q"&(QUOTIENT(MONTH(C55),3.1)+1) -> Q2 | C55: 45755 | D55: =DRE!D55 -> 8258.9165 | G55: 300 | J55: =D55*6% -> 495.53499 | K55: =L55+M55 -> 8645.2403 | L55: =Financiamento!D64 -> 7534.2953 | M55: =Financiamento!C64 -> 1110.945 | Q55: =D55 -> 8258.9165 | R55: =-SUM(F48:I48) -> -300 | S55: =SUM(Q55:R55) -> 7958.9165 | U55: =SUM(S55:T55) -> 7958.9165 | V55: =-M48 -> -1875.3361 | W55: =SUM(U55:V55) -> 6083.5804 | X55: =-J48 -> -241.54793 | Y55: =SUM(W55:X55) -> 5842.0324 | AA55: =S55 -> 7958.9165 | AB55: =-O48 -> 0 | AC55: =N55 -> 0 | AD55: =-K48 -> -8645.2403 | AE55: =SUM(AA55:AD55) -> -686.32389 | AF55: =AG54 -> -275876.06 | AG55: =AF55+AE55 -> -276562.38 | AQ55: =AE55 -> -686.32389 | AR55: =AQ55 -> -686.32389
A56: =YEAR(C56) -> 2025 | B56: ="Q"&(QUOTIENT(MONTH(C56),3.1)+1) -> Q2 | C56: 45756 | D56: =DRE!D56 -> 9620.5779 | G56: 300 | J56: =D56*6% -> 577.23467 | K56: =L56+M56 -> 8645.2403 | L56: =Financiamento!D65 -> 7650.3235 | M56: =Financiamento!C65 -> 994.91686 | Q56: =D56 -> 9620.5779 | R56: =-SUM(F48:I48) -> -300 | S56: =SUM(Q56:R56) -> 9320.5779 | U56: =SUM(S56:T56) -> 9320.5779 | V56: =-M48 -> -1875.3361 | W56: =SUM(U56:V56) -> 7445.2418 | X56: =-J48 -> -241.54793 | Y56: =SUM(W56:X56) -> 7203.6939 | AA56: =S56 -> 9320.5779 | AB56: =-O48 -> 0 | AC56: =N56 -> 0 | AD56: =-K48 -> -8645.2403 | AE56: =SUM(AA56:AD56) -> 675.33755 | AF56: =AG55 -> -276562.38 | AG56: =AF56+AE56 -> -275887.04 | AQ56: =AE56 -> 675.33755 | AR56: =AQ56 -> 675.33755
A57: =YEAR(C57) -> 2025 | B57: ="Q"&(QUOTIENT(MONTH(C57),3.1)+1) -> Q2 | C57: 45757 | D57: =DRE!D57 -> 9504.8005 | G57: 300 | J57: =D57*6% -> 570.28803 | K57: =L57+M57 -> 8645.2403 | L57: =Financiamento!D66 -> 7768.1385 | M57: =Financiamento!C66 -> 877.10188 | Q57: =D57 -> 9504.8005 | R57: =-SUM(F48:I48) -> -300 | S57: =SUM(Q57:R57) -> 9204.8005 | U57: =SUM(S57:T57) -> 9204.8005 | V57: =-M48 -> -1875.3361 | W57: =SUM(U57:V57) -> 7329.4644 | X57: =-J48 -> -241.54793 | Y57: =SUM(W57:X57) -> 7087.9165 | AA57: =S57 -> 9204.8005 | AB57: =-O48 -> 0 | AC57: =N57 -> 0 | AD57: =-K48 -> -8645.2403 | AE57: =SUM(AA57:AD57) -> 559.5602 | AF57: =AG56 -> -275887.04 | AG57: =AF57+AE57 -> -275327.48 | AQ57: =AE57 -> 559.5602 | AR57: =AQ57 -> 559.5602
A58: =YEAR(C58) -> 2026 | B58: ="Q"&(QUOTIENT(MONTH(C58),3.1)+1) -> Q1 | C58: 46054 | D58: {=7000*(53%*0.4+47%*0.85)+2800*0.9*_xludf.IFS(B58="Q1",1.3,B58="Q2",0.7,B58="Q3",0.8,B58="Q4",1.2)} -> #NAME? | E58: 2087.3269 | F58: =IF(MONTH(C58)=11,2000,0) -> 0 | G58: 300 | J58: =(D58+E58)*6% -> #NAME? | K58: =L58+M58 -> 8645.2403 | L58: =Financiamento!D67 -> 7887.7678 | M58: =Financiamento!C67 -> 757.47255 | Q58: =SUM(D58:E58) -> #NAME? | R58: =-SUM(F58:I58) -> -300 | S58: =SUM(Q58:R58) -> #NAME? | U58: =SUM(S58:T58) -> #NAME? | V58: =-M58 -> -757.47255 | W58: =SUM(U58:V58) -> #NAME? | X58: =-J58 -> #NAME? | Y58: =SUM(W58:X58) -> #NAME? | AA58: =S58 -> #NAME? | AB58: =-O58 -> 0 | AC58: =N58 -> 0 | AD58: =-K58 -> -8645.2403 | AE58: =SUM(AA58:AD58) -> #NAME? | AF58: =AG57 -> -275327.48 | AG58: =AF58+AE58 -> #NAME? | AQ58: =AE58-E58+150+200 -> #NAME? | AR58: =AQ58 -> #NAME?
A59: =YEAR(C59) -> 2026 | B59: ="Q"&(QUOTIENT(MONTH(C59),3.1)+1) -> Q1 | C59: 46082 | D59: {=7000*(53%*0.4+47%*0.85)+2800*0.9*_xludf.IFS(B59="Q1",1.3,B59="Q2",0.7,B59="Q3",0.8,B59="Q4",1.2)} -> #NAME? | E59: 2278.9626 | F59: =IF(MONTH(C59)=11,2000,0) -> 0 | G59: 300 | J59: =(D59+E59)*6% -> #NAME? | K59: =L59+M59 -> 8645.2403 | L59: =Financiamento!D68 -> 8009.2394 | M59: =Financiamento!C68 -> 636.00093 | Q59: =SUM(D59:E59) -> #NAME? | R59: =-SUM(F59:I59) -> -300 | S59: =SUM(Q59:R59) -> #NAME? | U59: =SUM(S59:T59) -> #NAME? | V59: =-M59 -> -636.00093 | W59: =SUM(U59:V59) -> #NAME? | X59: =-J59 -> #NAME? | Y59: =SUM(W59:X59) -> #NAME? | AA59: =S59 -> #NAME? | AB59: =-O59 -> 0 | AC59: =N59 -> 0 | AD59: =-K59 -> -8645.2403 | AE59: =SUM(AA59:AD59) -> #NAME? | AF59: =AG58 -> #NAME? | AG59: =AF59+AE59 -> #NAME? | AQ59: =AE59-E59+150+200 -> #NAME? | AR59: =AQ59 -> #NAME?
A60: =YEAR(C60) -> 2026 | B60: ="Q"&(QUOTIENT(MONTH(C60),3.1)+1) -> Q2 | C60: 46113 | D60: {=7000*(53%*0.4+47%*0.85)+2800*0.9*_xludf.IFS(B60="Q1",1.3,B60="Q2",0.7,B60="Q3",0.8,B60="Q4",1.2)} -> #NAME? | E60: 2413.8216 | F60: =IF(MONTH(C60)=11,2000,0) -> 0 | G60: 300 | J60: =(D60+E60)*6% -> #NAME? | K60: =L60+M60 -> 8645.2403 | L60: =Financiamento!D69 -> 8132.5817 | M60: =Financiamento!C69 -> 512.65864 | Q60: =SUM(D60:E60) -> #NAME? | R60: =-SUM(F60:I60) -> -300 | S60: =SUM(Q60:R60) -> #NAME? | U60: =SUM(S60:T60) -> #NAME? | V60: =-M60 -> -512.65864 | W60: =SUM(U60:V60) -> #NAME? | X60: =-J60 -> #NAME? | Y60: =SUM(W60:X60) -> #NAME? | AA60: =S60 -> #NAME? | AB60: =-O60 -> 0 | AC60: =N60 -> 0 | AD60: =-K60 -> -8645.2403 | AE60: =SUM(AA60:AD60) -> #NAME? | AF60: =AG59 -> #NAME? | AG60: =AF60+AE60 -> #NAME? | AQ60: =AE60-E60+150+200 -> #NAME? | AR60: =AQ60 -> #NAME?
A61: =YEAR(C61) -> 2026 | B61: ="Q"&(QUOTIENT(MONTH(C61),3.1)+1) -> Q2 | C61: 46143 | D61: {=7000*(53%*0.4+47%*0.85)+2800*0.9*_xludf.IFS(B61="Q1",1.3,B61="Q2",0.7,B61="Q3",0.8,B61="Q4",1.2)} -> #NAME? | E61: 2325.7396 | F61: =IF(MONTH(C61)=11,2000,0) -> 0 | G61: 300 | J61: =(D61+E61)*6% -> #NAME? | K61: =L61+M61 -> 8645.2403 | L61: =Financiamento!D70 -> 8257.8235 | M61: =Financiamento!C70 -> 387.41688 | Q61: =SUM(D61:E61) -> #NAME? | R61: =-SUM(F61:I61) -> -300 | S61: =SUM(Q61:R61) -> #NAME? | U61: =SUM(S61:T61) -> #NAME? | V61: =-M61 -> -387.41688 | W61: =SUM(U61:V61) -> #NAME? | X61: =-J61 -> #NAME? | Y61: =SUM(W61:X61) -> #NAME? | AA61: =S61 -> #NAME? | AB61: =-O61 -> 0 | AC61: =N61 -> 0 | AD61: =-K61 -> -8645.2403 | AE61: =SUM(AA61:AD61) -> #NAME? | AF61: =AG60 -> #NAME? | AG61: =AF61+AE61 -> #NAME? | AQ61: =AE61-E61+150+200 -> #NAME? | AR61: =AQ61 -> #NAME?
A62: =YEAR(C62) -> 2026 | B62: ="Q"&(QUOTIENT(MONTH(C62),3.1)+1) -> Q2 | C62: 46174 | D62: {=7000*(53%*0.4+47%*0.85)+2800*0.9*_xludf.IFS(B62="Q1",1.3,B62="Q2",0.7,B62="Q3",0.8,B62="Q4",1.2)} -> #NAME? | E62: 2451.3033 | F62: =IF(MONTH(C62)=11,2000,0) -> 0 | G62: 300 | J62: =(D62+E62)*6% -> #NAME? | K62: =L62+M62 -> 8645.2403 | L62: =Financiamento!D71 -> 8384.9939 | M62: =Financiamento!C71 -> 260.2464 | Q62: =SUM(D62:E62) -> #NAME? | R62: =-SUM(F62:I62) -> -300 | S62: =SUM(Q62:R62) -> #NAME? | U62: =SUM(S62:T62) -> #NAME? | V62: =-M62 -> -260.2464 | W62: =SUM(U62:V62) -> #NAME? | X62: =-J62 -> #NAME? | Y62: =SUM(W62:X62) -> #NAME? | AA62: =S62 -> #NAME? | AB62: =-O62 -> 0 | AC62: =N62 -> 0 | AD62: =-K62 -> -8645.2403 | AE62: =SUM(AA62:AD62) -> #NAME? | AF62: =AG61 -> #NAME? | AG62: =AF62+AE62 -> #NAME? | AQ62: =AE62-E62+150+200 -> #NAME? | AR62: =AQ62 -> #NAME?
A63: =YEAR(C63) -> 2026 | B63: ="Q"&(QUOTIENT(MONTH(C63),3.1)+1) -> Q3 | C63: 46204 | D63: {=7000*(53%*0.4+47%*0.85)+2800*0.9*_xludf.IFS(B63="Q1",1.3,B63="Q2",0.7,B63="Q3",0.8,B63="Q4",1.2)} -> #NAME? | E63: 2258.2725 | F63: =IF(MONTH(C63)=11,2000,0) -> 0 | G63: 300 | J63: =(D63+E63)*6% -> #NAME? | K63: =L63+M63 -> 8645.2403 | L63: =Financiamento!D72 -> 8514.1228 | M63: =Financiamento!C72 -> 131.11749 | Q63: =SUM(D63:E63) -> #NAME? | R63: =-SUM(F63:I63) -> -300 | S63: =SUM(Q63:R63) -> #NAME? | U63: =SUM(S63:T63) -> #NAME? | V63: =-M63 -> -131.11749 | W63: =SUM(U63:V63) -> #NAME? | X63: =-J63 -> #NAME? | Y63: =SUM(W63:X63) -> #NAME? | AA63: =S63 -> #NAME? | AB63: =-O63 -> 0 | AC63: =N63 -> 0 | AD63: =-K63 -> -8645.2403 | AE63: =SUM(AA63:AD63) -> #NAME? | AF63: =AG62 -> #NAME? | AG63: =AF63+AE63 -> #NAME? | AQ63: =AE63-E63+150+200 -> #NAME? | AR63: =AQ63 -> #NAME?
A64: =YEAR(C64) -> 2026 | B64: ="Q"&(QUOTIENT(MONTH(C64),3.1)+1) -> Q3 | C64: 46235 | D64: {=7000*(53%*0.4+47%*0.85)+2800*0.9*_xludf.IFS(B64="Q1",1.3,B64="Q2",0.7,B64="Q3",0.8,B64="Q4",1.2)} -> #NAME? | E64: 2046.5009 | F64: =IF(MONTH(C64)=11,2000,0) -> 0 | G64: 300 | J64: =(D64+E64)*6% -> #NAME? | K64: =L64+M64 -> 0 | L64: =Financiamento!D73 -> 0 | M64: =Financiamento!C73 -> 0 | Q64: =SUM(D64:E64) -> #NAME? | R64: =-SUM(F64:I64) -> -300 | S64: =SUM(Q64:R64) -> #NAME? | U64: =SUM(S64:T64) -> #NAME? | V64: =-M64 -> 0 | W64: =SUM(U64:V64) -> #NAME? | X64: =-J64 -> #NAME? | Y64: =SUM(W64:X64) -> #NAME? | AA64: =S64 -> #NAME? | AB64: =-O64 -> 0 | AC64: =N64 -> 0 | AD64: =-K64 -> 0 | AE64: =SUM(AA64:AD64) -> #NAME? | AF64: =AG63 -> #NAME? | AG64: =AF64+AE64 -> #NAME? | AQ64: =(AE64-E64+150+200) -> #NAME? | AR64: =AQ64*1.4 -> #NAME?
A65: =YEAR(C65) -> 2026 | B65: ="Q"&(QUOTIENT(MONTH(C65),3.1)+1) -> Q3 | C65: 46266 | D65: {=7000*(53%*0.4+47%*0.85)+2800*0.9*_xludf.IFS(B65="Q1",1.3,B65="Q2",0.7,B65="Q3",0.8,B65="Q4",1.2)} -> #NAME? | E65: 1960.293 | F65: =IF(MONTH(C65)=11,2000,0) -> 0 | G65: 300 | J65: =(D65+E65)*6% -> #NAME? | K65: =L65+M65 -> 0 | L65: =Financiamento!D74 -> 0 | M65: =Financiamento!C74 -> 0 | Q65: =SUM(D65:E65) -> #NAME? | R65: =-SUM(F65:I65) -> -300 | S65: =SUM(Q65:R65) -> #NAME? | U65: =SUM(S65:T65) -> #NAME? | V65: =-M65 -> 0 | W65: =SUM(U65:V65) -> #NAME? | X65: =-J65 -> #NAME? | Y65: =SUM(W65:X65) -> #NAME? | AA65: =S65 -> #NAME? | AB65: =-O65 -> 0 | AC65: =N65 -> 0 | AD65: =-K65 -> 0 | AE65: =SUM(AA65:AD65) -> #NAME? | AF65: =AG64 -> #NAME? | AG65: =AF65+AE65 -> #NAME? | AQ65: =(AE65-E65+150+200) -> #NAME? | AR65: =AQ65*1.4 -> #NAME?
A66: =YEAR(C66) -> 2026 | B66: ="Q"&(QUOTIENT(MONTH(C66),3.1)+1) -> Q4 | C66: 46296 | D66: {=7000*(53%*0.4+47%*0.85)+2800*0.9*_xludf.IFS(B66="Q1",1.3,B66="Q2",0.7,B66="Q3",0.8,B66="Q4",1.2)} -> #NAME? | E66: 2093.3531 | F66: =IF(MONTH(C66)=11,2000,0) -> 0 | G66: 300 | J66: =(D66+E66)*6% -> #NAME? | K66: =L66+M66 -> 0 | L66: =Financiamento!D75 -> 0 | M66: =Financiamento!C75 -> 0 | Q66: =SUM(D66:E66) -> #NAME? | R66: =-SUM(F66:I66) -> -300 | S66: =SUM(Q66:R66) -> #NAME? | U66: =SUM(S66:T66) -> #NAME? | V66: =-M66 -> 0 | W66: =SUM(U66:V66) -> #NAME? | X66: =-J66 -> #NAME? | Y66: =SUM(W66:X66) -> #NAME? | AA66: =S66 -> #NAME? | AB66: =-O66 -> 0 | AC66: =N66 -> 0 | AD66: =-K66 -> 0 | AE66: =SUM(AA66:AD66) -> #NAME? | AF66: =AG65 -> #NAME? | AG66: =AF66+AE66 -> #NAME? | AQ66: =(AE66-E66+150+200) -> #NAME? | AR66: =AQ66*1.4 -> #NAME?
A67: =YEAR(C67) -> 2026 | B67: ="Q"&(QUOTIENT(MONTH(C67),3.1)+1) -> Q4 | C67: 46327 | D67: {=7000*(53%*0.4+47%*0.85)+2800*0.9*_xludf.IFS(B67="Q1",1.3,B67="Q2",0.7,B67="Q3",0.8,B67="Q4",1.2)} -> #NAME? | E67: 2258.2725 | F67: =IF(MONTH(C67)=11,2000,0) -> 2000 | G67: 300 | J67: =(D67+E67)*6% -> #NAME? | K67: =L67+M67 -> 0 | L67: =Financiamento!D76 -> 0 | M67: =Financiamento!C76 -> 0 | Q67: =SUM(D67:E67) -> #NAME? | R67: =-SUM(F67:I67) -> -2300 | S67: =SUM(Q67:R67) -> #NAME? | U67: =SUM(S67:T67) -> #NAME? | V67: =-M67 -> 0 | W67: =SUM(U67:V67) -> #NAME? | X67: =-J67 -> #NAME? | Y67: =SUM(W67:X67) -> #NAME? | AA67: =S67 -> #NAME? | AB67: =-O67 -> 0 | AC67: =N67 -> 0 | AD67: =-K67 -> 0 | AE67: =SUM(AA67:AD67) -> #NAME? | AF67: =AG66 -> #NAME? | AG67: =AF67+AE67 -> #NAME? | AQ67: =(AE67-E67+150+200) -> #NAME? | AR67: =AQ67*1.4 -> #NAME?
A68: =YEAR(C68) -> 2026 | B68: ="Q"&(QUOTIENT(MONTH(C68),3.1)+1) -> Q4 | C68: 46357 | D68: {=7000*(53%*0.4+47%*0.85)+2800*0.9*_xludf.IFS(B68="Q1",1.3,B68="Q2",0.7,B68="Q3",0.8,B68="Q4",1.2)} -> #NAME? | E68: 2136.457 | F68: =IF(MONTH(C68)=11,2000,0) -> 0 | G68: 300 | J68: =(D68+E68)*6% -> #NAME? | K68: =L68+M68 -> 0 | L68: =Financiamento!D77 -> 0 | M68: =Financiamento!C77 -> 0 | Q68: =SUM(D68:E68) -> #NAME? | R68: =-SUM(F68:I68) -> -300 | S68: =SUM(Q68:R68) -> #NAME? | U68: =SUM(S68:T68) -> #NAME? | V68: =-M68 -> 0 | W68: =SUM(U68:V68) -> #NAME? | X68: =-J68 -> #NAME? | Y68: =SUM(W68:X68) -> #NAME? | AA68: =S68 -> #NAME? | AB68: =-O68 -> 0 | AC68: =N68 -> 0 | AD68: =-K68 -> 0 | AE68: =SUM(AA68:AD68) -> #NAME? | AF68: =AG67 -> #NAME? | AG68: =AF68+AE68 -> #NAME? | AQ68: =(AE68-E68+150+200) -> #NAME? | AR68: =AQ68*1.4 -> #NAME?
A69: =YEAR(C69) -> 2027 | B69: ="Q"&(QUOTIENT(MONTH(C69),3.1)+1) -> Q1 | C69: 46388 | D69: {=7000*(53%*0.4+47%*0.85)+2800*0.9*_xludf.IFS(B69="Q1",1.3,B69="Q2",0.7,B69="Q3",0.8,B69="Q4",1.2)} -> #NAME? | E69: 2170.1905 | F69: =IF(MONTH(C69)=11,2000,0) -> 0 | G69: 300 | J69: =(D69+E69)*6% -> #NAME? | K69: =L69+M69 -> 0 | L69: =Financiamento!D78 -> 0 | M69: =Financiamento!C78 -> 0 | Q69: =SUM(D69:E69) -> #NAME? | R69: =-SUM(F69:I69) -> -300 | S69: =SUM(Q69:R69) -> #NAME? | U69: =SUM(S69:T69) -> #NAME? | V69: =-M69 -> 0 | W69: =SUM(U69:V69) -> #NAME? | X69: =-J69 -> #NAME? | Y69: =SUM(W69:X69) -> #NAME? | AA69: =S69 -> #NAME? | AB69: =-O69 -> 0 | AC69: =N69 -> 0 | AD69: =-K69 -> 0 | AE69: =SUM(AA69:AD69) -> #NAME? | AF69: =AG68 -> #NAME? | AG69: =AF69+AE69 -> #NAME? | AQ69: =(AE69-E69+150+200) -> #NAME? | AR69: =AQ69*1.4 -> #NAME?
A70: =YEAR(C70) -> 2027 | B70: ="Q"&(QUOTIENT(MONTH(C70),3.1)+1) -> Q1 | C70: 46419 | D70: {=7000*(53%*0.4+47%*0.85)+2800*0.9*_xludf.IFS(B70="Q1",1.3,B70="Q2",0.7,B70="Q3",0.8,B70="Q4",1.2)} -> #NAME? | E70: 2082.1085 | F70: =IF(MONTH(C70)=11,2000,0) -> 0 | G70: 300 | J70: =(D70+E70)*6% -> #NAME? | K70: =L70+M70 -> 0 | L70: =Financiamento!D79 -> 0 | M70: =Financiamento!C79 -> 0 | Q70: =SUM(D70:E70) -> #NAME? | R70: =-SUM(F70:I70) -> -300 | S70: =SUM(Q70:R70) -> #NAME? | U70: =SUM(S70:T70) -> #NAME? | V70: =-M70 -> 0 | W70: =SUM(U70:V70) -> #NAME? | X70: =-J70 -> #NAME? | Y70: =SUM(W70:X70) -> #NAME? | AA70: =S70 -> #NAME? | AB70: =-O70 -> 0 | AC70: =N70 -> 0 | AD70: =-K70 -> 0 | AE70: =SUM(AA70:AD70) -> #NAME? | AF70: =AG69 -> #NAME? | AG70: =AF70+AE70 -> #NAME? | AQ70: =(AE70-E70+150+200) -> #NAME? | AR70: =AQ70*1.4 -> #NAME?
A71: =YEAR(C71) -> 2027 | B71: ="Q"&(QUOTIENT(MONTH(C71),3.1)+1) -> Q1 | C71: 46447 | D71: {=7000*(53%*0.4+47%*0.85)+2800*0.9*_xludf.IFS(B71="Q1",1.3,B71="Q2",0.7,B71="Q3",0.8,B71="Q4",1.2)} -> #NAME? | E71: 2273.2652 | F71: =IF(MONTH(C71)=11,2000,0) -> 0 | G71: 300 | J71: =(D71+E71)*6% -> #NAME? | K71: =L71+M71 -> 0 | L71: =Financiamento!D80 -> 0 | M71: =Financiamento!C80 -> 0 | Q71: =SUM(D71:E71) -> #NAME? | R71: =-SUM(F71:I71) -> -300 | S71: =SUM(Q71:R71) -> #NAME? | U71: =SUM(S71:T71) -> #NAME? | V71: =-M71 -> 0 | W71: =SUM(U71:V71) -> #NAME? | X71: =-J71 -> #NAME? | Y71: =SUM(W71:X71) -> #NAME? | AA71: =S71 -> #NAME? | AB71: =-O71 -> 0 | AC71: =N71 -> 0 | AD71: =-K71 -> 0 | AE71: =SUM(AA71:AD71) -> #NAME? | AF71: =AG70 -> #NAME? | AG71: =AF71+AE71 -> #NAME? | AQ71: =(AE71-E71+150+200) -> #NAME? | AR71: =AQ71*1.4 -> #NAME?
A72: =YEAR(C72) -> 2027 | B72: ="Q"&(QUOTIENT(MONTH(C72),3.1)+1) -> Q2 | C72: 46478 | D72: {=7000*(53%*0.4+47%*0.85)+2800*0.9*_xludf.IFS(B72="Q1",1.3,B72="Q2",0.7,B72="Q3",0.8,B72="Q4",1.2)} -> #NAME? | E72: 2407.7719 | F72: =IF(MONTH(C72)=11,2000,0) -> 0 | G72: 300 | J72: =(D72+E72)*6% -> #NAME? | K72: =L72+M72 -> 0 | L72: =Financiamento!D81 -> 0 | M72: =Financiamento!C81 -> 0 | Q72: =SUM(D72:E72) -> #NAME? | R72: =-SUM(F72:I72) -> -300 | S72: =SUM(Q72:R72) -> #NAME? | U72: =SUM(S72:T72) -> #NAME? | V72: =-M72 -> 0 | W72: =SUM(U72:V72) -> #NAME? | X72: =-J72 -> #NAME? | Y72: =SUM(W72:X72) -> #NAME? | AA72: =S72 -> #NAME? | AB72: =-O72 -> 0 | AC72: =N72 -> 0 | AD72: =-K72 -> 0 | AE72: =SUM(AA72:AD72) -> #NAME? | AF72: =AG71 -> #NAME? | AG72: =AF72+AE72 -> #NAME? | AQ72: =(AE72-E72+150+200) -> #NAME? | AR72: =AQ72*1.4 -> #NAME?
A73: =YEAR(C73) -> 2027 | B73: ="Q"&(QUOTIENT(MONTH(C73),3.1)+1) -> Q2 | C73: 46508 | D73: {=7000*(53%*0.4+47%*0.85)+2800*0.9*_xludf.IFS(B73="Q1",1.3,B73="Q2",0.7,B73="Q3",0.8,B73="Q4",1.2)} -> #NAME? | E73: 2319.9107 | F73: =IF(MONTH(C73)=11,2000,0) -> 0 | G73: 300 | J73: =(D73+E73)*6% -> #NAME? | K73: =L73+M73 -> 0 | L73: =Financiamento!D82 -> 0 | M73: =Financiamento!C82 -> 0 | Q73: =SUM(D73:E73) -> #NAME? | R73: =-SUM(F73:I73) -> -300 | S73: =SUM(Q73:R73) -> #NAME? | U73: =SUM(S73:T73) -> #NAME? | V73: =-M73 -> 0 | W73: =SUM(U73:V73) -> #NAME? | X73: =-J73 -> #NAME? | Y73: =SUM(W73:X73) -> #NAME? | AA73: =S73 -> #NAME? | AB73: =-O73 -> 0 | AC73: =N73 -> 0 | AD73: =-K73 -> 0 | AE73: =SUM(AA73:AD73) -> #NAME? | AF73: =AG72 -> #NAME? | AG73: =AF73+AE73 -> #NAME? | AQ73: =(AE73-E73+150+200) -> #NAME? | AR73: =AQ73*1.4 -> #NAME?
A74: =YEAR(C74) -> 2027 | B74: ="Q"&(QUOTIENT(MONTH(C74),3.1)+1) -> Q2 | C74: 46539 | D74: {=7000*(53%*0.4+47%*0.85)+2800*0.9*_xludf.IFS(B74="Q1",1.3,B74="Q2",0.7,B74="Q3",0.8,B74="Q4",1.2)} -> #NAME? | E74: 2445.1597 | F74: =IF(MONTH(C74)=11,2000,0) -> 0 | G74: 300 | J74: =(D74+E74)*6% -> #NAME? | K74: =L74+M74 -> 0 | L74: =Financiamento!D83 -> 0 | M74: =Financiamento!C83 -> 0 | Q74: =SUM(D74:E74) -> #NAME? | R74: =-SUM(F74:I74) -> -300 | S74: =SUM(Q74:R74) -> #NAME? | U74: =SUM(S74:T74) -> #NAME? | V74: =-M74 -> 0 | W74: =SUM(U74:V74) -> #NAME? | X74: =-J74 -> #NAME? | Y74: =SUM(W74:X74) -> #NAME? | AA74: =S74 -> #NAME? | AB74: =-O74 -> 0 | AC74: =N74 -> 0 | AD74: =-K74 -> 0 | AE74: =SUM(AA74:AD74) -> #NAME? | AF74: =AG73 -> #NAME? | AG74: =AF74+AE74 -> #NAME? | AQ74: =(AE74-E74+150+200) -> #NAME? | AR74: =AQ74*1.4 -> #NAME?
A75: =YEAR(C75) -> 2027 | B75: ="Q"&(QUOTIENT(MONTH(C75),3.1)+1) -> Q3 | C75: 46569 | D75: {=7000*(53%*0.4+47%*0.85)+2800*0.9*_xludf.IFS(B75="Q1",1.3,B75="Q2",0.7,B75="Q3",0.8,B75="Q4",1.2)} -> #NAME? | E75: 2252.6127 | F75: =IF(MONTH(C75)=11,2000,0) -> 0 | G75: 300 | J75: =(D75+E75)*6% -> #NAME? | K75: =L75+M75 -> 0 | L75: =Financiamento!D84 -> 0 | M75: =Financiamento!C84 -> 0 | Q75: =SUM(D75:E75) -> #NAME? | R75: =-SUM(F75:I75) -> -300 | S75: =SUM(Q75:R75) -> #NAME? | U75: =SUM(S75:T75) -> #NAME? | V75: =-M75 -> 0 | W75: =SUM(U75:V75) -> #NAME? | X75: =-J75 -> #NAME? | Y75: =SUM(W75:X75) -> #NAME? | AA75: =S75 -> #NAME? | AB75: =-O75 -> 0 | AC75: =N75 -> 0 | AD75: =-K75 -> 0 | AE75: =SUM(AA75:AD75) -> #NAME? | AF75: =AG74 -> #NAME? | AG75: =AF75+AE75 -> #NAME? | AQ75: =(AE75-E75+150+200) -> #NAME? | AR75: =AQ75*1.4 -> #NAME?
... A167: =YEAR(C167) -> 2035 | B167: ="Q"&(QUOTIENT(MONTH(C167),3.1)+1) -> Q1 | C167: 49369 | D167: {=7000*(53%*0.4+47%*0.85)+2800*0.9*_xludf.IFS(B167="Q1",1.3,B167="Q2",0.7,B167="Q3",0.8,B167="Q4",1.2)} -> #NAME? | E167: 1113.843 | F167: =IF(MONTH(C167)=11,2000,0) -> 0 | G167: 300 | J167: =(D167+E167)*6% -> #NAME? | K167: =L167+M167 -> 0 | L167: =Financiamento!D176 -> 0 | M167: =Financiamento!C176 -> 0 | Q167: =SUM(D167:E167) -> #NAME? | R167: =-SUM(F167:I167) -> -300 | S167: =SUM(Q167:R167) -> #NAME? | U167: =SUM(S167:T167) -> #NAME? | V167: =-M167 -> 0 | W167: =SUM(U167:V167) -> #NAME? | X167: =-J167 -> #NAME? | Y167: =SUM(W167:X167) -> #NAME? | AA167: =S167 -> #NAME? | AB167: =-O167 -> 0 | AC167: =N167 -> 0 | AD167: =-K167 -> 0 | AE167: =SUM(AA167:AD167) -> #NAME? | AF167: =AG166 -> #NAME? | AG167: =AF167+AE167 -> #NAME? | AQ167: =(AE167-E167+150+200) -> #NAME? | AR167: =AQ167*1.4 -> #NAME?
A168: =YEAR(C168) -> 2035 | B168: ="Q"&(QUOTIENT(MONTH(C168),3.1)+1) -> Q2 | C168: 49400 | D168: {=7000*(53%*0.4+47%*0.85)+2800*0.9*_xludf.IFS(B168="Q1",1.3,B168="Q2",0.7,B168="Q3",0.8,B168="Q4",1.2)} -> #NAME? | F168: =IF(MONTH(C168)=11,2000,0) -> 0 | G168: 300 | J168: =(D168+E168)*6% -> #NAME? | K168: =L168+M168 -> 0 | L168: =Financiamento!D177 -> 0 | M168: =Financiamento!C177 -> 0 | Q168: =SUM(D168:E168) -> #NAME? | R168: =-SUM(F168:I168) -> -300 | S168: =SUM(Q168:R168) -> #NAME? | U168: =SUM(S168:T168) -> #NAME? | V168: =-M168 -> 0 | W168: =SUM(U168:V168) -> #NAME? | X168: =-J168 -> #NAME? | Y168: =SUM(W168:X168) -> #NAME? | AA168: =S168 -> #NAME? | AB168: =-O168 -> 0 | AC168: =N168 -> 0 | AD168: =-K168 -> 0 | AE168: =SUM(AA168:AD168) -> #NAME? | AF168: =AG167 -> #NAME? | AG168: =AF168+AE168 -> #NAME? | AQ168: =(AE168-E168+150+200) -> #NAME? | AR168: =AQ168*1.4 -> #NAME?
A169: =YEAR(C169) -> 2035 | B169: ="Q"&(QUOTIENT(MONTH(C169),3.1)+1) -> Q2 | C169: 49430 | D169: {=7000*(53%*0.4+47%*0.85)+2800*0.9*_xludf.IFS(B169="Q1",1.3,B169="Q2",0.7,B169="Q3",0.8,B169="Q4",1.2)} -> #NAME? | F169: =IF(MONTH(C169)=11,2000,0) -> 0 | G169: 300 | J169: =(D169+E169)*6% -> #NAME? | K169: =L169+M169 -> 0 | L169: =Financiamento!D178 -> 0 | M169: =Financiamento!C178 -> 0 | Q169: =SUM(D169:E169) -> #NAME? | R169: =-SUM(F169:I169) -> -300 | S169: =SUM(Q169:R169) -> #NAME? | U169: =SUM(S169:T169) -> #NAME? | V169: =-M169 -> 0 | W169: =SUM(U169:V169) -> #NAME? | X169: =-J169 -> #NAME? | Y169: =SUM(W169:X169) -> #NAME? | AA169: =S169 -> #NAME? | AB169: =-O169 -> 0 | AC169: =N169 -> 0 | AD169: =-K169 -> 0 | AE169: =SUM(AA169:AD169) -> #NAME? | AF169: =AG168 -> #NAME? | AG169: =AF169+AE169 -> #NAME? | AQ169: =(AE169-E169+150+200) -> #NAME? | AR169: =AQ169*1.4 -> #NAME?
A170: =YEAR(C170) -> 2035 | B170: ="Q"&(QUOTIENT(MONTH(C170),3.1)+1) -> Q2 | C170: 49461 | D170: {=7000*(53%*0.4+47%*0.85)+2800*0.9*_xludf.IFS(B170="Q1",1.3,B170="Q2",0.7,B170="Q3",0.8,B170="Q4",1.2)} -> #NAME? | F170: =IF(MONTH(C170)=11,2000,0) -> 0 | G170: 300 | J170: =(D170+E170)*6% -> #NAME? | K170: =L170+M170 -> 0 | L170: =Financiamento!D179 -> 0 | M170: =Financiamento!C179 -> 0 | Q170: =SUM(D170:E170) -> #NAME? | R170: =-SUM(F170:I170) -> -300 | S170: =SUM(Q170:R170) -> #NAME? | U170: =SUM(S170:T170) -> #NAME? | V170: =-M170 -> 0 | W170: =SUM(U170:V170) -> #NAME? | X170: =-J170 -> #NAME? | Y170: =SUM(W170:X170) -> #NAME? | AA170: =S170 -> #NAME? | AB170: =-O170 -> 0 | AC170: =N170 -> 0 | AD170: =-K170 -> 0 | AE170: =SUM(AA170:AD170) -> #NAME? | AF170: =AG169 -> #NAME? | AG170: =AF170+AE170 -> #NAME? | AQ170: =(AE170-E170+150+200) -> #NAME? | AR170: =AQ170*1.4 -> #NAME?
A171: =YEAR(C171) -> 2035 | B171: ="Q"&(QUOTIENT(MONTH(C171),3.1)+1) -> Q3 | C171: 49491 | D171: {=7000*(53%*0.4+47%*0.85)+2800*0.9*_xludf.IFS(B171="Q1",1.3,B171="Q2",0.7,B171="Q3",0.8,B171="Q4",1.2)} -> #NAME? | F171: =IF(MONTH(C171)=11,2000,0) -> 0 | G171: 300 | J171: =(D171+E171)*6% -> #NAME? | K171: =L171+M171 -> 0 | L171: =Financiamento!D180 -> 0 | M171: =Financiamento!C180 -> 0 | Q171: =SUM(D171:E171) -> #NAME? | R171: =-SUM(F171:I171) -> -300 | S171: =SUM(Q171:R171) -> #NAME? | U171: =SUM(S171:T171) -> #NAME? | V171: =-M171 -> 0 | W171: =SUM(U171:V171) -> #NAME? | X171: =-J171 -> #NAME? | Y171: =SUM(W171:X171) -> #NAME? | AA171: =S171 -> #NAME? | AB171: =-O171 -> 0 | AC171: =N171 -> 0 | AD171: =-K171 -> 0 | AE171: =SUM(AA171:AD171) -> #NAME? | AF171: =AG170 -> #NAME? | AG171: =AF171+AE171 -> #NAME? | AQ171: =(AE171-E171+150+200) -> #NAME? | AR171: =AQ171*1.4 -> #NAME?
A172: =YEAR(C172) -> 2035 | B172: ="Q"&(QUOTIENT(MONTH(C172),3.1)+1) -> Q3 | C172: 49522 | D172: {=7000*(53%*0.4+47%*0.85)+2800*0.9*_xludf.IFS(B172="Q1",1.3,B172="Q2",0.7,B172="Q3",0.8,B172="Q4",1.2)} -> #NAME? | F172: =IF(MONTH(C172)=11,2000,0) -> 0 | G172: 300 | J172: =(D172+E172)*6% -> #NAME? | K172: =L172+M172 -> 0 | L172: =Financiamento!D181 -> 0 | M172: =Financiamento!C181 -> 0 | Q172: =SUM(D172:E172) -> #NAME? | R172: =-SUM(F172:I172) -> -300 | S172: =SUM(Q172:R172) -> #NAME? | U172: =SUM(S172:T172) -> #NAME? | V172: =-M172 -> 0 | W172: =SUM(U172:V172) -> #NAME? | X172: =-J172 -> #NAME? | Y172: =SUM(W172:X172) -> #NAME? | AA172: =S172 -> #NAME? | AB172: =-O172 -> 0 | AC172: =N172 -> 0 | AD172: =-K172 -> 0 | AE172: =SUM(AA172:AD172) -> #NAME? | AF172: =AG171 -> #NAME? | AG172: =AF172+AE172 -> #NAME? | AQ172: =(AE172-E172+150+200) -> #NAME? | AR172: =AQ172*1.4 -> #NAME?
A173: =YEAR(C173) -> 2035 | B173: ="Q"&(QUOTIENT(MONTH(C173),3.1)+1) -> Q3 | C173: 49553 | D173: {=7000*(53%*0.4+47%*0.85)+2800*0.9*_xludf.IFS(B173="Q1",1.3,B173="Q2",0.7,B173="Q3",0.8,B173="Q4",1.2)} -> #NAME? | F173: =IF(MONTH(C173)=11,2000,0) -> 0 | G173: 300 | J173: =(D173+E173)*6% -> #NAME? | K173: =L173+M173 -> 0 | L173: =Financiamento!D182 -> 0 | M173: =Financiamento!C182 -> 0 | Q173: =SUM(D173:E173) -> #NAME? | R173: =-SUM(F173:I173) -> -300 | S173: =SUM(Q173:R173) -> #NAME? | U173: =SUM(S173:T173) -> #NAME? | V173: =-M173 -> 0 | W173: =SUM(U173:V173) -> #NAME? | X173: =-J173 -> #NAME? | Y173: =SUM(W173:X173) -> #NAME? | AA173: =S173 -> #NAME? | AB173: =-O173 -> 0 | AC173: =N173 -> 0 | AD173: =-K173 -> 0 | AE173: =SUM(AA173:AD173) -> #NAME? | AF173: =AG172 -> #NAME? | AG173: =AF173+AE173 -> #NAME? | AQ173: =(AE173-E173+150+200) -> #NAME? | AR173: =AQ173*1.4 -> #NAME?
A174: =YEAR(C174) -> 2035 | B174: ="Q"&(QUOTIENT(MONTH(C174),3.1)+1) -> Q4 | C174: 49583 | D174: {=7000*(53%*0.4+47%*0.85)+2800*0.9*_xludf.IFS(B174="Q1",1.3,B174="Q2",0.7,B174="Q3",0.8,B174="Q4",1.2)} -> #NAME? | F174: =IF(MONTH(C174)=11,2000,0) -> 0 | G174: 300 | J174: =(D174+E174)*6% -> #NAME? | K174: =L174+M174 -> 0 | L174: =Financiamento!D183 -> 0 | M174: =Financiamento!C183 -> 0 | Q174: =SUM(D174:E174) -> #NAME? | R174: =-SUM(F174:I174) -> -300 | S174: =SUM(Q174:R174) -> #NAME? | U174: =SUM(S174:T174) -> #NAME? | V174: =-M174 -> 0 | W174: =SUM(U174:V174) -> #NAME? | X174: =-J174 -> #NAME? | Y174: =SUM(W174:X174) -> #NAME? | AA174: =S174 -> #NAME? | AB174: =-O174 -> 0 | AC174: =N174 -> 0 | AD174: =-K174 -> 0 | AE174: =SUM(AA174:AD174) -> #NAME? | AF174: =AG173 -> #NAME? | AG174: =AF174+AE174 -> #NAME? | AQ174: =(AE174-E174+150+200) -> #NAME? | AR174: =AQ174*1.4 -> #NAME?
A175: =YEAR(C175) -> 2035 | B175: ="Q"&(QUOTIENT(MONTH(C175),3.1)+1) -> Q4 | C175: 49614 | D175: {=7000*(53%*0.4+47%*0.85)+2800*0.9*_xludf.IFS(B175="Q1",1.3,B175="Q2",0.7,B175="Q3",0.8,B175="Q4",1.2)} -> #NAME? | F175: =IF(MONTH(C175)=11,2000,0) -> 2000 | G175: 300 | J175: =(D175+E175)*6% -> #NAME? | K175: =L175+M175 -> 0 | L175: =Financiamento!D184 -> 0 | M175: =Financiamento!C184 -> 0 | Q175: =SUM(D175:E175) -> #NAME? | R175: =-SUM(F175:I175) -> -2300 | S175: =SUM(Q175:R175) -> #NAME? | U175: =SUM(S175:T175) -> #NAME? | V175: =-M175 -> 0 | W175: =SUM(U175:V175) -> #NAME? | X175: =-J175 -> #NAME? | Y175: =SUM(W175:X175) -> #NAME? | AA175: =S175 -> #NAME? | AB175: =-O175 -> 0 | AC175: =N175 -> 0 | AD175: =-K175 -> 0 | AE175: =SUM(AA175:AD175) -> #NAME? | AF175: =AG174 -> #NAME? | AG175: =AF175+AE175 -> #NAME? | AQ175: =(AE175-E175+150+200) -> #NAME? | AR175: =AQ175*1.4 -> #NAME?
A176: =YEAR(C176) -> 2035 | B176: ="Q"&(QUOTIENT(MONTH(C176),3.1)+1) -> Q4 | C176: 49644 | D176: {=7000*(53%*0.4+47%*0.85)+2800*0.9*_xludf.IFS(B176="Q1",1.3,B176="Q2",0.7,B176="Q3",0.8,B176="Q4",1.2)} -> #NAME? | F176: =IF(MONTH(C176)=11,2000,0) -> 0 | G176: 300 | J176: =(D176+E176)*6% -> #NAME? | K176: =L176+M176 -> 0 | L176: =Financiamento!D185 -> 0 | M176: =Financiamento!C185 -> 0 | Q176: =SUM(D176:E176) -> #NAME? | R176: =-SUM(F176:I176) -> -300 | S176: =SUM(Q176:R176) -> #NAME? | U176: =SUM(S176:T176) -> #NAME? | V176: =-M176 -> 0 | W176: =SUM(U176:V176) -> #NAME? | X176: =-J176 -> #NAME? | Y176: =SUM(W176:X176) -> #NAME? | AA176: =S176 -> #NAME? | AB176: =-O176 -> 0 | AC176: =N176 -> 0 | AD176: =-K176 -> 0 | AE176: =SUM(AA176:AD176) -> #NAME? | AF176: =AG175 -> #NAME? | AG176: =AF176+AE176 -> #NAME? | AQ176: =(AE176-E176+150+200) -> #NAME? | AR176: =AQ176*1.4 -> #NAME?
C177: 49675 | AQ177: 6683.33 | AR177: =AQ177 -> 6683.33
C178: 49706 | AQ178: 6683.33 | AR178: =AQ178 -> 6683.33
C179: 49735 | AQ179: 6683.33 | AR179: =AQ179 -> 6683.33
C180: 49766 | AQ180: 6683.33 | AR180: =AQ180 -> 6683.33 | AS180: TIR ate 2035 | AT180: =XIRR(AQ4:AQ176,C4:C176) -> #NAME?
C181: 49796 | AQ181: 6683.33 | AR181: =AQ181 -> 6683.33 | AS181: TIR ate 2040 | AT181: =XIRR(AQ4:AQ236,C4:C236) -> #NAME?
C182: 49827 | AQ182: 6683.33 | AR182: =AQ182 -> 6683.33 | AS182: TIR alvo | AT182: =XIRR(AR4:AR176,C4:C176) -> #NAME?
C183: 49857 | AQ183: 6683.33 | AR183: =AQ183 -> 6683.33 | AS183: TIR alvo | AT183: =XIRR(AR4:AR236,C4:C236) -> #NAME?
C184: 49888 | AQ184: 6683.33 | AR184: =AQ184 -> 6683.33
C185: 49919 | AQ185: 6683.33 | AR185: =AQ185 -> 6683.33
C186: 49949 | AQ186: 6683.33 | AR186: =AQ186 -> 6683.33
C187: 49980 | AQ187: 6683.33 | AR187: =AQ187 -> 6683.33
C188: 50010 | AQ188: 6683.33 | AR188: =AQ188 -> 6683.33
C189: 50041 | AQ189: 6683.33 | AR189: =AQ189 -> 6683.33
C190: 50072 | AQ190: 6683.33 | AR190: =AQ190 -> 6683.33
C191: 50100 | AQ191: 6683.33 | AR191: =AQ191 -> 6683.33
C192: 50131 | AQ192: 6683.33 | AR192: =AQ192 -> 6683.33
...

Sheet Financiamento
A1: Método | B1: Price
A2: Valor solicitado | B2: 325186.38
A3: Valor liberado | B3: 331380.09
A4: Prazo (meses) | B4: 60
A5: CET (% a.m.) | B5: 0.0154
A6: Carência (meses) | B6: 2
A7: Valor total devido | B7: 518714.4
A9: Data | B9: Período | C9: Juros | D9: Amortização | E9: Parcela | F9: Saldo devedor
A10: 44341 | B10: 0
A11: 44371 | B11: 1
A12: 44401 | B12: 2 | F12: 336977.2
A13: 44432 | B13: 3 | C13: =F12*$B$5 -> 5189.4489 | D13: =E13-C13 -> 3455.7915 | E13: =-PMT($B$5,$B$4,$F$12) -> 8645.2403 | F13: =F12-D13 -> 333521.41
A14: 44463 | B14: 4 | C14: =F13*$B$5 -> 5136.2297 | D14: =E14-C14 -> 3509.0106 | E14: =-PMT($B$5,$B$4,$F$12) -> 8645.2403 | F14: =F13-D14 -> 330012.4
A15: 44493 | B15: 5 | C15: =F14*$B$5 -> 5082.1909 | D15: =E15-C15 -> 3563.0494 | E15: =-PMT($B$5,$B$4,$F$12) -> 8645.2403 | F15: =F14-D15 -> 326449.35
A16: 44524 | B16: 6 | C16: =F15*$B$5 -> 5027.32 | D16: =E16-C16 -> 3617.9204 | E16: =-PMT($B$5,$B$4,$F$12) -> 8645.2403 | F16: =F15-D16 -> 322831.43
A17: 44554 | B17: 7 | C17: =F16*$B$5 -> 4971.604 | D17: =E17-C17 -> 3673.6363 | E17: =-PMT($B$5,$B$4,$F$12) -> 8645.2403 | F17: =F16-D17 -> 319157.79
A18: 44585 | B18: 8 | C18: =F17*$B$5 -> 4915.03 | D18: =E18-C18 -> 3730.2103 | E18: =-PMT($B$5,$B$4,$F$12) -> 8645.2403 | F18: =F17-D18 -> 315427.58
A19: 44616 | B19: 9 | C19: =F18*$B$5 -> 4857.5848 | D19: =E19-C19 -> 3787.6556 | E19: =-PMT($B$5,$B$4,$F$12) -> 8645.2403 | F19: =F18-D19 -> 311639.93
A20: 44644 | B20: 10 | C20: =F19*$B$5 -> 4799.2549 | D20: =E20-C20 -> 3845.9855 | E20: =-PMT($B$5,$B$4,$F$12) -> 8645.2403 | F20: =F19-D20 -> 307793.94
A21: 44675 | B21: 11 | C21: =F20*$B$5 -> 4740.0267 | D21: =E21-C21 -> 3905.2137 | E21: =-PMT($B$5,$B$4,$F$12) -> 8645.2403 | F21: =F20-D21 -> 303888.73
A22: 44705 | B22: 12 | C22: =F21*$B$5 -> 4679.8864 | D22: =E22-C22 -> 3965.354 | E22: =-PMT($B$5,$B$4,$F$12) -> 8645.2403 | F22: =F21-D22 -> 299923.37
A23: 44736 | B23: 13 | C23: =F22*$B$5 -> 4618.8199 | D23: =E23-C23 -> 4026.4204 | E23: =-PMT($B$5,$B$4,$F$12) -> 8645.2403 | F23: =F22-D23 -> 295896.95
A24: 44766 | B24: 14 | C24: =F23*$B$5 -> 4556.8131 | D24: =E24-C24 -> 4088.4273 | E24: =-PMT($B$5,$B$4,$F$12) -> 8645.2403 | F24: =F23-D24 -> 291808.53
... A72: 46227 | B72: 62 | C72: =F71*$B$5 -> 131.11749 | D72: =E72-C72 -> 8514.1228 | E72: =-PMT($B$5,$B$4,$F$12) -> 8645.2403 | F72: =F71-D72 -> 8.9130481e-11

Sheet Geração por usina
B1: Geração | C1: Geração
A2: Unidade | B2: kWh | C2: kWh
A3: Usina | B3: 235 | C3: 281
A4: 44969 | B4: 217
A5: 44970 | B5: 217
A6: 44971 | B6: 217
A7: 44972 | B7: 217
A8: 44973 | B8: 217
A9: 44974 | B9: 217
A10: 44975 | B10: 217
A11: 44976 | B11: 217
A12: 44977 | B12: 217
A13: 44978 | B13: 217
A14: 44979 | B14: 217
A15: 44980 | B15: 212.89
... A35: 45000 | B35: 134.42
A36: 45001 | B36: 207.75 | C36: 119
A37: 45002 | B37: 211.2 | C37: 127.7
A38: 45003
A39: 45004
A40: 45005 | B40: 211.66 | C40: 135.2
A41: 45006 | B41: 29.1 | C41: 20.9
A42: 45007 | B42: 212.19 | C42: 125.6
A43: 45008 | B43: 207.14 | C43: 125
A44: 45009 | B44: 211.15 | C44: 129.4
A45: 45010 | B45: 184.51 | C45: 110.9
A46: 45011 | B46: 205.99 | C46: 127
A47: 45012 | B47: 72.19 | C47: 40.7
A48: 45013 | B48: 95.57 | C48: 57.1
A49: 45014 | B49: 173.63 | C49: 110.4
A50: 45015 | B50: 160.58 | C50: 99.1
A51: 45016 | B51: 197.64 | C51: 126.3
... A85: 45050 | B85: 130.5 | C85: 89.4
A86: 45051 | B86: 98.85 | C86: =B86*64% -> 63.264
A87: 45052 | B87: 122.8 | C87: =B87*64% -> 78.592
A88: 45053 | B88: 103.28 | C88: =B88*64% -> 66.0992
A89: 45054 | B89: 122.09 | C89: =B89*64% -> 78.1376
A90: 45055 | B90: 100.43 | C90: =B90*64% -> 64.2752
A91: 45056 | B91: 39.18 | C91: =B91*64% -> 25.0752
A92: 45057 | B92: 58.24 | C92: =B92*64% -> 37.2736
A93: 45058 | B93: 73.73 | C93: =B93*64% -> 47.1872
A94: 45059 | B94: 97.99 | C94: =B94*64% -> 62.7136
A95: 45060 | B95: 118.01 | C95: =B95*64% -> 75.5264
A96: 45061 | B96: 115.3 | C96: =B96*64% -> 73.792
A97: 45062 | B97: 118.88 | C97: =B97*64% -> 76.0832
... A188: 45153 | B188: 58.07 | C188: =B188*64% -> 37.1648
A189: 45154
A190: 45155
A191: 45156
A192: 45157
A193: 45158
A194: 45159
A195: 45160
A196: 45161
A197: 45162
B199: =SUM(B3:B188) -> 23155.36 | C199: =SUM(C3:C188) -> 10520.646
B201: 15033 | C201: 24569
B202: 32474

Sheet Créditos CP
C1: Injeção | D1: Injeção | E1: Injeção | F1: Abatimento | G1: Abatimento | H1: Injeção líquida | I1: Injeção líquida | J1: Injeção líquida | L1: Percentual 235 | M1: Percentual 235 | N1: Percentual 235 | O1: Percentual 235 | P1: Percentual 281 | Q1: Percentual 281 | R1: Percentual 281 | S1: Percentual 281 | U1: Créditos recebidos | V1: Créditos recebidos | W1: Créditos recebidos | X1: Créditos recebidos | Z1: Saldo | AA1: Saldo | AB1: Saldo | AC1: Saldo
A2: Mês de referência | B2: Período | C2: Usina 235 | D2: Usina 281 | E2: Total | F2: Usina 235 | G2: Usina 281 | H2: Usina 235 | I2: Usina 281 | J2: Total | L2: Itaipu | M2: Icaraí | N2: Laura Jardim | O2: Essence | P2: Itaipu | Q2: Icaraí | R2: Laura Jardim | S2: Essence | U2: Itaipu | V2: Icaraí | W2: Laura Jardim | X2: Essence | Z2: Itaipu | AA2: Icaraí | AB2: Laura Jardim | AC2: Essence
A3: 44927 | B3: 15/12/2022 - 13/01/2023 | D3: 3195 | E3: =D3+C3 -> 3195 | G3: ='Faturamento 281'!I2 -> 67 | H3: =C3-F3 -> 0 | I3: =D3-G3 -> 3128 | J3: =SUM(H3:I3) -> 3128
A4: 44958 | B4: 14/01/2023 - 11/02/2023 | D4: 3310 | E4: =D4+C4 -> 3310 | G4: ='Faturamento 281'!I3 -> 62 | H4: =C4-F4 -> 0 | I4: =D4-G4 -> 3248 | J4: =SUM(H4:I4) -> 3248
A5: 44986 | B5: 12/02/2023 - 15/03/2023 | C5: 12784 | D5: 3512 | E5: =D5+C5 -> 16296 | F5: ='Faturamento 235'!M4 -> 289 | G5: ='Faturamento 281'!I4 -> 78 | H5: =C5-F5 -> 12495 | I5: =D5-G5 -> 3434 | J5: =SUM(H5:I5) -> 15929 | L5: 0.46 | M5: 0.54 | U5: =L5*$H5+P5*$I5 -> 5747.7 | V5: =M5*$H5+Q5*$I5 -> 6747.3 | W5: =N5*$H5+R5*$I5 -> 0 | X5: =O5*$H5+S5*$I5 -> 0 | Z5: =U5-'Faturamento Itaipu'!G2 -> 2616.7 | AA5: =V5-'Faturamento Icaraí'!J2 -> 5097.3
A6: 45017 | B6: 16/03/2023 - 14/04/2023 | C6: 2798 | D6: 2706 | E6: =D6+C6 -> 5504 | F6: ='Faturamento 235'!M5 -> 737 | G6: ='Faturamento 281'!I5 -> 22 | H6: =C6-F6 -> 2061 | I6: =D6-G6 -> 2684 | J6: =SUM(H6:I6) -> 4745 | L6: 0.46 | M6: 0.54 | P6: 0.46 | Q6: 0.54 | U6: =L6*$H6+P6*$I6 -> 2182.7 | V6: =M6*$H6+Q6*$I6 -> 2562.3 | W6: =N6*$H6+R6*$I6 -> 0 | X6: =O6*$H6+S6*$I6 -> 0 | Z6: =MAX(U6-'Faturamento Itaipu'!G3+Z5,0) -> 2329.4 | AA6: =MAX(V6-'Faturamento Icaraí'!J3+AA5,0) -> 6349.6
A7: 45047 | B7: 15/04/2023 - 16/05/2023 | C7: 2319 | D7: 2258 | E7: =D7+C7 -> 4577 | F7: ='Faturamento 235'!M6 -> 853 | G7: ='Faturamento 281'!I6 -> 8 | H7: =C7-F7 -> 1466 | I7: =D7-G7 -> 2250 | J7: =SUM(H7:I7) -> 3716 | L7: 0.46 | M7: 0.54 | P7: 0.46 | Q7: 0.54 | U7: =L7*$H7+P7*$I7 -> 1709.36 | V7: =M7*$H7+Q7*$I7 -> 2006.64 | W7: =N7*$H7+R7*$I7 -> 0 | X7: =O7*$H7+S7*$I7 -> 0 | Z7: =MAX(U7-'Faturamento Itaipu'!G4+Z6,0) -> 1396.76 | AA7: =MAX(V7-'Faturamento Icaraí'!J4+AA6,0) -> 7166.24
A8: 45078 | B8: 17/05/2023 - 16/06/2023 | C8: 1946 | D8: 1888 | E8: =D8+C8 -> 3834 | F8: ='Faturamento 235'!M7 -> 464 | G8: ='Faturamento 281'!I7 -> 0 | H8: =C8-F8 -> 1482 | I8: =D8-G8 -> 1888 | J8: =SUM(H8:I8) -> 3370 | L8: 0.46 | M8: 0.54 | P8: 0.46 | Q8: 0.54 | U8: =L8*$H8+P8*$I8 -> 1550.2 | V8: =M8*$H8+Q8*$I8 -> 1819.8 | W8: =N8*$H8+R8*$I8 -> 0 | X8: =O8*$H8+S8*$I8 -> 0 | Z8: =MAX(U8-'Faturamento Itaipu'!G5+Z7,0) -> 611.96 | AA8: =MAX(V8-'Faturamento Icaraí'!J5+AA7,0) -> 7986.04
A9: 45108 | B9: 17/06/2023 - 14/07/2023 | C9: 1533 | D9: 1593 | E9: =D9+C9 -> 3126 | F9: ='Faturamento 235'!M8 -> 412 | G9: ='Faturamento 281'!I8 -> 0 | H9: =C9-F9 -> 1121 | I9: =D9-G9 -> 1593 | J9: =SUM(H9:I9) -> 2714 | L9: 0.46 | M9: 0.54 | P9: 0.46 | Q9: 0.54 | U9: =L9*$H9+P9*$I9 -> 1248.44 | V9: =M9*$H9+Q9*$I9 -> 1465.56 | W9: =N9*$H9+R9*$I9 -> 0 | X9: =O9*$H9+S9*$I9 -> 0 | Z9: =MAX(U9-'Faturamento Itaipu'!G6+Z8,0) -> 79.4 | AA9: =MAX(V9-'Faturamento Icaraí'!J6+AA8,0) -> 8461.6
A10: 45139 | B10: 15/07/2023 - 15/08/2023 | C10: 2894 | D10: 2045 | E10: =D10+C10 -> 4939 | F10: ='Faturamento 235'!M9 -> 292 | G10: ='Faturamento 281'!I9 -> 0 | H10: =C10-F10 -> 2602 | I10: =D10-G10 -> 2045 | J10: =SUM(H10:I10) -> 4647 | L10: 0.95 | M10: 0.05 | P10: 0.95 | Q10: 0.05 | U10: =L10*$H10+P10*$I10 -> 4414.65 | V10: =M10*$H10+Q10*$I10 -> 232.35 | W10: =N10*$H10+R10*$I10 -> 0 | X10: =O10*$H10+S10*$I10 -> 0 | Z10: =MAX(U10-'Faturamento Itaipu'!G7+Z9,0) -> 1993.05 | AA10: =MAX(V10-'Faturamento Icaraí'!J7+AA9,0) -> 7643.95
A11: 45170 | B11: 16/08/2023 - 15/09/2023 | C11: 4100 | D11: 2237 | E11: =D11+C11 -> 6337 | F11: ='Faturamento 235'!M10 -> 601 | G11: ='Faturamento 281'!I10 -> 0 | H11: =C11-F11 -> 3499 | I11: =D11-G11 -> 2237 | J11: =SUM(H11:I11) -> 5736 | L11: 0.95 | M11: 0.05 | P11: 0.95 | Q11: 0.05 | U11: =L11*$H11+P11*$I11 -> 5449.2 | V11: =M11*$H11+Q11*$I11 -> 286.8 | W11: =N11*$H11+R11*$I11 -> 0 | X11: =O11*$H11+S11*$I11 -> 0 | Z11: =MAX(U11-'Faturamento Itaipu'!G8+Z10,0) -> 4655.25 | AA11: =MAX(V11-'Faturamento Icaraí'!J8+AA10,0) -> 6820.75
A12: 45200 | B12: 16/09/2023 - 17/10/2023 | C12: 4772 | D12: 2916 | E12: =D12+C12 -> 7688 | F12: ='Faturamento 235'!M11 -> 589 | G12: ='Faturamento 281'!I11 -> 23 | H12: =C12-F12 -> 4183 | I12: =D12-G12 -> 2893 | J12: =SUM(H12:I12) -> 7076 | L12: 0.95 | M12: 0.05 | P12: 0.95 | Q12: 0.05 | U12: =L12*$H12+P12*$I12 -> 6722.2 | V12: =M12*$H12+Q12*$I12 -> 353.8 | W12: =N12*$H12+R12*$I12 -> 0 | X12: =O12*$H12+S12*$I12 -> 0 | Z12: =MAX(U12-'Faturamento Itaipu'!G9+Z11,0) -> 8510.45 | AA12: =MAX(V12-'Faturamento Icaraí'!J9+AA11,0) -> 6134.55
A13: 45231 | B13: 18/10/2023 - 14/11/2023 | C13: 5134 | D13: 3012 | E13: =D13+C13 -> 8146 | F13: ='Faturamento 235'!M12 -> 540 | G13: ='Faturamento 281'!I12 -> 0 | H13: =C13-F13 -> 4594 | I13: =D13-G13 -> 3012 | J13: =SUM(H13:I13) -> 7606 | L13: 0.95 | M13: 0.05 | P13: 0.95 | Q13: 0.05 | U13: =L13*$H13+P13*$I13 -> 7225.7 | V13: =M13*$H13+Q13*$I13 -> 380.3 | W13: =N13*$H13+R13*$I13 -> 0 | X13: =O13*$H13+S13*$I13 -> 0 | Z13: =MAX(U13-'Faturamento Itaipu'!G10+Z12,0) -> 13125.15 | AA13: =MAX(V13-'Faturamento Icaraí'!J10+AA12,0) -> 5004.85
A14: 45261 | B14: 15/11/2023 - 14/12/2023 | C14: 4320 | D14: 2593 | E14: =D14+C14 -> 6913 | F14: ='Faturamento 235'!M13 -> 461 | G14: ='Faturamento 281'!I13 -> 41 | H14: =C14-F14 -> 3859 | I14: =D14-G14 -> 2552 | J14: =SUM(H14:I14) -> 6411 | L14: 0.95 | M14: 0.05 | P14: 0.95 | Q14: 0.05 | U14: =L14*$H14+P14*$I14 -> 6090.45 | V14: =M14*$H14+Q14*$I14 -> 320.55 | W14: =N14*$H14+R14*$I14 -> 0 | X14: =O14*$H14+S14*$I14 -> 0 | Z14: =MAX(U14-'Faturamento Itaipu'!G11+Z13,0) -> 16740.6 | AA14: =MAX(V14-'Faturamento Icaraí'!J11+AA13,0) -> 4045.4
A15: 45292 | B15: 15/12/2023 - 14/01/2024 | C15: 2374 | D15: 4133 | E15: =D15+C15 -> 6507 | F15: ='Faturamento 235'!M14 -> 0 | G15: ='Faturamento 281'!I14 -> 0 | H15: =C15-F15 -> 2374 | I15: =D15-G15 -> 4133 | J15: =SUM(H15:I15) -> 6507 | L15: 0.95 | M15: 0.05 | P15: 0.95 | Q15: 0.05 | U15: =L15*$H15+P15*$I15 -> 6181.65 | V15: =M15*$H15+Q15*$I15 -> 325.35 | W15: =N15*$H15+R15*$I15 -> 0 | X15: =O15*$H15+S15*$I15 -> 0 | Z15: =MAX(U15-'Faturamento Itaipu'!G12+Z14,0) -> 19984.25 | AA15: =MAX(V15-'Faturamento Icaraí'!J12+AA14,0) -> 2692.75
A16: 45323 | B16: 15/01/2024 - 14/02/2024 | C16: 6875 | D16: 3560 | E16: =D16+C16 -> 10435 | F16: ='Faturamento 235'!M15 -> 126 | G16: ='Faturamento 281'!I15 -> 0 | H16: =C16-F16 -> 6749 | I16: =D16-G16 -> 3560 | J16: =SUM(H16:I16) -> 10309 | L16: 0.95 | M16: 0.05 | P16: 0.95 | Q16: 0.05 | U16: =L16*$H16+P16*$I16 -> 9793.55 | V16: =M16*$H16+Q16*$I16 -> 515.45 | W16: =N16*$H16+R16*$I16 -> 0 | X16: =O16*$H16+S16*$I16 -> 0 | Z16: =MAX(U16-'Faturamento Itaipu'!G13+Z15,0) -> 27062.8 | AA16: =MAX(V16-'Faturamento Icaraí'!J13+AA15,0) -> 1680.2 | AB16: =MAX(W16-'Faturamento Laura Jardim'!G2+AB15,0) -> 0
A17: 45352 | B17: 15/02/2024 - 13/03/2024 | C17: 4472 | D17: 2756 | E17: =D17+C17 -> 7228 | F17: ='Faturamento 235'!M16 -> 599 | G17: ='Faturamento 281'!I16 -> 0 | H17: =C17-F17 -> 3873 | I17: =D17-G17 -> 2756 | J17: =SUM(H17:I17) -> 6629 | L17: 0.95 | M17: 0.05 | P17: 0.35 | Q17: 0.2 | R17: 0.45 | U17: =L17*$H17+P17*$I17 -> 4643.95 | V17: =M17*$H17+Q17*$I17 -> 744.85 | W17: =N17*$H17+R17*$I17 -> 1240.2 | X17: =O17*$H17+S17*$I17 -> 0 | Z17: =MAX(U17-'Faturamento Itaipu'!G14+Z16,0) -> 28831.75 | AA17: =MAX(V17-'Faturamento Icaraí'!J14+AA16,0) -> 905.05 | AB17: =MAX(W17-'Faturamento Laura Jardim'!G3+AB16,0) -> 228.2
A18: 45383 | B18: 14/03/2024 - 12/04/2024 | C18: 3171 | D18: 1981 | E18: =D18+C18 -> 5152 | F18: ='Faturamento 235'!M17 -> 542 | G18: ='Faturamento 281'!I17 -> 0 | H18: =C18-F18 -> 2629 | I18: =D18-G18 -> 1981 | J18: =SUM(H18:I18) -> 4610 | L18: 0.95 | M18: 0.05 | P18: 0.35 | Q18: 0.2 | R18: 0.45 | U18: =L18*$H18+P18*$I18 -> 3190.9 | V18: =M18*$H18+Q18*$I18 -> 527.65 | W18: =N18*$H18+R18*$I18 -> 891.45 | X18: =O18*$H18+S18*$I18 -> 0 | Z18: =MAX(U18-'Faturamento Itaipu'!G15+Z17,0) -> 29491.65 | AA18: =MAX(V18-'Faturamento Icaraí'!J15+AA17,0) -> 353.7 | AB18: =MAX(W18-'Faturamento Laura Jardim'!G4+AB17,0) -> 0
A19: 45413 | B19: 13/04/2024 - 14/05/2024 | C19: 3271 | D19: 2319 | E19: =D19+C19 -> 5590 | F19: ='Faturamento 235'!M18 -> 858 | G19: ='Faturamento 281'!I18 -> 0 | H19: =C19-F19 -> 2413 | I19: =D19-G19 -> 2319 | J19: =SUM(H19:I19) -> 4732 | L19: 0.17 | M19: 0.18 | N19: =N20 -> 0.3 | O19: =O20 -> 0.35 | P19: 0.17 | Q19: 0.18 | R19: 0.3 | S19: 0.35 | U19: =L19*$H19+P19*$I19 -> 804.44 | V19: =M19*$H19+Q19*$I19 -> 851.76 | W19: =N19*$H19+R19*$I19 -> 1419.6 | X19: =O19*$H19+S19*$I19 -> 1656.2 | Z19: =MAX(U19-'Faturamento Itaipu'!G16+Z18,0) -> 27828.09 | AA19: =MAX(V19-'Faturamento Icaraí'!J16+AA18,0) -> 0 | AB19: =MAX(W19-'Faturamento Laura Jardim'!G5+AB18,0) -> 326.6
A20: 45444 | B20: 15/05/2024 - 14/06/2024 | C20: 2049 | D20: 1638 | E20: =D20+C20 -> 3687 | F20: ='Faturamento 235'!M19 -> 762 | G20: ='Faturamento 281'!I19 -> 0 | H20: =C20-F20 -> 1287 | I20: =D20-G20 -> 1638 | J20: =SUM(H20:I20) -> 2925 | L20: 0.17 | M20: 0.18 | N20: 0.3 | O20: 0.35 | P20: 0.17 | Q20: 0.18 | R20: 0.3 | S20: 0.35 | U20: =L20*$H20+P20*$I20 -> 497.25 | V20: =M20*$H20+Q20*$I20 -> 526.5 | W20: =N20*$H20+R20*$I20 -> 877.5 | X20: =O20*$H20+S20*$I20 -> 1023.75 | Z20: =MAX(U20-'Faturamento Itaipu'!G17+Z19,0) -> 26029.34 | AA20: =MAX(V20-'Faturamento Icaraí'!J17+AA19,0) -> 0 | AB20: =MAX(W20-'Faturamento Laura Jardim'!G6+AB19,0) -> 58.1
A21: 45474 | B21: 15/06/2024 - 15/07/2024 | C21: 1826 | D21: 1410 | E21: =D21+C21 -> 3236 | F21: ='Faturamento 235'!M20 -> 688 | G21: ='Faturamento 281'!I20 -> 0 | H21: =C21-F21 -> 1138 | I21: =D21-G21 -> 1410 | J21: =SUM(H21:I21) -> 2548 | L21: 0.17 | M21: 0.18 | N21: 0.3 | O21: 0.35 | P21: 0.17 | Q21: 0.18 | R21: 0.3 | S21: 0.35 | U21: =L21*$H21+P21*$I21 -> 433.16 | V21: =M21*$H21+Q21*$I21 -> 458.64 | W21: =N21*$H21+R21*$I21 -> 764.4 | X21: =O21*$H21+S21*$I21 -> 891.8 | Z21: =MAX(U21-'Faturamento Itaipu'!G18+Z20,0) -> 24471.5 | AA21: =MAX(V21-'Faturamento Icaraí'!J18+AA20,0) -> 17.64 | AB21: =MAX(W21-'Faturamento Laura Jardim'!G7+AB20,0) -> 87.5
A22: 45505 | B22: 15/07/2024 - 14/08/2024 | C22: 3226 | D22: 2202 | E22: =D22+C22 -> 5428 | F22: 255 | G22: 0 | H22: =C22-F22 -> 2971 | I22: =D22-G22 -> 2202 | J22: =SUM(H22:I22) -> 5173 | L22: 0.17 | M22: 0.18 | N22: 0.3 | O22: 0.35 | P22: 0.17 | Q22: 0.18 | R22: 0.3 | S22: 0.35 | U22: =L22*$H22+P22*$I22 -> 879.41 | V22: =M22*$H22+Q22*$I22 -> 931.14 | W22: =N22*$H22+R22*$I22 -> 1551.9 | X22: =O22*$H22+S22*$I22 -> 1810.55 | Z22: =MAX(U22-'Faturamento Itaipu'!G19+Z21,0) -> 23325.91 | AA22: =MAX(V22-'Faturamento Icaraí'!J19+AA21,0) -> 17.78 | AB22: =MAX(W22-'Faturamento Laura Jardim'!G8+AB21,0) -> 449.4
A23: 45536 | B23: 15/08/2024 - 14/09/2024 | C23: 4547 | D23: 2884 | E23: =D23+C23 -> 7431 | F23: 492 | G23: 43 | H23: =C23-F23 -> 4055 | I23: =D23-G23 -> 2841 | J23: =SUM(H23:I23) -> 6896 | L23: 0.17 | M23: 0.18 | N23: 0.3 | O23: 0.35 | P23: 0.17 | Q23: 0.18 | R23: 0.3 | S23: 0.35 | U23: =L23*$H23+P23*$I23 -> 1172.32 | V23: =M23*$H23+Q23*$I23 -> 1241.28 | W23: =N23*$H23+R23*$I23 -> 2068.8 | X23: =O23*$H23+S23*$I23 -> 2413.6 | Z23: =MAX(U23-'Faturamento Itaipu'!G20+Z22,0) -> 21997.23 | AA23: =MAX(V23-'Faturamento Icaraí'!J20+AA22,0) -> 18.06 | AB23: =MAX(W23-'Faturamento Laura Jardim'!G9+AB22,0) -> 1308.2
A24: 45566 | B24: 15/09/2024 - 15/10/2024 | C24: 4114 | D24: 2513 | E24: =D24+C24 -> 6627 | F24: 591 | G24: 46 | H24: =C24-F24 -> 3523 | I24: =D24-G24 -> 2467 | J24: =SUM(H24:I24) -> 5990 | L24: 0.17 | M24: 0.18 | N24: 0.3 | O24: 0.35 | P24: 0.17 | Q24: 0.18 | R24: 0.3 | S24: 0.35 | U24: =L24*$H24+P24*$I24 -> 1018.3 | V24: =M24*$H24+Q24*$I24 -> 1078.2 | W24: =N24*$H24+R24*$I24 -> 1797 | X24: =O24*$H24+S24*$I24 -> 2096.5 | Z24: =MAX(U24-'Faturamento Itaipu'!G21+Z23,0) -> 20303.53 | AA24: =MAX(V24-'Faturamento Icaraí'!J21+AA23,0) -> 18.26 | AB24: =MAX(W24-'Faturamento Laura Jardim'!G10+AB23,0) -> 1959.2
A25: 45597 | B25: 16/10/2024 - 14/11/2024 | C25: 4046 | D25: 2578 | E25: =D25+C25 -> 6624 | F25: 598 | G25: 94 | H25: =C25-F25 -> 3448 | I25: =D25-G25 -> 2484 | J25: =SUM(H25:I25) -> 5932 | L25: 0.17 | M25: 0.18 | N25: 0.3 | O25: 0.35 | P25: 0.17 | Q25: 0.18 | R25: 0.3 | S25: 0.35 | U25: =L25*$H25+P25*$I25 -> 1008.44 | V25: =M25*$H25+Q25*$I25 -> 1067.76 | W25: =N25*$H25+R25*$I25 -> 1779.6 | X25: =O25*$H25+S25*$I25 -> 2076.2 | Z25: =MAX(U25-'Faturamento Itaipu'!G22+Z24,0) -> 18626.97 | AA25: =MAX(V25-'Faturamento Icaraí'!J22+AA24,0) -> 19.02 | AB25: =MAX(W25-'Faturamento Laura Jardim'!G11+AB24,0) -> 2519.8
A26: 45627 | B26: 15/11/2024 - 13/12/2024 | C26: 4483 | D26: 2813 | E26: =D26+C26 -> 7296 | F26: 448 | G26: 41 | H26: =C26-F26 -> 4035 | I26: =D26-G26 -> 2772 | J26: =SUM(H26:I26) -> 6807 | L26: 0.17 | M26: 0.18 | N26: 0.3 | O26: 0.35 | P26: 0.17 | Q26: 0.18 | R26: 0.3 | S26: 0.35 | U26: =L26*$H26+P26*$I26 -> 1157.19 | V26: =M26*$H26+Q26*$I26 -> 1225.26 | W26: =N26*$H26+R26*$I26 -> 2042.1 | X26: =O26*$H26+S26*$I26 -> 2382.45 | Z26: =MAX(U26-'Faturamento Itaipu'!G23+Z25,0) -> 17012.16 | AA26: =MAX(V26-'Faturamento Icaraí'!J23+AA25,0) -> 19.28 | AB26: =MAX(W26-'Faturamento Laura Jardim'!G12+AB25,0) -> 3276.9
A27: 45658 | B27: 14/12/2024 - 13/01/2025 | C27: 6633 | D27: 3509 | E27: =D27+C27 -> 10142 | F27: 12 | G27: 0 | H27: =C27-F27 -> 6621 | I27: =D27-G27 -> 3509 | J27: =SUM(H27:I27) -> 10130 | L27: 0.17 | M27: 0.18 | N27: 0.3 | O27: 0.35 | P27: 0.17 | Q27: 0.18 | R27: 0.3 | S27: 0.35 | U27: =L27*$H27+P27*$I27 -> 1722.1 | V27: =M27*$H27+Q27*$I27 -> 1823.4 | W27: =N27*$H27+R27*$I27 -> 3039 | X27: =O27*$H27+S27*$I27 -> 3545.5 | Z27: =MAX(U27-'Faturamento Itaipu'!G24+Z26,0) -> 15541.26 | AA27: =MAX(V27-'Faturamento Icaraí'!J24+AA26,0) -> 20.68 | AB27: =MAX(W27-'Faturamento Laura Jardim'!G13+AB26,0) -> 5205.9
A28: 45689 | B28: 14/01/2025 - 13/02/2025 | C28: 6232 | D28: 3812 | E28: =D28+C28 -> 10044 | F28: 183 | G28: 0 | H28: =C28-F28 -> 6049 | I28: =D28-G28 -> 3812 | J28: =SUM(H28:I28) -> 9861 | L28: 0.17 | M28: 0.18 | N28: 0.3 | O28: 0.35 | P28: 0.17 | Q28: 0.18 | R28: 0.3 | S28: 0.35 | U28: =L28*$H28+P28*$I28 -> 1676.37 | V28: =M28*$H28+Q28*$I28 -> 1774.98 | W28: =N28*$H28+R28*$I28 -> 2958.3 | X28: =O28*$H28+S28*$I28 -> 3451.35 | Z28: =MAX(U28-'Faturamento Itaipu'!G25+Z27,0) -> 13877.63 | AA28: =MAX(V28-'Faturamento Icaraí'!J25+AA27,0) -> 41.66 | AB28: =MAX(W28-'Faturamento Laura Jardim'!G14+AB27,0) -> 6924.2
A29: 45717 | B29: 14/02/2025 - 13/03/2025 | C29: 5469 | D29: 3498 | E29: =D29+C29 -> 8967 | F29: 418 | G29: 20 | H29: =C29-F29 -> 5051 | I29: =D29-G29 -> 3478 | J29: =SUM(H29:I29) -> 8529 | L29: 0.17 | M29: 0.18 | N29: 0.3 | O29: 0.35 | P29: 0.17 | Q29: 0.18 | R29: 0.3 | S29: 0.35 | U29: =L29*$H29+P29*$I29 -> 1449.93 | V29: =M29*$H29+Q29*$I29 -> 1535.22 | W29: =N29*$H29+R29*$I29 -> 2558.7 | X29: =O29*$H29+S29*$I29 -> 2985.15 | Z29: =MAX(U29-'Faturamento Itaipu'!G26+Z28,0) -> 12402.56 | AA29: =MAX(V29-'Faturamento Icaraí'!J26+AA28,0) -> 41.88 | AB29: =MAX(W29-'Faturamento Laura Jardim'!G15+AB28,0) -> 8291.9
A30: 45748 | B30: 14/03/2025 - 13/04/2025 | C30: 2995 | D30: 2003 | E30: =D30+C30 -> 4998 | F30: 638 | G30: 206 | H30: =C30-F30 -> 2357 | I30: =D30-G30 -> 1797 | J30: =SUM(H30:I30) -> 4154 | L30: 0.17 | M30: 0.18 | N30: 0.3 | O30: 0.35 | P30: 0.17 | Q30: 0.18 | R30: 0.3 | S30: 0.35 | U30: =L30*$H30+P30*$I30 -> 706.18 | V30: =M30*$H30+Q30*$I30 -> 747.72 | W30: =N30*$H30+R30*$I30 -> 1246.2 | X30: =O30*$H30+S30*$I30 -> 1453.9 | Z30: =MAX(U30-'Faturamento Itaipu'!G27+Z29,0) -> 10575.74 | AA30: =MAX(V30-'Faturamento Icaraí'!J27+AA29,0) -> 42.6 | AB30: =MAX(W30-'Faturamento Laura Jardim'!G16+AB29,0) -> 8356.1
A31: 45778 | B31: 14/04/2025 - 13/05/2025 | C31: 2934 | D31: 2013 | E31: =D31+C31 -> 4947 | F31: 425 | G31: 73 | H31: =C31-F31 -> 2509 | I31: =D31-G31 -> 1940 | J31: =SUM(H31:I31) -> 4449 | L31: 0.17 | M31: 0.18 | N31: 0.3 | O31: 0.35 | P31: 0.17 | Q31: 0.18 | R31: 0.3 | S31: 0.35 | U31: =L31*$H31+P31*$I31 -> 756.33 | V31: =M31*$H31+Q31*$I31 -> 800.82 | W31: =N31*$H31+R31*$I31 -> 1334.7 | X31: =O31*$H31+S31*$I31 -> 1557.15 | Z31: =MAX(U31-'Faturamento Itaipu'!G28+Z30,0) -> 8978.07 | AA31: =MAX(V31-'Faturamento Icaraí'!J28+AA30,0) -> 43.42 | AB31: =MAX(W31-'Faturamento Laura Jardim'!G17+AB30,0) -> 8488.8
A32: 45809 | B32: 14/05/2025 - 13/06/2025 | C32: 2368 | D32: 1960 | E32: =D32+C32 -> 4328 | F32: 511 | G32: 80 | H32: =C32-F32 -> 1857 | I32: =D32-G32 -> 1880 | J32: =SUM(H32:I32) -> 3737 | L32: 0 | M32: 0.44 | N32: 0.12 | O32: 0.44 | P32: 0 | Q32: 0.44 | R32: 0.12 | S32: 0.44 | U32: =L32*$H32+P32*$I32 -> 0 | V32: =M32*$H32+Q32*$I32 -> 1644.28 | W32: =N32*$H32+R32*$I32 -> 448.44 | X32: =O32*$H32+S32*$I32 -> 1644.28 | Z32: =MAX(U32-'Faturamento Itaipu'!G29+Z31,0) -> 6747.07 | AA32: =MAX(V32-'Faturamento Icaraí'!J29+AA31,0) -> 43.7 | AB32: =MAX(W32-'Faturamento Laura Jardim'!G18+AB31,0) -> 7794.24
A33: 45839 | B33: 14/06/2025 - 13/07/2025 | C33: 2358 | D33: 1762 | E33: =D33+C33 -> 4120 | F33: 264 | G33: 11 | H33: =C33-F33 -> 2094 | I33: =D33-G33 -> 1751 | J33: =SUM(H33:I33) -> 3845 | L33: 0 | M33: 0.44 | N33: 0.12 | O33: 0.44 | P33: 0 | Q33: 0.44 | R33: 0.12 | S33: 0.44 | U33: =L33*$H33+P33*$I33 -> 0 | V33: =M33*$H33+Q33*$I33 -> 1691.8 | W33: =N33*$H33+R33*$I33 -> 461.4 | X33: =O33*$H33+S33*$I33 -> 1691.8 | Z33: =MAX(U33-'Faturamento Itaipu'!G30+Z32,0) -> 4677.07 | AA33: =MAX(V33-'Faturamento Icaraí'!J30+AA32,0) -> 44.5 | AB33: =MAX(W33-'Faturamento Laura Jardim'!G19+AB32,0) -> 7107.64
... A46: 46235 | B46: 14/07/2026 - 13/08/2026 | C46: 3201 | D46: 2419 | E46: =D46+C46 -> 5620 | F46: 285 | G46: 0 | H46: =C46-F46 -> 2916 | I46: =D46-G46 -> 2419 | J46: =SUM(H46:I46) -> 5335 | L46: 0 | M46: 0.44 | N46: 0.12 | O46: 0.44 | P46: 0 | Q46: 0.44 | R46: 0.12 | S46: 0.44 | U46: =L46*$H46+P46*$I46 -> 0 | V46: =M46*$H46+Q46*$I46 -> 2347.4 | W46: =N46*$H46+R46*$I46 -> 640.2 | X46: =O46*$H46+S46*$I46 -> 2347.4 | Z46: =MAX(U46-'Faturamento Itaipu'!G43+Z45,0) -> 424.07 | AA46: =MAX(V46-'Faturamento Icaraí'!J43+AA45,0) -> 49.82 | AB46: =MAX(W46-'Faturamento Laura Jardim'!G32+AB45,0) -> 1530

Sheet Registro_inversores
A1: Mês de referência | B1: Data medição | C1: Usina 235/1 | D1: Usina 235/2 | E1: Usina 281 | F1: Dias entre medições | H1: Mês de referência | I1: Data de corte | J1: Dias excedentes ao corte | K1: Dias dentro do corte | L1: Geração 235/1 | M1: Geração 235/2 | N1: Geração 235 | O1: Geração 235 ajustada | P1: Geração 281 | Q1: Geração 281 ajustada | R1: Injeção 235 | S1: Injeção 281 | T1: Geração ajustada - injeção 235 | U1: Geração ajustada - injeção 281 | X1: Geração 235 ajustada | AA1: 45597 | AB1: 45689 | AC1: 45717 | AD1: 45748 | AE1: 45778 | AF1: 45809
A2: 45505 | B2: 45525 | E2: 56752 | H2: =A2 -> 45505 | I2: =DATE(YEAR(H2),MONTH(H2),15) -> 45519 | J2: {=MIN(_xlfn.XLOOKUP($H2,$A$2:$A$12,$F$2:$F$12))} -> 0 | AA2: Como se passaram 40 dias entre as medições(26/11 e 16/10), fiz uma regra de 3 para calcular o consumo da 235 de novembro | AB2: Como se passaram 38 dias entre as medições(24/02/2025 e 17/01/2025), fiz uma regra de 3 para calcular o consumo | AC2: somando sobra do ajuste de fevereiro + geração de 24/02 até 16/03 (22 dias) | AD2: somando sobra do ajuste de março (17/03 até 24/03 - 8 dias) + geração de 25/03 até 16/04 (23 dias) | AE2: somando sobra do ajuste de abril (17/04 até 05/05 - 19 dias) + geração de 06/05 até 16/05 (11 dias) | AF2: somando sobra do ajuste de abril (17/05 até 22/05 - 6 dias) + geração de 23/05 até 16/06 (25 dias)
A3: 45536 | B3: 45559 | E3: 59905 | F3: =B3-B2 -> 34 | H3: =A3 -> 45536 | I3: =DATE(YEAR(H3),MONTH(H3),15) -> 45550 | J3: =MIN(_xlfn.XLOOKUP($H3,$A$2:$A$12,$B$2:$B$12))-I3 -> 9 | K3: =F3-J3 -> 25 | Z3: Geração 235/1 | AA3: =C5-C4 -> 5712 | AB3: =C8-C7 -> 6570 | AC3: =C9-C8 -> 4210 | AD3: =$C10-$C9 -> 4287 | AE3: =$C11-$C10 -> 1378 | AF3: =$C12-$C11 -> 2366
A4: 45566 | B4: 45581 | C4: 82589 | D4: 36994 | E4: 61944 | F4: =B4-B3 -> 22 | H4: =A4 -> 45566 | I4: =DATE(YEAR(H4),MONTH(H4),15) -> 45580 | J4: =MIN(_xlfn.XLOOKUP($H4,$A$2:$A$12,$B$2:$B$12))-I4 -> 1 | K4: =F4-J4 -> 21 | L4: {=_xlfn.XLOOKUP($H4,$A:$A,$C:$C)-_xlfn.XLOOKUP($H3,$A:$A,$C:$C)} -> 82589 | M4: {=_xlfn.XLOOKUP($H4,$A:$A,$D:$D)-_xlfn.XLOOKUP($H3,$A:$A,$D:$D)} -> 36994 | N4: =M4+L4 -> 119583 | P4: {=_xlfn.XLOOKUP($H4,$A:$A,$E:$E)-_xlfn.XLOOKUP($H3,$A:$A,$E:$E)} -> 2039 | R4: {=_xlfn.XLOOKUP($H4,'Créditos CP'!A:A,'Créditos CP'!C:C)} -> 4114 | S4: {=_xlfn.XLOOKUP($H4,'Créditos CP'!A:A,'Créditos CP'!D:D)} -> 2513 | Z4: Geração 235/2 | AA4: =D5-D4 -> 2592 | AB4: =D8-D7 -> 3329 | AC4: =D9-D8 -> 2087 | AD4: =$D10-$D9 -> 2063 | AE4: =$D11-$D10 -> 668 | AF4: =$D12-$D11 -> 1148
A5: 45597 | B5: 45621 | C5: 88301 | D5: 39586 | E5: 65615 | F5: =B5-B4 -> 40 | H5: =A5 -> 45597 | I5: =DATE(YEAR(H5),MONTH(H5),15) -> 45611 | J5: =MIN(_xlfn.XLOOKUP($H5,$A$2:$A$12,$B$2:$B$12))-I5 -> 10 | K5: =F5-J5 -> 30 | L5: {=_xlfn.XLOOKUP($H5,$A:$A,$C:$C)-_xlfn.XLOOKUP($H4,$A:$A,$C:$C)} -> 5712 | M5: {=_xlfn.XLOOKUP($H5,$A:$A,$D:$D)-_xlfn.XLOOKUP($H4,$A:$A,$D:$D)} -> 2592 | N5: =M5+L5 -> 8304 | O5: =$K5/SUM($J5:$K5)*N5 -> 6228 | P5: {=_xlfn.XLOOKUP($H5,$A:$A,$E:$E)-_xlfn.XLOOKUP($H4,$A:$A,$E:$E)} -> 3671 | Q5: =$K5/SUM($J5:$K5)*P5 -> 2753.25 | R5: {=_xlfn.XLOOKUP($H5,'Créditos CP'!A:A,'Créditos CP'!C:C)} -> 4046 | S5: {=_xlfn.XLOOKUP($H5,'Créditos CP'!A:A,'Créditos CP'!D:D)} -> 2578 | T5: =O5-R5 -> 2182 | U5: =Q5-S5 -> 175.25 | V5: =O5+Q5 -> 8981.25 | Z5: Geração 235 | AA5: =AA3+AA4 -> 8304 | AB5: =AB3+AB4 -> 9899 | AC5: =AC4+AC3 -> 6297 | AD5: =AD4+AD3 -> 6350 | AE5: =AE4+AE3 -> 2046 | AF5: =AF4+AF3 -> 3514
A6: 45627 | B6: 45645 | C6: 92044 | D6: 41341 | E6: 68819 | F6: =B6-B5 -> 24 | H6: =A6 -> 45627 | I6: =DATE(YEAR(H6),MONTH(H6),15) -> 45641 | J6: =MIN(_xlfn.XLOOKUP($H6,$A$2:$A$12,$B$2:$B$12))-I6 -> 4 | K6: =F6-J6 -> 20 | L6: {=_xlfn.XLOOKUP($H6,$A:$A,$C:$C)-_xlfn.XLOOKUP($H5,$A:$A,$C:$C)} -> 3743 | M6: {=_xlfn.XLOOKUP($H6,$A:$A,$D:$D)-_xlfn.XLOOKUP($H5,$A:$A,$D:$D)} -> 1755 | N6: =M6+L6 -> 5498 | O6: =$K6/SUM($J6:$K6)*N6+$J5/SUM($J5:$K5)*N5 -> 6657.6667 | P6: {=_xlfn.XLOOKUP($H6,$A:$A,$E:$E)-_xlfn.XLOOKUP($H5,$A:$A,$E:$E)} -> 3204 | Q6: =$K6/SUM($J6:$K6)*P6+$J5/SUM($J5:$K5)*P5 -> 3587.75 | R6: {=_xlfn.XLOOKUP($H6,'Créditos CP'!A:A,'Créditos CP'!C:C)} -> 4483 | S6: {=_xlfn.XLOOKUP($H6,'Créditos CP'!A:A,'Créditos CP'!D:D)} -> 2813 | T6: =O6-R6 -> 2174.6667 | U6: =Q6-S6 -> 774.75 | V6: =O6+Q6 -> 10245.417 | Z6: Geração ajustada 235 | AA6: =AA5*3/4 -> 6228 | AB6: =30/(B8-B7)*AB5 -> 7815 | AC6: =AB5-AB6+22/($B9-$B8)*AC5 -> 7031.6429 | AD6: =MAX(AD7,AC5-AC6+23/($B10-$B9)*AD5) -> 2995 | AE6: =AD5-AD6+11/($B11-$B10)*AE5 -> 4678.8824 | AF6: =AE5-AE6+25/($B12-$B11)*AF5 -> -192.60458
A7: 45658 | B7: 45674 | C7: 96279 | D7: 43278 | E7: 71907 | F7: =B7-B6 -> 29 | H7: =A7 -> 45658 | I7: =DATE(YEAR(H7),MONTH(H7),15) -> 45672 | J7: =MIN(_xlfn.XLOOKUP($H7,$A$2:$A$12,$B$2:$B$12))-I7 -> 2 | K7: =F7-J7 -> 27 | L7: {=_xlfn.XLOOKUP($H7,$A:$A,$C:$C)-_xlfn.XLOOKUP($H6,$A:$A,$C:$C)} -> 4235 | M7: {=_xlfn.XLOOKUP($H7,$A:$A,$D:$D)-_xlfn.XLOOKUP($H6,$A:$A,$D:$D)} -> 1937 | N7: =M7+L7 -> 6172 | O7: =$K7/SUM($J7:$K7)*N7+$J6/SUM($J6:$K6)*N6 -> 6662.6782 | P7: {=_xlfn.XLOOKUP($H7,$A:$A,$E:$E)-_xlfn.XLOOKUP($H6,$A:$A,$E:$E)} -> 3088 | Q7: =$K7/SUM($J7:$K7)*P7+$J6/SUM($J6:$K6)*P6 -> 3409.0345 | R7: {=_xlfn.XLOOKUP($H7,'Créditos CP'!A:A,'Créditos CP'!C:C)} -> 6633 | S7: {=_xlfn.XLOOKUP($H7,'Créditos CP'!A:A,'Créditos CP'!D:D)} -> 3509 | T7: =O7-R7 -> 29.678161 | U7: =Q7-S7 -> -99.965517 | V7: =O7+Q7 -> 10071.713 | W7: =V7/AVERAGE($V$7:$V$18) -> 1.2082436 | Z7: Injeção 235 | AA7: ='Créditos CP'!C25 -> 4046 | AB7: ='Créditos CP'!C28 -> 6232 | AC7: ='Créditos CP'!C29 -> 5469 | AD7: ='Créditos CP'!C30 -> 2995 | AE7: ='Créditos CP'!C31 -> 2934 | AF7: ='Créditos CP'!C32 -> 2368
A8: 45689 | B8: 45712 | C8: 102849 | D8: 46607 | E8: 77220 | F8: =B8-B7 -> 38 | H8: =A8 -> 45689 | I8: =DATE(YEAR(H8),MONTH(H8),15) -> 45703 | J8: =MIN(_xlfn.XLOOKUP($H8,$A$2:$A$12,$B$2:$B$12))-I8 -> 9 | K8: =F8-J8 -> 29 | L8: {=_xlfn.XLOOKUP($H8,$A:$A,$C:$C)-_xlfn.XLOOKUP($H7,$A:$A,$C:$C)} -> 6570 | M8: {=_xlfn.XLOOKUP($H8,$A:$A,$D:$D)-_xlfn.XLOOKUP($H7,$A:$A,$D:$D)} -> 3329 | N8: =M8+L8 -> 9899 | O8: =$K8/SUM($J8:$K8)*N8+$J7/SUM($J7:$K7)*N7 -> 7980.1552 | P8: {=_xlfn.XLOOKUP($H8,$A:$A,$E:$E)-_xlfn.XLOOKUP($H7,$A:$A,$E:$E)} -> 5313 | Q8: =$K8/SUM($J8:$K8)*P8+$J7/SUM($J7:$K7)*P7 -> 4267.6234 | R8: {=_xlfn.XLOOKUP($H8,'Créditos CP'!A:A,'Créditos CP'!C:C)} -> 6232 | S8: {=_xlfn.XLOOKUP($H8,'Créditos CP'!A:A,'Créditos CP'!D:D)} -> 3812 | T8: =O8-R8 -> 1748.1552 | U8: =Q8-S8 -> 455.62341 | V8: =O8+Q8 -> 12247.779 | W8: =V8/AVERAGE($V$7:$V$18) -> 1.4692933 | Z8: Geração - injeção 235 | AA8: =AA5-AA7 -> 4258 | AB8: =AB5-AB7 -> 3667 | AC8: =AC5-AC7 -> 828 | AD8: =AD5-AD7 -> 3355 | AE8: =AE5-AE7 -> -888 | AF8: =AF5-AF7 -> 1146
A9: 45717 | B9: 45740 | C9: 107059 | D9: 48694 | E9: 80560 | F9: =B9-B8 -> 28 | H9: =A9 -> 45717 | I9: =DATE(YEAR(H9),MONTH(H9),15) -> 45731 | J9: =MIN(_xlfn.XLOOKUP($H9,$A$2:$A$12,$B$2:$B$12))-I9 -> 9 | K9: =F9-J9 -> 19 | L9: {=_xlfn.XLOOKUP($H9,$A:$A,$C:$C)-_xlfn.XLOOKUP($H8,$A:$A,$C:$C)} -> 4210 | M9: {=_xlfn.XLOOKUP($H9,$A:$A,$D:$D)-_xlfn.XLOOKUP($H8,$A:$A,$D:$D)} -> 2087 | N9: =M9+L9 -> 6297 | O9: =$K9/SUM($J9:$K9)*N9+$J8/SUM($J8:$K8)*N8 -> 6617.4643 | P9: {=_xlfn.XLOOKUP($H9,$A:$A,$E:$E)-_xlfn.XLOOKUP($H8,$A:$A,$E:$E)} -> 3340 | Q9: =$K9/SUM($J9:$K9)*P9+$J8/SUM($J8:$K8)*P8 -> 3524.7707 | R9: {=_xlfn.XLOOKUP($H9,'Créditos CP'!A:A,'Créditos CP'!C:C)} -> 5469 | S9: {=_xlfn.XLOOKUP($H9,'Créditos CP'!A:A,'Créditos CP'!D:D)} -> 3498 | T9: =O9-R9 -> 1148.4643 | U9: =Q9-S9 -> 26.770677 | V9: =O9+Q9 -> 10142.235 | W9: =V9/AVERAGE($V$7:$V$18) -> 1.2167037 | Z9: Geração ajustada - injeção 235 | AA9: =AA6-AA7 -> 2182 | AB9: =AB6-AB7 -> 1583 | AC9: =AC6-AC7 -> 1562.6429 | AD9: =AD6-AD7 -> 0 | AE9: =AE6-AE7 -> 1744.8824 | AF9: =AF6-AF7 -> -2560.6046
A10: 45748 | B10: 45782 | C10: 111346 | D10: 50757 | E10: 84049 | F10: =B10-B9 -> 42 | H10: =A10 -> 45748 | I10: =DATE(YEAR(H10),MONTH(H10),15) -> 45762 | J10: =MIN(_xlfn.XLOOKUP($H10,$A$2:$A$12,$B$2:$B$12))-I10 -> 20 | K10: =F10-J10 -> 22 | L10: {=_xlfn.XLOOKUP($H10,$A:$A,$C:$C)-_xlfn.XLOOKUP($H9,$A:$A,$C:$C)} -> 4287 | M10: {=_xlfn.XLOOKUP($H10,$A:$A,$D:$D)-_xlfn.XLOOKUP($H9,$A:$A,$D:$D)} -> 2063 | N10: =M10+L10 -> 6350 | O10: =$K10/SUM($J10:$K10)*N10+$J9/SUM($J9:$K9)*N9 -> 5350.2262 | P10: {=_xlfn.XLOOKUP($H10,$A:$A,$E:$E)-_xlfn.XLOOKUP($H9,$A:$A,$E:$E)} -> 3489 | Q10: =$K10/SUM($J10:$K10)*P10+$J9/SUM($J9:$K9)*P9 -> 2901.1429 | R10: {=_xlfn.XLOOKUP($H10,'Créditos CP'!A:A,'Créditos CP'!C:C)} -> 2995 | S10: {=_xlfn.XLOOKUP($H10,'Créditos CP'!A:A,'Créditos CP'!D:D)} -> 2003 | T10: =O10-R10 -> 2355.2262 | U10: =Q10-S10 -> 898.14286 | V10: =O10+Q10 -> 8251.369 | W10: =V10/AVERAGE($V$7:$V$18) -> 0.98986778 | Z10: Geração 281 | AB10: =E8-E7 -> 5313 | AC10: =$E$9-$E$8 -> 3340 | AD10: =$E10-$E9 -> 3489 | AE10: =$E11-$E10 -> 1381 | AF10: =$E12-$E11 -> 2347
A11: 45778 | B11: 45799 | C11: 112724 | D11: 51425 | E11: 85430 | F11: =B11-B10 -> 17 | H11: =A11 -> 45778 | I11: =DATE(YEAR(H11),MONTH(H11),15) -> 45792 | J11: =MIN(_xlfn.XLOOKUP($H11,$A$2:$A$12,$B$2:$B$12))-I11 -> 7 | K11: =F11-J11 -> 10 | L11: {=_xlfn.XLOOKUP($H11,$A:$A,$C:$C)-_xlfn.XLOOKUP($H10,$A:$A,$C:$C)} -> 1378 | M11: {=_xlfn.XLOOKUP($H11,$A:$A,$D:$D)-_xlfn.XLOOKUP($H10,$A:$A,$D:$D)} -> 668 | N11: =M11+L11 -> 2046 | O11: =$K11/SUM($J11:$K11)*N11+$J10/SUM($J10:$K10)*N10 -> 4227.3389 | P11: {=_xlfn.XLOOKUP($H11,$A:$A,$E:$E)-_xlfn.XLOOKUP($H10,$A:$A,$E:$E)} -> 1381 | Q11: =$K11/SUM($J11:$K11)*P11+$J10/SUM($J10:$K10)*P10 -> 2473.7815 | R11: {=_xlfn.XLOOKUP($H11,'Créditos CP'!A:A,'Créditos CP'!C:C)} -> 2934 | S11: {=_xlfn.XLOOKUP($H11,'Créditos CP'!A:A,'Créditos CP'!D:D)} -> 2013 | T11: =O11-R11 -> 1293.3389 | U11: =Q11-S11 -> 460.78151 | V11: =O11+Q11 -> 6701.1204 | W11: =V11/AVERAGE($V$7:$V$18) -> 0.80389366 | Z11: Geração ajustada 281 | AB11: =30/(B8-B7)*AB10 -> 4194.4737 | AC11: =AB10-AB11+22/($B$9-$B$8)*AC10 -> 3742.812 | AD11: =MAX(AD12,AC10-AC11+23/($B$10-$B$9)*AD10) -> 2003 | AE11: =AD10-AD11+11/($B$9-$B$8)*AE10 -> 2028.5357 | AF11: =AE10-AE11+25/($B$9-$B$8)*AF10 -> 1448
A12: 45809 | B12: 45835 | C12: 115090 | D12: 52573 | E12: 87777 | F12: =B12-B11 -> 36 | H12: =A12 -> 45809 | I12: =DATE(YEAR(H12),MONTH(H12),15) -> 45823 | J12: =MIN(_xlfn.XLOOKUP($H12,$A$2:$A$12,$B$2:$B$12))-I12 -> 12 | K12: =F12-J12 -> 24 | L12: {=_xlfn.XLOOKUP($H12,$A:$A,$C:$C)-_xlfn.XLOOKUP($H11,$A:$A,$C:$C)} -> 2366 | M12: {=_xlfn.XLOOKUP($H12,$A:$A,$D:$D)-_xlfn.XLOOKUP($H11,$A:$A,$D:$D)} -> 1148 | N12: =M12+L12 -> 3514 | O12: =$K12/SUM($J12:$K12)*N12+$J11/SUM($J11:$K11)*N11 -> 3185.1373 | P12: {=_xlfn.XLOOKUP($H12,$A:$A,$E:$E)-_xlfn.XLOOKUP($H11,$A:$A,$E:$E)} -> 2347 | Q12: =$K12/SUM($J12:$K12)*P12+$J11/SUM($J11:$K11)*P11 -> 2133.3137 | R12: {=_xlfn.XLOOKUP($H12,'Créditos CP'!A:A,'Créditos CP'!C:C)} -> 2368 | S12: {=_xlfn.XLOOKUP($H12,'Créditos CP'!A:A,'Créditos CP'!D:D)} -> 1960 | T12: =O12-R12 -> 817.13725 | U12: =Q12-S12 -> 173.31373 | V12: =O12+Q12 -> 5318.451 | W12: =V12/AVERAGE($V$7:$V$18) -> 0.638023 | Z12: Injeção 281 | AB12: ='Créditos CP'!D28 -> 3812 | AC12: ='Créditos CP'!D29 -> 3498 | AD12: ='Créditos CP'!D30 -> 2003 | AE12: ='Créditos CP'!D31 -> 2013 | AF12: ='Créditos CP'!D32 -> 1960
A13: 45839 | B13: 45853 | C13: 116347 | D13: 53176 | E13: 88976 | F13: =B13-B12 -> 18 | H13: =A13 -> 45839 | I13: =DATE(YEAR(H13),MONTH(H13),15) -> 45853 | J13: {=MIN(_xlfn.XLOOKUP($H13,$A:$A,$B:$B))-I13} -> 0 | K13: =F13-J13 -> 18 | L13: {=_xlfn.XLOOKUP($H13,$A:$A,$C:$C)-_xlfn.XLOOKUP($H12,$A:$A,$C:$C)} -> 1257 | M13: {=_xlfn.XLOOKUP($H13,$A:$A,$D:$D)-_xlfn.XLOOKUP($H12,$A:$A,$D:$D)} -> 603 | N13: =M13+L13 -> 1860 | O13: =$K13/SUM($J13:$K13)*N13+$J12/SUM($J12:$K12)*N12 -> 3031.3333 | P13: {=_xlfn.XLOOKUP($H13,$A:$A,$E:$E)-_xlfn.XLOOKUP($H12,$A:$A,$E:$E)} -> 1199 | Q13: =$K13/SUM($J13:$K13)*P13+$J12/SUM($J12:$K12)*P12 -> 1981.3333 | R13: {=_xlfn.XLOOKUP($H13,'Créditos CP'!A:A,'Créditos CP'!C:C)} -> 2358 | S13: {=_xlfn.XLOOKUP($H13,'Créditos CP'!A:A,'Créditos CP'!D:D)} -> 1762 | T13: =O13-R13 -> 673.33333 | U13: =Q13-S13 -> 219.33333 | V13: =O13+Q13 -> 5012.6667 | W13: =V13/AVERAGE($V$7:$V$18) -> 0.60133987 | Z13: Geração - injeção 281 | AB13: =AB10-AB12 -> 1501 | AC13: =AC10-AC12 -> -158 | AD13: =AD10-AD12 -> 1486 | AE13: =AE10-AE12 -> -632 | AF13: =AF10-AF12 -> 387
A14: 45870 | B14: 45888 | C14: 119055 | D14: 54463 | E14: 91408 | F14: =B14-B13 -> 35 | H14: =A14 -> 45870 | I14: =DATE(YEAR(H14),MONTH(H14),15) -> 45884 | J14: {=MIN(_xlfn.XLOOKUP($H14,$A:$A,$B:$B))-I14} -> 4 | K14: =F14-J14 -> 31 | L14: {=_xlfn.XLOOKUP($H14,$A:$A,$C:$C)-_xlfn.XLOOKUP($H13,$A:$A,$C:$C)} -> 2708 | M14: {=_xlfn.XLOOKUP($H14,$A:$A,$D:$D)-_xlfn.XLOOKUP($H13,$A:$A,$D:$D)} -> 1287 | N14: =M14+L14 -> 3995 | O14: =$K14/SUM($J14:$K14)*N14+$J13/SUM($J13:$K13)*N13 -> 3538.4286 | P14: {=_xlfn.XLOOKUP($H14,$A:$A,$E:$E)-_xlfn.XLOOKUP($H13,$A:$A,$E:$E)} -> 2432 | Q14: =$K14/SUM($J14:$K14)*P14+$J13/SUM($J13:$K13)*P13 -> 2154.0571 | R14: {=_xlfn.XLOOKUP($H14,'Créditos CP'!A:A,'Créditos CP'!C:C)} -> 3139 | S14: {=_xlfn.XLOOKUP($H14,'Créditos CP'!A:A,'Créditos CP'!D:D)} -> 2098 | T14: =O14-R14 -> 399.42857 | U14: =Q14-S14 -> 56.057143 | V14: =O14+Q14 -> 5692.4857 | W14: =V14/AVERAGE($V$7:$V$18) -> 0.68289373 | Z14: Geração ajustada - injeção 281 | AB14: =AB11-AB12 -> 382.47368 | AC14: =AC11-AC12 -> 244.81203 | AD14: =AD11-AD12 -> 0 | AE14: =AE11-AE12 -> 15.535714 | AF14: =AF11-AF12 -> -512
A15: 45901 | B15: 45930 | C15: 124063 | D15: 56915 | E15: 95456 | F15: =B15-B14 -> 42 | H15: =A15 -> 45901 | I15: =DATE(YEAR(H15),MONTH(H15),15) -> 45915 | J15: {=MIN(_xlfn.XLOOKUP($H15,$A:$A,$B:$B))-I15} -> 15 | K15: =F15-J15 -> 27 | L15: {=_xlfn.XLOOKUP($H15,$A:$A,$C:$C)-_xlfn.XLOOKUP($H14,$A:$A,$C:$C)} -> 5008 | M15: {=_xlfn.XLOOKUP($H15,$A:$A,$D:$D)-_xlfn.XLOOKUP($H14,$A:$A,$D:$D)} -> 2452 | N15: =M15+L15 -> 7460 | O15: =$K15/SUM($J15:$K15)*N15+$J14/SUM($J14:$K14)*N14 -> 5252.2857 | P15: {=_xlfn.XLOOKUP($H15,$A:$A,$E:$E)-_xlfn.XLOOKUP($H14,$A:$A,$E:$E)} -> 4048 | Q15: =$K15/SUM($J15:$K15)*P15+$J14/SUM($J14:$K14)*P14 -> 2880.2286 | R15: {=_xlfn.XLOOKUP($H15,'Créditos CP'!A:A,'Créditos CP'!C:C)} -> 3612 | S15: {=_xlfn.XLOOKUP($H15,'Créditos CP'!A:A,'Créditos CP'!D:D)} -> 2595 | T15: =O15-R15 -> 1640.2857 | U15: =Q15-S15 -> 285.22857 | V15: =O15+Q15 -> 8132.5143 | W15: =V15/AVERAGE($V$7:$V$18) -> 0.97560948
A16: 45931 | B16: 45954 | C16: 127009 | D16: 58366 | E16: 97769 | F16: =B16-B15 -> 24 | H16: =A16 -> 45931 | I16: =DATE(YEAR(H16),MONTH(H16),15) -> 45945 | J16: {=MIN(_xlfn.XLOOKUP($H16,$A:$A,$B:$B))-I16} -> 9 | K16: =F16-J16 -> 15 | L16: {=_xlfn.XLOOKUP($H16,$A:$A,$C:$C)-_xlfn.XLOOKUP($H15,$A:$A,$C:$C)} -> 2946 | M16: {=_xlfn.XLOOKUP($H16,$A:$A,$D:$D)-_xlfn.XLOOKUP($H15,$A:$A,$D:$D)} -> 1451 | N16: =M16+L16 -> 4397 | O16: =$K16/SUM($J16:$K16)*N16+$J15/SUM($J15:$K15)*N15 -> 5412.4107 | P16: {=_xlfn.XLOOKUP($H16,$A:$A,$E:$E)-_xlfn.XLOOKUP($H15,$A:$A,$E:$E)} -> 2313 | Q16: =$K16/SUM($J16:$K16)*P16+$J15/SUM($J15:$K15)*P15 -> 2891.3393 | R16: {=_xlfn.XLOOKUP($H16,'Créditos CP'!A:A,'Créditos CP'!C:C)} -> 4187 | S16: {=_xlfn.XLOOKUP($H16,'Créditos CP'!A:A,'Créditos CP'!D:D)} -> 2766 | T16: =O16-R16 -> 1225.4107 | U16: =Q16-S16 -> 125.33929 | V16: =O16+Q16 -> 8303.75 | W16: =V16/AVERAGE($V$7:$V$18) -> 0.99615161
A17: 45962 | B17: 45980 | C17: 130468 | D17: 60091 | E17: 100714 | F17: =B17-B16 -> 26 | H17: =A17 -> 45962 | I17: =DATE(YEAR(H17),MONTH(H17),15) -> 45976 | J17: {=MIN(_xlfn.XLOOKUP($H17,$A:$A,$B:$B))-I17} -> 4 | K17: =F17-J17 -> 22 | L17: {=_xlfn.XLOOKUP($H17,$A:$A,$C:$C)-_xlfn.XLOOKUP($H16,$A:$A,$C:$C)} -> 3459 | M17: {=_xlfn.XLOOKUP($H17,$A:$A,$D:$D)-_xlfn.XLOOKUP($H16,$A:$A,$D:$D)} -> 1725 | N17: =M17+L17 -> 5184 | O17: =$K17/SUM($J17:$K17)*N17+$J16/SUM($J16:$K16)*N16 -> 6035.3365 | P17: {=_xlfn.XLOOKUP($H17,$A:$A,$E:$E)-_xlfn.XLOOKUP($H16,$A:$A,$E:$E)} -> 2945 | Q17: =$K17/SUM($J17:$K17)*P17+$J16/SUM($J16:$K16)*P16 -> 3359.2981 | R17: {=_xlfn.XLOOKUP($H17,'Créditos CP'!A:A,'Créditos CP'!C:C)} -> 4324 | S17: {=_xlfn.XLOOKUP($H17,'Créditos CP'!A:A,'Créditos CP'!D:D)} -> 2814 | T17: =O17-R17 -> 1711.3365 | U17: =Q17-S17 -> 545.29808 | V17: =O17+Q17 -> 9394.6346 | W17: =V17/AVERAGE($V$7:$V$18) -> 1.1270186
A18: 45992 | B18: 46009 | C18: 135101 | D18: 62502 | E18: 104278 | F18: =B18-B17 -> 29 | H18: =A18 -> 45992 | I18: =DATE(YEAR(H18),MONTH(H18),15) -> 46006 | J18: {=MIN(_xlfn.XLOOKUP($H18,$A:$A,$B:$B))-I18} -> 3 | K18: =F18-J18 -> 26 | L18: {=_xlfn.XLOOKUP($H18,$A:$A,$C:$C)-_xlfn.XLOOKUP($H17,$A:$A,$C:$C)} -> 4633 | M18: {=_xlfn.XLOOKUP($H18,$A:$A,$D:$D)-_xlfn.XLOOKUP($H17,$A:$A,$D:$D)} -> 2411 | N18: =M18+L18 -> 7044 | O18: =$K18/SUM($J18:$K18)*N18+$J17/SUM($J17:$K17)*N17 -> 7112.8488 | P18: {=_xlfn.XLOOKUP($H18,$A:$A,$E:$E)-_xlfn.XLOOKUP($H17,$A:$A,$E:$E)} -> 3564 | Q18: =$K18/SUM($J18:$K18)*P18+$J17/SUM($J17:$K17)*P17 -> 3648.3873 | R18: {=_xlfn.XLOOKUP($H18,'Créditos CP'!A:A,'Créditos CP'!C:C)} -> 4968 | S18: {=_xlfn.XLOOKUP($H18,'Créditos CP'!A:A,'Créditos CP'!D:D)} -> 3262 | T18: =O18-R18 -> 2144.8488 | U18: =Q18-S18 -> 386.38727 | V18: =O18+Q18 -> 10761.236 | W18: =V18/AVERAGE($V$7:$V$18) -> 1.2909616
A19: 46023 | B19: 46041 | C19: 139971 | D19: 65115 | E19: 108335 | F19: =B19-B18 -> 32 | H19: =A19 -> 46023 | I19: =DATE(YEAR(H19),MONTH(H19),15) -> 46037 | J19: {=MIN(_xlfn.XLOOKUP($H19,$A:$A,$B:$B))-I19} -> 4 | K19: =F19-J19 -> 28 | L19: {=_xlfn.XLOOKUP($H19,$A:$A,$C:$C)-_xlfn.XLOOKUP($H18,$A:$A,$C:$C)} -> 4870 | M19: {=_xlfn.XLOOKUP($H19,$A:$A,$D:$D)-_xlfn.XLOOKUP($H18,$A:$A,$D:$D)} -> 2613 | N19: =M19+L19 -> 7483 | O19: =$K19/SUM($J19:$K19)*N19+$J18/SUM($J18:$K18)*N18 -> 7276.3147 | P19: {=_xlfn.XLOOKUP($H19,$A:$A,$E:$E)-_xlfn.XLOOKUP($H18,$A:$A,$E:$E)} -> 4057 | Q19: =$K19/SUM($J19:$K19)*P19+$J18/SUM($J18:$K18)*P18 -> 3918.5647 | R19: {=_xlfn.XLOOKUP($H19,'Créditos CP'!A:A,'Créditos CP'!C:C)} -> 6868 | S19: {=_xlfn.XLOOKUP($H19,'Créditos CP'!A:A,'Créditos CP'!D:D)} -> 3875 | T19: =O19-R19 -> 408.31466 | U19: =Q19-S19 -> 43.564655 | V19: =O19+Q19 -> 11194.879
A20: 46054 | B20: 46065 | C20: 142229 | D20: 66586 | E20: 110673 | F20: =B20-B19 -> 24 | H20: =A20 -> 46054 | I20: =DATE(YEAR(H20),MONTH(H20),15) -> 46068 | J20: {=MIN(_xlfn.XLOOKUP($H20,$A:$A,$B:$B))-I20} -> -3 | K20: =F20-J20 -> 27 | L20: {=_xlfn.XLOOKUP($H20,$A:$A,$C:$C)-_xlfn.XLOOKUP($H19,$A:$A,$C:$C)} -> 2258 | M20: {=_xlfn.XLOOKUP($H20,$A:$A,$D:$D)-_xlfn.XLOOKUP($H19,$A:$A,$D:$D)} -> 1471 | N20: =M20+L20 -> 3729 | O20: =$K20/SUM($J20:$K20)*N20+$J19/SUM($J19:$K19)*N19 -> 5130.5 | P20: {=_xlfn.XLOOKUP($H20,$A:$A,$E:$E)-_xlfn.XLOOKUP($H19,$A:$A,$E:$E)} -> 2338 | Q20: =$K20/SUM($J20:$K20)*P20+$J19/SUM($J19:$K19)*P19 -> 3137.375 | R20: {=_xlfn.XLOOKUP($H20,'Créditos CP'!A:A,'Créditos CP'!C:C)} -> 4439 | S20: {=_xlfn.XLOOKUP($H20,'Créditos CP'!A:A,'Créditos CP'!D:D)} -> 2674 | T20: =O20-R20 -> 691.5 | U20: =Q20-S20 -> 463.375 | V20: =O20+Q20 -> 8267.875
A21: 46082 | B21: 46100 | C21: 147468 | D21: 68939 | E21: 114366 | F21: =B21-B20 -> 35 | H21: =A21 -> 46082 | I21: =DATE(YEAR(H21),MONTH(H21),15) -> 46096 | J21: {=MIN(_xlfn.XLOOKUP($H21,$A:$A,$B:$B))-I21} -> 4 | K21: =F21-J21 -> 31 | L21: {=_xlfn.XLOOKUP($H21,$A:$A,$C:$C)-_xlfn.XLOOKUP($H20,$A:$A,$C:$C)} -> 5239 | M21: {=_xlfn.XLOOKUP($H21,$A:$A,$D:$D)-_xlfn.XLOOKUP($H20,$A:$A,$D:$D)} -> 2353 | N21: =M21+L21 -> 7592 | O21: =$K21/SUM($J21:$K21)*N21+$J20/SUM($J20:$K20)*N20 -> 6258.2179 | P21: {=_xlfn.XLOOKUP($H21,$A:$A,$E:$E)-_xlfn.XLOOKUP($H20,$A:$A,$E:$E)} -> 3693 | Q21: =$K21/SUM($J21:$K21)*P21+$J20/SUM($J20:$K20)*P20 -> 2978.6929 | R21: {=_xlfn.XLOOKUP($H21,'Créditos CP'!A:A,'Créditos CP'!C:C)} -> 4747 | S21: {=_xlfn.XLOOKUP($H21,'Créditos CP'!A:A,'Créditos CP'!D:D)} -> 3086 | T21: =O21-R21 -> 1511.2179 | U21: =Q21-S21 -> -107.30714 | V21: =O21+Q21 -> 9236.9107
A22: 46113 | B22: 46128 | C22: 150725 | D22: 70560 | E22: 117143 | F22: =B22-B21 -> 28 | H22: =A22 -> 46113 | I22: =DATE(YEAR(H22),MONTH(H22),15) -> 46127 | J22: {=MIN(_xlfn.XLOOKUP($H22,$A:$A,$B:$B))-I22} -> 1 | K22: =F22-J22 -> 27 | L22: {=_xlfn.XLOOKUP($H22,$A:$A,$C:$C)-_xlfn.XLOOKUP($H21,$A:$A,$C:$C)} -> 3257 | M22: {=_xlfn.XLOOKUP($H22,$A:$A,$D:$D)-_xlfn.XLOOKUP($H21,$A:$A,$D:$D)} -> 1621 | N22: =M22+L22 -> 4878 | O22: =$K22/SUM($J22:$K22)*N22+$J21/SUM($J21:$K21)*N21 -> 5571.4429 | P22: {=_xlfn.XLOOKUP($H22,$A:$A,$E:$E)-_xlfn.XLOOKUP($H21,$A:$A,$E:$E)} -> 2777 | Q22: =$K22/SUM($J22:$K22)*P22+$J21/SUM($J21:$K21)*P21 -> 3099.8786 | R22: {=_xlfn.XLOOKUP($H22,'Créditos CP'!A:A,'Créditos CP'!C:C)} -> 3234 | S22: {=_xlfn.XLOOKUP($H22,'Créditos CP'!A:A,'Créditos CP'!D:D)} -> 2541 | T22: =O22-R22 -> 2337.4429 | U22: =Q22-S22 -> 558.87857 | V22: =O22+Q22 -> 8671.3214
A23: 46143 | B23: 46154 | C23: 153297 | D23: 71797 | E23: 119412 | F23: =B23-B22 -> 26 | H23: =A23 -> 46143 | I23: =DATE(YEAR(H23),MONTH(H23),15) -> 46157 | J23: {=MIN(_xlfn.XLOOKUP($H23,$A:$A,$B:$B))-I23} -> -3 | K23: =F23-J23 -> 29 | L23: {=_xlfn.XLOOKUP($H23,$A:$A,$C:$C)-_xlfn.XLOOKUP($H22,$A:$A,$C:$C)} -> 2572 | M23: {=_xlfn.XLOOKUP($H23,$A:$A,$D:$D)-_xlfn.XLOOKUP($H22,$A:$A,$D:$D)} -> 1237 | N23: =M23+L23 -> 3809 | O23: =$K23/SUM($J23:$K23)*N23+$J22/SUM($J22:$K22)*N22 -> 4422.7143 | P23: {=_xlfn.XLOOKUP($H23,$A:$A,$E:$E)-_xlfn.XLOOKUP($H22,$A:$A,$E:$E)} -> 2269 | Q23: =$K23/SUM($J23:$K23)*P23+$J22/SUM($J22:$K22)*P22 -> 2629.9863 | R23: {=_xlfn.XLOOKUP($H23,'Créditos CP'!A:A,'Créditos CP'!C:C)} -> 2819 | S23: {=_xlfn.XLOOKUP($H23,'Créditos CP'!A:A,'Créditos CP'!D:D)} -> 2286 | T23: =O23-R23 -> 1603.7143 | U23: =Q23-S23 -> 343.98626 | V23: =O23+Q23 -> 7052.7005
A24: 46174 | B24: 46203 | C24: 156165 | D24: 73183 | E24: 122092 | F24: =B24-B23 -> 49 | H24: =A24 -> 46174 | I24: =DATE(YEAR(H24),MONTH(H24),15) -> 46188 | J24: {=MIN(_xlfn.XLOOKUP($H24,$A:$A,$B:$B))-I24} -> 15 | K24: =F24-J24 -> 34 | L24: {=_xlfn.XLOOKUP($H24,$A:$A,$C:$C)-_xlfn.XLOOKUP($H23,$A:$A,$C:$C)} -> 2868 | M24: {=_xlfn.XLOOKUP($H24,$A:$A,$D:$D)-_xlfn.XLOOKUP($H23,$A:$A,$D:$D)} -> 1386 | N24: =M24+L24 -> 4254 | O24: =$K24/SUM($J24:$K24)*N24+$J23/SUM($J23:$K23)*N23 -> 2512.2551 | P24: {=_xlfn.XLOOKUP($H24,$A:$A,$E:$E)-_xlfn.XLOOKUP($H23,$A:$A,$E:$E)} -> 2680 | Q24: =$K24/SUM($J24:$K24)*P24+$J23/SUM($J23:$K23)*P23 -> 1597.7841 | R24: {=_xlfn.XLOOKUP($H24,'Créditos CP'!A:A,'Créditos CP'!C:C)} -> 1998 | S24: {=_xlfn.XLOOKUP($H24,'Créditos CP'!A:A,'Créditos CP'!D:D)} -> 1686 | T24: =O24-R24 -> 514.2551 | U24: =Q24-S24 -> -88.215856 | V24: =O24+Q24 -> 4110.0392
A25: 46204 | B25: 46223 | C25: 157666 | D25: 73914 | E25: 123584 | F25: =B25-B24 -> 20 | H25: =A25 -> 46204 | I25: =DATE(YEAR(H25),MONTH(H25),15) -> 46218 | J25: {=MIN(_xlfn.XLOOKUP($H25,$A:$A,$B:$B))-I25} -> 5 | K25: =F25-J25 -> 15 | L25: {=_xlfn.XLOOKUP($H25,$A:$A,$C:$C)-_xlfn.XLOOKUP($H24,$A:$A,$C:$C)} -> 1501 | M25: {=_xlfn.XLOOKUP($H25,$A:$A,$D:$D)-_xlfn.XLOOKUP($H24,$A:$A,$D:$D)} -> 731 | N25: =M25+L25 -> 2232 | O25: =$K25/SUM($J25:$K25)*N25+$J24/SUM($J24:$K24)*N24 -> 2976.2449 | P25: {=_xlfn.XLOOKUP($H25,$A:$A,$E:$E)-_xlfn.XLOOKUP($H24,$A:$A,$E:$E)} -> 1492 | Q25: =$K25/SUM($J25:$K25)*P25+$J24/SUM($J24:$K24)*P24 -> 1939.4082 | R25: {=_xlfn.XLOOKUP($H25,'Créditos CP'!A:A,'Créditos CP'!C:C)} -> 1930 | S25: {=_xlfn.XLOOKUP($H25,'Créditos CP'!A:A,'Créditos CP'!D:D)} -> 1605 | T25: =O25-R25 -> 1046.2449 | U25: =Q25-S25 -> 334.40816 | V25: =O25+Q25 -> 4915.6531
A26: 46235 | B26: 46255 | C26: 160328 | D26: 75146 | E26: 126016 | F26: =B26-B25 -> 32 | H26: =A26 -> 46235 | I26: =DATE(YEAR(H26),MONTH(H26),15) -> 46249 | J26: {=MIN(_xlfn.XLOOKUP($H26,$A:$A,$B:$B))-I26} -> 6 | K26: =F26-J26 -> 26 | L26: {=_xlfn.XLOOKUP($H26,$A:$A,$C:$C)-_xlfn.XLOOKUP($H25,$A:$A,$C:$C)} -> 2662 | M26: {=_xlfn.XLOOKUP($H26,$A:$A,$D:$D)-_xlfn.XLOOKUP($H25,$A:$A,$D:$D)} -> 1232 | N26: =M26+L26 -> 3894 | O26: =$K26/SUM($J26:$K26)*N26+$J25/SUM($J25:$K25)*N25 -> 3721.875 | P26: {=_xlfn.XLOOKUP($H26,$A:$A,$E:$E)-_xlfn.XLOOKUP($H25,$A:$A,$E:$E)} -> 2432 | Q26: =$K26/SUM($J26:$K26)*P26+$J25/SUM($J25:$K25)*P25 -> 2349 | R26: {=_xlfn.XLOOKUP($H26,'Créditos CP'!A:A,'Créditos CP'!C:C)} -> 3201 | S26: {=_xlfn.XLOOKUP($H26,'Créditos CP'!A:A,'Créditos CP'!D:D)} -> 2419 | T26: =O26-R26 -> 520.875 | U26: =Q26-S26 -> -70 | V26: =O26+Q26 -> 6070.875

Sheet Créditos ZeroHum
G1: Maricá (UC 1138227)
A2: Data da leitura | B2: Mês de referência | C2: Energia injetada pela UC 1138227 | D2: Créditos gerados em favor da UC 1138227 | E2: Créditos gerados em favor da | G2: Data da leitura | H2: Mês de referência | I2: Saldo inicial | J2: Créditos recebidos | K2: Saldo utilizado | L2: Saldo final
A3: 46106 | B3: 46082 | C3: 8342 | D3: =C3 -> 8342 | E3: 0 | G3: 46106 | H3: 46082 | I3: 0 | J3: =D3 -> 8342 | K3: 3008 | L3: =I3+J3-K3 -> 5334
A4: 46136 | B4: 46113 | C4: 2080 | D4: =C4 -> 2080 | G4: 46136 | H4: 46113 | I4: =L3 -> 5334 | J4: =D4 -> 2080 | K4: 1647 | L4: =I4+J4-K4 -> 5767
A5: 46167 | B5: 46143 | C5: 5211 | D5: 5211 | G5: 46167 | H5: 46143 | I5: =L4 -> 5767 | J5: =D5 -> 5211 | K5: 3678 | L5: =I5+J5-K5 -> 7300
D7: =SUM(D3:D5)/3 -> 5211

Sheet Crédito Pres Kennedy
A1: Pres Kennedy | G1: Pio borges
A2: Data da leitura | B2: Mês de referência | C2: Energia injetada pela UC 62920508 | D2: Créditos gerados em favor da Geraldo Martins | E2: Créditos gerados em favor da Pio Borges | G2: Data da leitura | H2: Mês de referência | I2: Saldo inicial | J2: Créditos recebidos | K2: Saldo utilizado | L2: Saldo final
A3: 45796 | B3: 45778 | C3: 849 | D3: =77%*C3 -> 653.73 | E3: =21%*C3 -> 178.29
A4: 45826 | B4: 45809 | C4: 2837 | D4: =77%*C4 -> 2184.49 | E4: =21%*C4 -> 595.77 | G4: 45822 | H4: 45809 | I4: =L3 -> 0 | J4: =K4+L4-I4 -> 178.29 | K4: 178.29 | L4: 0
A5: 45856 | B5: 45839 | C5: 2642 | D5: =77%*C5 -> 2034.34 | E5: =21%*C5 -> 554.82 | H5: 45839 | I5: =L4 -> 0 | J5: =K5+L5-I5 -> 595.77 | K5: 585 | L5: 10.77
A6: 45888 | B6: 45870 | C6: 2926 | D6: =77%*C6 -> 2253.02 | E6: =21%*C6 -> 614.46 | G6: 46248 | H6: 45870 | I6: =L5 -> 10.77 | J6: =K6+L6-I6 -> 554.82 | K6: 565.59 | L6: 0
B7: 45901 | C7: 0 | D7: =77%*C7 -> 0 | E7: =21%*C7 -> 0 | G7: 45915 | H7: 45901 | I7: =L6 -> 0 | J7: =K7+L7-I7 -> 614 | K7: 614 | L7: 0
A8: 45950 | B8: 45931 | C8: 4231 | D8: =77%*C8 -> 3257.87 | E8: =21%*C8 -> 888.51 | G8: 45945 | H8: 45931 | I8: =L7 -> 0 | J8: =K8+L8-I8 -> 0 | K8: 0 | L8: 0
A9: 45979 | B9: 45962 | C9: 4045 | D9: =77%*C9 -> 3114.65 | E9: =21%*C9 -> 849.45 | G9: 45974 | H9: 45962 | I9: =L8 -> 0 | J9: =K9+L9-I9 -> 888.51 | K9: 680 | L9: 208.51
A10: 46008 | B10: 45992 | C10: 2235 | D10: =77%*C10 -> 1720.95 | E10: =21%*C10 -> 469.35 | G10: 46369 | H10: 45992 | I10: =L9 -> 208.51 | J10: =K10+L10-I10 -> 849.49 | K10: 705 | L10: 353
A11: 46041 | B11: 46023 | C11: 2169 | D11: =77%*C11 -> 1670.13 | E11: =21%*C11 -> 455.49 | G11: 46036 | H11: 46023 | I11: =L10 -> 353 | J11: =K11+L11-I11 -> 469.131 | K11: 782 | L11: 40.131
A12: 46071 | B12: 46054 | C12: 4093 | D12: =77%*C12 -> 3151.61 | E12: =21%*C12 -> 859.53 | G12: 46065 | H12: 46054 | I12: =L11 -> 40.131 | J12: =K12+L12-I12 -> 455.669 | K12: 495.8 | L12: 0
A13: 46100 | B13: 46082 | C13: 3736 | D13: =77%*C13 -> 2876.72 | E13: =21%*C13 -> 784.56 | G13: 46097 | H13: 46082 | I13: =L12 -> 0 | J13: =K13+L13-I13 -> 859.53 | K13: 781 | L13: 78.53

Sheet Faturamento 235
A1: Categoria | B1: Tarifa | C1: Tarifa | D1: Tarifa | E1: Tarifa | F1: Tarifa | G1: Imposto | H1: Imposto | I1: Imposto | J1: Consumo | K1: Fornecimento | L1: Fornecimento | M1: Crédito | N1: Fatura | O1: Fatura | P1: Fatura | Q1: Desconto | R1: Desconto | S1: Preço
A2: Métrica | B2: TE | C2: TUSD | D2: Bandeira | E2: Bandeira | F2: Tarifa | G2: ICMS | H2: COFINS | I2: PIS | J2: Consumo (kWh) | K2: Eletricidade Enel (kWh) | L2: Eletricidade painel (kWh) | M2: Crédito utilizado | N2: Fatura Enel (R$) | O2: Total (R$) | P2: Fatura Zeta (R$) | Q2: 0.1 | R2: Bandeira | S2: kWh Zeta
A3: Unidade | B3: R$/kWh | C3: R$/kWh | D3: R$/kWh | E3: Cor | F3: R$/kWh | G3: % | H3: % | I3: % | J3: kWh | K3: kWh | L3: kWh | M3: kWh | N3: R$ | O3: R$ | P3: R$ | Q3: R$ | R3: R$ | S3: R$/kWh
A4: 44986 | F4: 1.10433 | J4: =K4+L4 -> 3074 | K4: 389 | L4: 2685 | M4: 289 | N4: 0 | O4: =F4*J4 -> 3394.7104 | P4: =O4*90%-K4*F4 -> 2625.655 | Q4: =10%*O4 -> 339.47104 | S4: =P4/J4 -> 0.85414932
A5: 45017 | F5: 1.19467 | J5: =K5+L5 -> 2351 | K5: 837 | L5: 1514 | M5: 737 | N5: 0 | O5: =F5*J5 -> 2808.6692 | P5: =O5*90%-K5*F5 -> 1527.8635 | Q5: =10%*O5 -> 280.86692 | S5: =P5/J5 -> 0.64987812
A6: 45047 | F6: 1.19467 | J6: =K6+L6 -> 2213.96 | K6: 953 | L6: 1260.96 | M6: 853 | N6: 0 | O6: =F6*J6 -> 2644.9516 | P6: =O6*90% -> 2380.4564 | Q6: =10%*O6 -> 264.49516 | S6: =P6/J6 -> 1.075203
A7: 45078 | F7: 1.1537 | J7: =K7+L7 -> 1180.9 | K7: 564 | L7: 616.9 | M7: 464 | N7: 0 | O7: =F7*J7 -> 1362.4043 | P7: =O7*90% -> 1226.1639 | Q7: =10%*O7 -> 136.24043 | S7: =P7/J7 -> 1.03833
A8: 45108 | F8: 1.144 | J8: =K8+L8 -> 1052 | K8: 512 | L8: 540 | M8: 412 | N8: 0 | O8: =F8*J8 -> 1203.488 | P8: =O8*90% -> 1083.1392 | Q8: =10%*O8 -> 120.3488 | S8: =P8/J8 -> 1.0296
A9: 45139 | F9: 1.18263 | J9: =K9+L9 -> 943.76 | K9: 392 | L9: 551.76 | M9: 292 | N9: 174.19 | O9: =F9*J9 -> 1116.1189 | P9: =O9*90%-N9 -> 830.317 | Q9: =10%*O9 -> 111.61189 | S9: =P9/J9 -> 0.87979677
A10: 45170 | F10: 1.22088 | J10: =K10+L10 -> 1099 | K10: 701 | L10: 398 | M10: 601 | N10: 252.07 | O10: =F10*J10 -> 1341.7471 | P10: =O10*90%-N10 -> 955.50241 | Q10: =10%*O10 -> 134.17471 | S10: =P10/J10 -> 0.86942894
A11: 45200 | F11: =0.40019+0.78695 -> 1.18714 | J11: =K11+L11 -> 1306 | K11: 689 | L11: 617 | M11: 589 | N11: 248.58 | O11: =F11*J11 -> 1550.4048 | P11: =O11*90%-N11 -> 1146.7844 | Q11: =10%*O11 -> 155.04048 | S11: =P11/J11 -> 0.87808909
A12: 45231 | F12: 1.1848 | J12: =K12+L12 -> 1791 | K12: 640 | L12: 1151 | M12: 540 | N12: 243.76 | O12: =F12*J12 -> 2121.9768 | P12: =O12*90%-N12 -> 1666.0191 | Q12: =10%*O12 -> 212.19768 | S12: =P12/J12 -> 0.93021726
A13: 45261 | F13: 1.22939 | J13: =K13+L13 -> 1387 | K13: 561 | L13: 826 | M13: 461 | N13: 233.42 | O13: =F13*J13 -> 1705.1639 | P13: =O13*90%-N13 -> 1301.2275 | Q13: =10%*O13 -> 170.51639 | S13: =P13/J13 -> 0.93815972
A14: 45292 | D14: 0 | E14: Verde | F14: 0.9535 | G14: 0.18 | H14: 0.0554 | I14: 0.012 | J14: 277 | K14: 31 | M14: 0 | N14: 122.36 | O14: =F14*J14 -> 264.1195 | P14: =O14*90%-N14 -> 115.34755 | Q14: =10%*O14 -> 26.41195 | S14: =P14/J14 -> 0.41641715
A15: 45323 | D15: 0 | E15: Verde | F15: 1.21725 | G15: 0.18 | H15: 0.0529 | I15: 0.0115 | J15: 1327 | K15: 226 | M15: 126 | N15: 327.46 | O15: =F15*J15 -> 1615.2907 | P15: =O15*90%-N15 -> 1126.3017 | Q15: =10%*O15 -> 161.52908 | S15: =P15/J15 -> 0.84875786
A16: 45352 | B16: 0.40123 | C16: 0.78901 | D16: 0 | E16: Verde | F16: =SUM(B16:D16) -> 1.19024 | G16: 0.22 | H16: 0.0354 | I16: 0.0078 | J16: 3074 | K16: 699 | M16: 599 | N16: 974.04 | O16: =F16*J16 -> 3658.7978 | P16: =O16*90%-N16 -> 2318.878 | Q16: =10%*O16 -> 365.87978 | S16: =P16/J16 -> 0.75435198
A17: 45383 | B17: 0.4035 | C17: 0.84087 | D17: 0 | E17: Verde | F17: =SUM(B17:D17) -> 1.24437 | G17: 0.24 | H17: 0.0309 | I17: 0.0068 | J17: 2351 | K17: 642 | M17: 542 | N17: 961.38 | O17: =F17*J17 -> 2925.5139 | P17: =O17*90%-N17 -> 1671.5825 | Q17: =10%*O17 -> 292.55139 | S17: =P17/J17 -> 0.71100914
A18: 45413 | B18: 0.40819 | C18: 0.86281 | D18: 0 | E18: Verde | F18: =SUM(B18:D18) -> 1.271 | G18: 0.24 | H18: 0.0453 | I18: 0.0097 | J18: 2214 | K18: 958 | M18: 858 | N18: 304.78 | O18: =F18*J18 -> 2813.994 | P18: =O18*90%-N18 -> 2227.8146 | Q18: =10%*O18 -> 281.3994 | S18: =P18/J18 -> 1.0062397
A19: 45444 | B19: 0.40963 | C19: 0.86584 | D19: 0 | E19: Verde | F19: =SUM(B19:D19) -> 1.27547 | G19: 0.24 | H19: 0.0479 | I19: 0.0104 | J19: 1181 | K19: 862 | M19: 762 | N19: 285.9 | O19: =F19*J19 -> 1506.3301 | P19: =O19*90%-N19 -> 1069.7971 | Q19: =10%*O19 -> 150.63301 | S19: =P19/J19 -> 0.90584002
A20: 45474 | B20: 0.40548 | C20: 0.85709 | D20: 0.01885 | E20: Amarela | F20: =SUM(B20:C20) -> 1.26257 | G20: 0.24 | H20: 0.04 | I20: 0.0087 | J20: 1052 | K20: 788 | M20: 688 | N20: 269.06 | O20: =F20*J20 -> 1328.2236 | P20: =O20*90%-N20 -> 926.34128 | Q20: =10%*O20 -> 132.82236 | S20: =P20/J20 -> 0.88055254
A21: 45505 | B21: 0.40054 | C21: 0.84668 | D21: 0.01366 | E21: Amarela | F21: =SUM(B21:C21) -> 1.24722 | G21: 0.24 | H21: 0.0305 | I21: 0.0066 | J21: 944 | K21: 355 | M21: 255 | N21: 177.89 | O21: =F21*J21 -> 1177.3757 | P21: =O21*90%-N21 -> 881.74811 | Q21: =10%*O21 -> 117.73757 | S21: =P21/J21 -> 0.9340552
A22: 45536 | B22: 0.40799 | C22: 0.86242 | D22: 0.02799 | E22: Vermelha | F22: =SUM(B22:C22) -> 1.27041 | G22: 0.24 | H22: 0.0443 | I22: 0.0096 | J22: 1099 | K22: 592 | M22: 492 | N22: 231.69 | O22: =F22*J22 -> 1396.1806 | P22: =O22*90%-N22 -> 1024.8725 | Q22: =10%*O22 -> 139.61806 | S22: =P22/J22 -> 0.93255007
A23: 45566 | B23: 0.40902 | C23: 0.86453 | D23: 0.08526 | E23: Vermelha 2 | F23: =SUM(B23:C23) -> 1.27355 | G23: 0.24 | H23: 0.0467 | I23: 0.0102 | J23: =J11 -> 1306 | K23: 691 | M23: 591 | N23: 258.52 | O23: =F23*J23 -> 1663.2563 | P23: =O23*90%-N23-D23*(J23-100) -> 1135.5871 | Q23: =10%*O23 -> 166.32563 | S23: =P23/J23 -> 0.8695154
A24: 45597 | B24: 0.4033 | C24: 0.85251 | D24: =0.01203+0.05774 -> 0.06977 | E24: Vermelha | F24: =SUM(B24:C24) -> 1.25581 | G24: 0.24 | H24: 0.0358 | I24: 0.0078 | J24: =K24+L24 -> 2880 | K24: 698 | L24: 2182 | M24: 598 | N24: 254.88 | O24: =(F24+D24)*J24 -> 3817.6704 | P24: =O24-N24-Q24-R24 -> 2987.0628 | Q24: =10%*O24 -> 381.76704 | R24: =(M24+L24)*D24 -> 193.9606 | S24: =P24/J24 -> 1.0371746
A25: 45627 | B25: 0.4023 | C25: 0.85038 | D25: 0.0142 | E25: Amarela | F25: =SUM(B25:C25) -> 1.25268 | G25: 0.24 | H25: 0.0338 | I25: 0.0074 | J25: =K25+L25 -> 1563 | K25: 548 | L25: =((Registro_inversores!C6-Registro_inversores!C5)+(Registro_inversores!D6-Registro_inversores!D5)-'Créditos CP'!C26) -> 1015 | M25: 448 | N25: 218.15 | O25: =(F25+D25)*J25 -> 1980.1334 | P25: =O25-N25-Q25-R25 -> 1543.1955 | Q25: =10%*O25 -> 198.01334 | R25: =(M25+L25)*D25 -> 20.7746 | S25: =P25/J25 -> 0.98732917
A26: 45658 | B26: 0.3823 | C26: 0.8081 | D26: 0 | E26: Verde | F26: =SUM(B26:C26) -> 1.1904 | G26: 0.18 | H26: 0.0523 | I26: 0.0112 | J26: =K26+L26 -> -361 | K26: 100 | L26: =((Registro_inversores!C7-Registro_inversores!C6)+(Registro_inversores!D7-Registro_inversores!D6)-'Créditos CP'!C27) -> -461 | M26: 0 | N26: 119.04 | O26: =MAX((F26+D26)*J26,0) -> 0 | P26: =MAX(O26-N26-Q26-R26,0) -> 0 | Q26: =10%*O26 -> 0 | R26: =(M26+L26)*D26 -> 0 | S26: =P26/J26 -> 0
A27: 45689 | B27: 0.38431 | C27: 0.81254 | D27: 0 | E27: Verde | F27: =SUM(B27:C27) -> 1.19685 | G27: 0.18 | H27: 0.0575 | I27: 0.0115 | J27: =K27+L27 -> 1866 | K27: 283 | L27: =Registro_inversores!AB9 -> 1583 | M27: 183 | N27: 166.63 | O27: =MAX((F27+D27)*J27,0) -> 2233.3221 | P27: =MAX(O27-N27-Q27-R27,0) -> 1843.3599 | Q27: =10%*O27 -> 223.33221 | R27: =(M27+L27)*D27 -> 0 | S27: =P27/J27 -> 0.98786704
A28: 45717 | B28: 0.38761 | C28: 0.82083 | D28: 0 | E28: Verde | F28: =SUM(B28:C28) -> 1.20844 | G28: 0.24 | H28: 0.004 | I28: 0.0008 | J28: =K28+L28 -> 2080.6429 | K28: 518 | L28: =Registro_inversores!AC9 -> 1562.6429 | M28: 418 | N28: 227.12 | O28: =MAX((F28+D28)*J28,0) -> 2514.3321 | P28: =MAX(O28-N28-Q28-R28,0) -> 2035.7788 | Q28: =10%*O28 -> 251.43321 | R28: =(M28+L28)*D28 -> 0 | S28: =P28/J28 -> 0.97843743
A29: 45748 | B29: 0.39467 | C29: 0.85016 | D29: 0 | E29: Verde | F29: =SUM(B29:C29) -> 1.24483 | G29: 0.24 | H29: 0.0181 | I29: 0.0038 | J29: =K29+L29 -> 738 | K29: 738 | L29: =Registro_inversores!AD9 -> 0 | M29: 618 | N29: 282.86 | O29: =MAX((F29+D29)*J29,0) -> 918.68454 | P29: =MAX(O29-N29-Q29-R29,0) -> 543.95609 | Q29: =10%*O29 -> 91.868454 | R29: =(M29+L29)*D29 -> 0 | S29: =P29/J29 -> 0.73706787
A30: 45778 | B30: 0.41703 | C30: 0.89834 | D30: 0.012242 | E30: Amarela | F30: =SUM(B30:C30) -> 1.31537 | G30: 0.24 | H30: 0.0616 | I30: 0.0135 | J30: =K30+L30 -> 2269.8824 | K30: 525 | L30: =Registro_inversores!AE9 -> 1744.8824 | M30: 425 | N30: 254.55 | O30: =MAX((F30+D30)*J30,0) -> 3013.5231 | P30: =MAX(O30-N30-Q30-R30,0) -> 2431.057 | Q30: =10%*O30 -> 301.35231 | R30: =(M30+L30)*D30 -> 26.5637 | S30: =P30/J30 -> 1.0710057
A31: 45809 | B31: 0.41423 | C31: 0.89217 | D31: =0.01452+0.0284 -> 0.04292 | E31: Vermelha | F31: =SUM(B31:D31) -> 1.34932 | G31: 0.24 | H31: 0.0572 | I31: 0.0126 | J31: =K31+L31 -> 1428.1373 | K31: 611 | L31: {=_xlfn.XLOOKUP(A31,Registro_inversores!H:H,Registro_inversores!T:T)} -> 817.13725 | M31: 511 | N31: 275.4 | O31: =MAX((F31+D31)*J31,0) -> 1988.3098 | P31: =MAX(O31-N31-Q31-R31,0) -> 1457.0752 | Q31: =10%*O31 -> 198.83098 | R31: =(M31+L31)*D31 -> 57.003651 | S31: =P31/J31 -> 1.0202627
A32: 45839 | B32: 0.40598 | C32: 0.87443 | D32: 0.06172 | E32: Vermelha | F32: =SUM(B32:D32) -> 1.34213 | G32: 0.24 | H32: 0.0403 | I32: 0.0088 | J32: =K32+L32 -> 1017.3333 | K32: 344 | L32: {=_xlfn.XLOOKUP(A32,Registro_inversores!H:H,Registro_inversores!T:T)} -> 673.33333 | M32: 264 | N32: 187.7 | O32: =MAX((F32+D32)*J32,0) -> 1428.1834 | P32: =MAX(O32-N32-Q32-R32,0) -> 1039.8128 | Q32: =10%*O32 -> 142.81834 | R32: =(M32+L32)*D32 -> 57.852213 | S32: =P32/J32 -> 1.0220965
A33: 45870 | B33: 0.36841 | C33: 0.79344 | D33: 0.07591 | E33: Vermelha | F33: =SUM(B33:D33) -> 1.23776 | G33: 0.18 | H33: 0.0235 | I33: 0.0052 | J33: =K33+L33 -> 656.42857 | K33: 257 | L33: {=_xlfn.XLOOKUP(A33,Registro_inversores!H:H,Registro_inversores!T:T)} -> 399.42857 | M33: 157 | N33: 159.87 | O33: =MAX((F33+D33)*J33,0) -> 862.33052 | P33: =MAX(O33-N33-Q33-R33,0) -> 573.98898 | Q33: =10%*O33 -> 86.233052 | R33: =(M33+L33)*D33 -> 42.238493 | S33: =P33/J33 -> 0.87441193
A34: 45901 | B34: 0.4113 | C34: 0.88619 | D34: 0.1104 | E34: Vermelha | F34: =SUM(B34:D34) -> 1.40789 | G34: 0.24 | H34: 0.0542 | I34: 0.0118 | J34: =K34+L34 -> 2213.2857 | K34: 573 | L34: {=_xlfn.XLOOKUP(A34,Registro_inversores!H:H,Registro_inversores!T:T)} -> 1640.2857 | M34: 473 | N34: 269.03 | O34: =MAX((F34+D34)*J34,0) -> 3360.4096 | P34: =MAX(O34-N34-Q34-R34,0) -> 2522.0319 | Q34: =10%*O34 -> 336.04096 | R34: =(M34+L34)*D34 -> 233.30674 | S34: =P34/J34 -> 1.1394967
A35: 45931 | B35: 0.41095 | C35: 0.88511 | D35: 0.08636 | E35: Vermelha | F35: =SUM(B35:D35) -> 1.38242 | G35: 0.24 | H35: 0.0498 | I35: 0.0108 | J35: =K35+L35 -> 1810.4107 | K35: 585 | L35: {=_xlfn.XLOOKUP(A35,Registro_inversores!H:H,Registro_inversores!T:T)} -> 1225.4107 | M35: 485 | N35: 272.11 | O35: =MAX((F35+D35)*J35,0) -> 2659.095 | P35: =MAX(O35-N35-Q35-R35,0) -> 1973.3645 | Q35: =10%*O35 -> 265.9095 | R35: =(M35+L35)*D35 -> 147.71107 | S35: =P35/J35 -> 1.0900093
A36: 45962 | B36: 0.4067 | C36: 0.8762 | D36: 0.06183 | E36: Vermelha | F36: =SUM(B36:D36) -> 1.34473 | G36: 0.24 | H36: 0.0428 | I36: 0.0094 | J36: =K36+L36 -> 2241.3365 | K36: 530 | L36: {=_xlfn.XLOOKUP(A36,Registro_inversores!H:H,Registro_inversores!T:T)} -> 1711.3365 | M36: 430 | N36: 258.34 | O36: =MAX((F36+D36)*J36,0) -> 3152.5743 | P36: =MAX(O36-N36-Q36-R36,0) -> 2446.5781 | Q36: =10%*O36 -> 315.25743 | R36: =(M36+L36)*D36 -> 132.39884 | S36: =P36/J36 -> 1.091571
A37: 45992 | B37: 0.41663 | C37: 0.89745 | D37: =0.03584+0.01157 -> 0.04741 | E37: Amarela | F37: =SUM(B37:D37) -> 1.36149 | G37: 0.24 | H37: 0.0624 | I37: 0.0136 | J37: =K37+L37 -> 2757.8488 | K37: 613 | L37: {=_xlfn.XLOOKUP(A37,Registro_inversores!H:H,Registro_inversores!T:T)} -> 2144.8488 | M37: 513 | N37: 276.12 | O37: =MAX((F37+D37)*J37,0) -> 3885.5332 | P37: =MAX(O37-N37-Q37-R37,0) -> 3094.8513 | Q37: =10%*O37 -> 388.55332 | R37: =(M37+L37)*D37 -> 126.00861 | S37: =P37/J37 -> 1.1221976
A38: 46023 | B38: 0.38528 | C38: 0.83 | D38: 0.01372 | E38: Amarela | F38: =SUM(B38:D38) -> 1.229 | G38: 0.18 | H38: 0.059 | I38: 0.0128 | J38: =K38+L38 -> 580.31466 | K38: 172 | L38: {=_xlfn.XLOOKUP(A38,Registro_inversores!H:H,Registro_inversores!T:T)} -> 408.31466 | M38: 72 | N38: 151.49 | O38: =MAX((F38+D38)*J38,0) -> 721.16863 | P38: =MAX(O38-N38-Q38-R38,0) -> 490.97185 | Q38: =10%*O38 -> 72.116863 | R38: =(M38+L38)*D38 -> 6.5899171 | S38: =P38/J38 -> 0.8460442
A39: 46054 | B39: 0.4114 | C39: 0.8867 | D39: 0 | E39: Verde | F39: =SUM(B39:D39) -> 1.2981 | G39: 0.24 | H39: 0.051 | I39: 0.011 | J39: =K39+L39 -> 1006.5 | K39: 315 | L39: {=_xlfn.XLOOKUP(A39,Registro_inversores!H:H,Registro_inversores!T:T)} -> 691.5 | M39: 215 | N39: 198.48 | O39: =MAX((F39+D39)*J39,0) -> 1306.5376 | P39: =MAX(O39-N39-Q39-R39,0) -> 977.40388 | Q39: =10%*O39 -> 130.65376 | R39: =(M39+L39)*D39 -> 0 | S39: =P39/J39 -> 0.97109179
A40: 46082 | B40: 0.40079 | C40: 0.86524 | D40: 0 | E40: Verde | F40: =SUM(B40:D40) -> 1.26603 | G40: 0.24 | H40: 0.0233 | I40: 0.0051 | J40: =K40+L40 -> 2178.2179 | K40: 667 | L40: {=_xlfn.XLOOKUP(A40,Registro_inversores!H:H,Registro_inversores!T:T)} -> 1511.2179 | M40: 567 | N40: 271.76 | O40: =MAX((F40+D40)*J40,0) -> 2757.6892 | P40: =MAX(O40-N40-Q40-R40,0) -> 2210.1602 | Q40: =10%*O40 -> 275.76892 | R40: =(M40+L40)*D40 -> 0 | S40: =P40/J40 -> 1.0146645
A41: 46113 | B41: 0.4653 | C41: 1.03423 | D41: 0 | E41: Verde | F41: =SUM(B41:D41) -> 1.49953 | G41: 0.24 | H41: 0.0568 | I41: 0.0123 | J41: =K41+L41 -> 3057.4429 | K41: 720 | L41: {=_xlfn.XLOOKUP(A41,Registro_inversores!H:H,Registro_inversores!T:T)} -> 2337.4429 | M41: 620 | N41: 331.31 | O41: =MAX((F41+D41)*J41,0) -> 4584.7273 | P41: =MAX(O41-N41-Q41-R41,0) -> 3794.9446 | Q41: =10%*O41 -> 458.47273 | R41: =(M41+L41)*D41 -> 0 | S41: =P41/J41 -> 1.2412152
A42: 46143 | B42: 0.46695 | C42: 1.03743 | D42: 0 | E42: Verde | F42: =SUM(B42:D42) -> 1.50438 | G42: 0.24 | H42: 0.0595 | I42: 0.0125 | J42: =K42+L42 -> 2271.7143 | K42: 668 | L42: {=_xlfn.XLOOKUP(A42,Registro_inversores!H:H,Registro_inversores!T:T)} -> 1603.7143 | M42: 568 | N42: 321.44 | O42: =MAX((F42+D42)*J42,0) -> 3417.5215 | P42: =MAX(O42-N42-Q42-R42,0) -> 2754.3294 | Q42: =10%*O42 -> 341.75215 | R42: =(M42+L42)*D42 -> 0 | S42: =P42/J42 -> 1.2124453
A43: 46174 | B43: 0.46333 | C43: 1.02935 | D43: 0.02648 | E43: Amarela | F43: =SUM(B43:D43) -> 1.51916 | G43: 0.24 | H43: 0.0533 | I43: 0.0131 | J43: =K43+L43 -> 1164.2551 | K43: 650 | L43: {=_xlfn.XLOOKUP(A43,Registro_inversores!H:H,Registro_inversores!T:T)} -> 514.2551 | M43: 550 | N43: 316.1 | O43: =MAX((F43+D43)*J43,0) -> 1799.5193 | P43: =MAX(O43-N43-Q43-R43,0) -> 1275.2859 | Q43: =10%*O43 -> 179.95193 | R43: =(M43+L43)*D43 -> 28.181475 | S43: =P43/J43 -> 1.0953663
A44: 46204 | B44: 0.47256 | C44: 1.04978 | D44: 0.027 | E44: Amarela | F44: =SUM(B44:D44) -> 1.54934 | G44: 0.24 | H44: 0.0681 | I44: 0.0148 | J44: =K44+L44 -> 1513.2449 | K44: 467 | L44: {=_xlfn.XLOOKUP(A44,Registro_inversores!H:H,Registro_inversores!T:T)} -> 1046.2449 | M44: 367 | N44: 274.52 | O44: =MAX((F44+D44)*J44,0) -> 2385.3885 | P44: =MAX(O44-N44-Q44-R44,0) -> 1834.172 | Q44: =10%*O44 -> 238.53885 | R44: =(M44+L44)*D44 -> 38.157612 | S44: =P44/J44 -> 1.2120788
A45: 46235 | B45: 0.44807 | C45: 0.99526 | D45: 0.02556 | E45: Amarela | F45: =SUM(B45:D45) -> 1.46889 | G45: 0.24 | H45: 0.0267 | I45: 0.6 | J45: =K45+L45 -> 905.875 | K45: 385 | L45: {=_xlfn.XLOOKUP(A45,Registro_inversores!H:H,Registro_inversores!T:T)} -> 520.875 | M45: 285 | N45: 233.25 | O45: =MAX((F45+D45)*J45,0) -> 1353.7849 | P45: =MAX(O45-N45-Q45-R45,0) -> 964.55824 | Q45: =10%*O45 -> 135.37849 | R45: =(M45+L45)*D45 -> 20.598165 | S45: =P45/J45 -> 1.0647807

Sheet Faturamento 281
A1: Mês de referência | B1: Consumo (kWh) | C1: TE | D1: TUSD | E1: Bandeira | F1: Tarifa (R$/kWh) | G1: Eletricidade Enel (kWh) | H1: Eletricidade painel (kWh) | I1: Crédito utilizados (kWh) | J1: Fatura enel (R$) | K1: Total (R$) | L1: Desconto 10% | M1: Desconto bandeira | N1: Fatura Zeta (R$) | O1: Valor eletricidade (R$/kWh)
A2: 44927 | G2: 67 | I2: 67
A3: 44958 | G3: 62 | I3: 62
A4: 44986 | G4: 78 | I4: 78
A5: 45017 | B5: =G5+H5 -> 386 | F5: 1.13607 | G5: 122 | H5: 264 | I5: 22 | K5: =B5*F5 -> 438.52302 | N5: =90%*K5 -> 394.67072 | O5: =N5/H5 -> 1.4949648
A6: 45047 | B6: =G6+H6 -> 328.12 | F6: 1.13607 | G6: 108 | H6: 220.12 | I6: 8 | K6: =B6*F6 -> 372.76729 | N6: =90%*K6 -> 335.49056 | O6: =N6/H6 -> 1.5241257
A7: 45078 | B7: =G7+H7 -> 100 | F7: 1.1537 | G7: 100 | H7: 0 | I7: 0 | K7: =B7*F7 -> 115.37 | N7: =90%*K7 -> 103.833 | O7: =N7/H7 -> #DIV/0!
A8: 45108 | B8: =G8+H8 -> 100 | F8: 1.144 | G8: 100 | H8: 0 | I8: 0 | K8: =B8*F8 -> 114.4 | N8: =90%*K8 -> 102.96 | O8: =N8/H8 -> #DIV/0!
A9: 45139 | B9: =G9+H9 -> 100 | F9: 1.18263 | G9: 100 | H9: 0 | I9: 0 | K9: =B9*F9 -> 118.263 | N9: =90%*K9 -> 106.4367 | O9: =N9/H9 -> #DIV/0!
A10: 45170 | B10: =G10+H10 -> 100 | F10: 1.161 | G10: 100 | I10: 0 | K10: =B10*F10 -> 116.1 | N10: =90%*K10 -> 104.49 | O10: =N10/H10 -> #DIV/0!
A11: 45200 | B11: =G11+H11 -> 213 | F11: 1.12911 | G11: 123 | H11: 90 | I11: 23 | J11: 136.57 | K11: =B11*F11 -> 240.50043 | N11: =90%*K11-J11 -> 79.880387 | O11: =N11/H11 -> 0.88755986
A12: 45231 | N12: 0
A13: 45261 | B13: =G13+H13 -> 141 | F13: 1.16929 | G13: 141 | I13: 41 | J13: 142.48 | K13: =B13*F13 -> 164.86989 | N13: =90%*K13-J13 -> 5.902901 | O13: =N13/H13 -> #DIV/0!
A14: 45292
A15: 45323
A16: 45352
A17: 45383
A18: 45413
A19: 45444
A20: 45474
A21: 45505
A22: 45536
A23: 45566 | B23: 146 | C23: 0.37884 | D23: 0.80103 | F23: =D23+C23 -> 1.17987 | G23: 146 | I23: 46 | J23: 146.28 | K23: =B23*F23 -> 172.26102 | N23: =90%*K23-J23 -> 8.754918 | O23: =N23/G23 -> 0.059965192
A24: 45597 | B24: =G24+H24 -> 1287 | C24: 0.37362 | D24: 0.79 | E24: =0.01108+0.0534 -> 0.06448 | F24: =D24+C24+E24 -> 1.2281 | G24: 194 | H24: 1093 | I24: 94 | J24: 158.89 | K24: =F24*B24 -> 1580.5647 | L24: =10%*K24 -> 158.05647 | M24: =E24*(H24+I24) -> 76.53776 | N24: =K24-J24-L24-M24 -> 1187.0805 | O24: =N24/(SUM(H24:I24)) -> 1.0000678
A25: 45627 | B25: =G25+H25 -> 532 | C25: 0.37262 | D25: 0.78794 | E25: 0.01268 | F25: =D25+C25+E25 -> 1.17324 | G25: 141 | H25: =Registro_inversores!E6-Registro_inversores!E5-'Créditos CP'!D26 -> 391 | I25: 41 | J25: 141.94 | K25: =F25*B25 -> 624.16368 | L25: =10%*K25 -> 62.416368 | M25: =E25*(H25+I25) -> 5.47776 | N25: =K25-J25-L25-M25 -> 414.32955 | O25: =N25/(SUM(H25:I25)) -> 0.95909619
A26: 45658 | B26: =G26+H26 -> -321 | C26: 0.3823 | D26: 0.8081 | E26: 0 | F26: =D26+C26+E26 -> 1.1904 | G26: 100 | H26: =Registro_inversores!E7-Registro_inversores!E6-'Créditos CP'!D27 -> -421 | I26: 0 | J26: 119.04 | K26: =MAX(F26*B26,0) -> 0 | L26: =10%*K26 -> 0 | M26: =E26*(H26+I26) -> 0 | N26: =MAX(K26-J26-L26-M26,0) -> 0 | O26: =N26/(SUM(H26:I26)) -> 0
A27: 45689 | B27: =G27+H27 -> 482.47368 | C27: 0.3842 | D27: 0.8124 | E27: 0 | F27: =D27+C27+E27 -> 1.1966 | G27: 100 | H27: =Registro_inversores!AB14 -> 382.47368 | I27: 0 | J27: 132.01 | K27: =F27*B27 -> 577.32801 | L27: =10%*K27 -> 57.732801 | M27: =E27*(H27+I27) -> 0 | N27: =MAX(K27-J27-L27-M27,0) -> 387.58521 | O27: =N27/(SUM(H27:I27)) -> 1.0133644
A28: 45717 | B28: =G28+H28 -> 364.81203 | C28: 0.359 | D28: 0.7605 | E28: 0 | F28: =D28+C28+E28 -> 1.1195 | G28: 120 | H28: =Registro_inversores!AC14 -> 244.81203 | I28: 20 | J28: 132.53 | K28: =F28*B28 -> 408.40707 | L28: =10%*K28 -> 40.840707 | M28: =E28*(H28+I28) -> 0 | N28: =MAX(K28-J28-L28-M28,0) -> 235.03636 | O28: =N28/(SUM(H28:I28)) -> 0.88755923
A29: 45748 | B29: =G29+H29 -> 306 | C29: 0.39464 | D29: 0.8501 | E29: 0 | F29: =D29+C29+E29 -> 1.24474 | G29: 306 | H29: =Registro_inversores!AD14 -> 0 | I29: 206 | J29: 191.85 | K29: =F29*B29 -> 380.89044 | L29: =10%*K29 -> 38.089044 | M29: =E29*(H29+I29) -> 0 | N29: =MAX(K29-J29-L29-M29,0) -> 150.9514 | O29: =N29/(SUM(H29:I29)) -> 0.73277377
A30: 45778 | B30: =G30+H30 -> 188.53571 | C30: 0.38642 | D30: 0.83254 | E30: 0.01139 | F30: =D30+C30+E30 -> 1.23035 | G30: 173 | H30: =Registro_inversores!AE14 -> 15.535714 | I30: 73 | J30: 155.96 | K30: =F30*B30 -> 231.96492 | L30: =10%*K30 -> 23.196492 | M30: =E30*(H30+I30) -> 1.0084218 | N30: =MAX(K30-J30-L30-M30,0) -> 51.800003 | O30: =N30/(SUM(H30:I30)) -> 0.58507466
A31: 45809 | B31: =G31+H31 -> 353.31373 | C31: 0.384 | D31: 0.8268 | E31: =0.01339+0.02617 -> 0.03956 | F31: =D31+C31+E31 -> 1.25036 | G31: 180 | H31: {=_xlfn.XLOOKUP(A31,Registro_inversores!H:H,Registro_inversores!U:U)} -> 173.31373 | I31: 80 | J31: 159.29 | K31: =F31*B31 -> 441.76935 | L31: =10%*K31 -> 44.176935 | M31: =E31*(H31+I31) -> 10.021091 | N31: =MAX(K31-J31-L31-M31,0) -> 228.28132 | O31: =N31/(SUM(H31:I31)) -> 0.90118024
A32: 45839 | B32: =G32+H32 -> 310.33333 | C32: 0.37727 | D32: 0.80909 | E32: 0.05703 | F32: =D32+C32+E32 -> 1.24339 | G32: 91 | H32: {=_xlfn.XLOOKUP(A32,Registro_inversores!H:H,Registro_inversores!U:U)} -> 219.33333 | I32: 11 | J32: 112.77 | K32: =F32*B32 -> 385.86536 | L32: =10%*K32 -> 38.586536 | M32: =E32*(H32+I32) -> 13.13591 | N32: =MAX(K32-J32-L32-M32,0) -> 221.37292 | O32: =N32/(SUM(H32:I32)) -> 0.96109805
A33: 45870 | B33: =G33+H33 -> 156.05714 | C33: 0.368 | D33: 0.7931 | E33: 0.0757 | F33: =D33+C33+E33 -> 1.2368 | G33: 100 | H33: {=_xlfn.XLOOKUP(A33,Registro_inversores!H:H,Registro_inversores!U:U)} -> 56.057143 | I33: 0 | J33: 126.21 | K33: =F33*B33 -> 193.01147 | L33: =10%*K33 -> 19.301147 | M33: =E33*(H33+I33) -> 4.2435257 | N33: =MAX(K33-J33-L33-M33,0) -> 43.256801 | O33: =N33/(SUM(H33:I33)) -> 0.77165547
A34: 45901 | B34: =G34+H34 -> 403.22857 | C34: 0.38111 | D34: 0.82 | E34: 0.1022 | F34: =D34+C34+E34 -> 1.30331 | G34: 118 | H34: {=_xlfn.XLOOKUP(A34,Registro_inversores!H:H,Registro_inversores!U:U)} -> 285.22857 | I34: 18 | J34: 153.74 | K34: =F34*B34 -> 525.53183 | L34: =10%*K34 -> 52.553183 | M34: =E34*(H34+I34) -> 30.98996 | N34: =MAX(K34-J34-L34-M34,0) -> 288.24869 | O34: =N34/(SUM(H34:I34)) -> 0.9505987
A35: 45931 | B35: =G35+H35 -> 246.33929 | C35: 0.38095 | D35: 0.8203 | E35: 0.07992 | F35: =D35+C35+E35 -> 1.28117 | G35: 121 | H35: {=_xlfn.XLOOKUP(A35,Registro_inversores!H:H,Registro_inversores!U:U)} -> 125.33929 | I35: 21 | J35: 153.27 | K35: =F35*B35 -> 315.6025 | L35: =10%*K35 -> 31.56025 | M35: =E35*(H35+I35) -> 11.695436 | N35: =MAX(K35-J35-L35-M35,0) -> 119.07682 | O35: =N35/(SUM(H35:I35)) -> 0.81370369
A36: 45962 | B36: =G36+H36 -> 645.29808 | C36: 0.3769 | D36: 0.8118 | E36: 0.0571 | F36: =D36+C36+E36 -> 1.2458 | G36: 100 | H36: {=_xlfn.XLOOKUP(A36,Registro_inversores!H:H,Registro_inversores!U:U)} -> 545.29808 | I36: 0 | J36: 141.94 | K36: =F36*B36 -> 803.91234 | L36: =10%*K36 -> 80.391234 | M36: =E36*(H36+I36) -> 31.13652 | N36: =MAX(K36-J36-L36-M36,0) -> 550.44459 | O36: =N36/(SUM(H36:I36)) -> 1.009438
A37: 45992 | B37: =G37+H37 -> 510.38727 | C37: 0.385 | D37: 0.83042 | E37: =0.03306+0.01056 -> 0.04362 | F37: =D37+C37+E37 -> 1.25904 | G37: 124 | H37: {=_xlfn.XLOOKUP(A37,Registro_inversores!H:H,Registro_inversores!U:U)} -> 386.38727 | I37: 24 | J37: 150.78 | K37: =F37*B37 -> 642.59799 | L37: =10%*K37 -> 64.259799 | M37: =E37*(H37+I37) -> 17.901093 | N37: =MAX(K37-J37-L37-M37,0) -> 409.65709 | O37: =N37/(SUM(H37:I37)) -> 0.99822077
A38: 46023 | B38: =G38+H38 -> 143.56466 | C38: 0.3852 | D38: 0.8301 | E38: 0.0136 | F38: =D38+C38+E38 -> 1.2289 | G38: 100 | H38: {=_xlfn.XLOOKUP(A38,Registro_inversores!H:H,Registro_inversores!U:U)} -> 43.564655 | I38: 0 | J38: 133.58 | K38: =F38*B38 -> 176.4266 | L38: =10%*K38 -> 17.64266 | M38: =E38*(H38+I38) -> 0.59247931 | N38: =MAX(K38-J38-L38-M38,0) -> 24.611465 | O38: =N38/(SUM(H38:I38)) -> 0.56494112
A39: 46054 | B39: =G39+H39 -> 612.375 | C39: 0.3813 | D39: 0.82122 | E39: 0 | F39: =D39+C39+E39 -> 1.20252 | G39: 149 | H39: {=_xlfn.XLOOKUP(A39,Registro_inversores!H:H,Registro_inversores!U:U)} -> 463.375 | I39: 49 | J39: 145.35 | K39: =F39*B39 -> 736.39318 | L39: =10%*K39 -> 73.639318 | M39: =E39*(H39+I39) -> 0 | N39: =MAX(K39-J39-L39-M39,0) -> 517.40387 | O39: =N39/(SUM(H39:I39)) -> 1.0098148
A40: 46082 | B40: =G40+H40 -> 38.692857 | C40: 0.3711 | D40: 0.80152 | E40: 0 | F40: =D40+C40+E40 -> 1.17262 | G40: 146 | H40: {=_xlfn.XLOOKUP(A40,Registro_inversores!H:H,Registro_inversores!U:U)} -> -107.30714 | I40: 46 | J40: 145.35 | K40: =F40*B40 -> 45.372018 | L40: =10%*K40 -> 4.5372018 | M40: =E40*(H40+I40) -> 0 | N40: =MAX(K40-J40-L40-M40,0) -> 0 | O40: =N40/(SUM(H40:I40)) -> 0
A41: 46113 | B41: =G41+H41 -> 664.57143 | C41: 0.43133 | D41: 0.9584 | E41: 0 | F41: =D41+C41+E41 -> 1.38973 | G41: 213 | H41: {=_xlfn.XLOOKUP(A41,Registro_inversores!H:H,Registro_inversores!U:U)+H40} -> 451.57143 | I41: 113 | J41: 181.8 | K41: =F41*B41 -> 923.57485 | L41: =10%*K41 -> 92.357485 | M41: =E41*(H41+I41) -> 0 | N41: =MAX(K41-J41-L41-M41,0) -> 649.41737 | O41: =N41/(SUM(H41:I41)) -> 1.1502838
A42: 46143 | B42: =G42+H42 -> 505.98626 | C42: 0.43242 | D42: 0.96113 | E42: 0 | F42: =D42+C42+E42 -> 1.39355 | G42: 162 | H42: {=_xlfn.XLOOKUP(A42,Registro_inversores!H:H,Registro_inversores!U:U)} -> 343.98626 | I42: 62 | J42: 172.37 | K42: =F42*B42 -> 705.11716 | L42: =10%*K42 -> 70.511716 | M42: =E42*(H42+I42) -> 0 | N42: =MAX(K42-J42-L42-M42,0) -> 462.23544 | O42: =N42/(SUM(H42:I42)) -> 1.1385495
A43: 46174 | B43: =G43+H43 -> 33.784144 | C43: 0.4293 | D43: 0.954 | E43: 0.02434 | F43: =D43+C43+E43 -> 1.40764 | G43: 122 | H43: {=_xlfn.XLOOKUP(A43,Registro_inversores!H:H,Registro_inversores!U:U)} -> -88.215856 | I43: 22 | J43: 165.65 | K43: =F43*B43 -> 47.555913 | L43: =10%*K43 -> 4.7555913 | M43: =E43*(H43+I43) -> -1.6116939 | N43: =MAX(K43-J43-L43-M43,0) -> 0 | O43: =N43/(SUM(H43:I43)) -> 0
A44: 46204 | B44: =G44+H44 -> 359.19231 | C44: 0.43769 | D44: 0.9729 | E44: 0.02487 | F44: =D44+C44+E44 -> 1.43546 | G44: 113 | H44: {=_xlfn.XLOOKUP(A44,Registro_inversores!H:H,Registro_inversores!U:U)+H43} -> 246.19231 | I44: 13 | J44: 166.96 | K44: =F44*B44 -> 515.60619 | L44: =10%*K44 -> 51.560619 | M44: =E44*(H44+I44) -> 6.4461127 | N44: =MAX(K44-J44-L44-M44,0) -> 290.63946 | O44: =N44/(SUM(H44:I44)) -> 1.1213275
A45: 46235 | B45: =G45+H45 -> 30 | C45: 0.415 | D45: 0.9223 | E45: 0.0236 | F45: =D45+C45+E45 -> 1.3609 | G45: 100 | H45: {=_xlfn.XLOOKUP(A45,Registro_inversores!H:H,Registro_inversores!U:U)} -> -70 | I45: 0 | J45: 139.92 | K45: =F45*B45 -> 40.827 | L45: =10%*K45 -> 4.0827 | M45: =E45*(H45+I45) -> -1.652 | N45: =MAX(K45-J45-L45-M45,0) -> 0 | O45: =N45/(SUM(H45:I45)) -> 0

Sheet Faturamento Itaipu
A1: Mês de referência | B1: Consumo (kWh) | C1: TE | D1: TUSD | E1: Bandeira | F1: Tarifa (R$/kWh) | G1: Créditos utilizados (kWh) | H1: Créditos saldo (kWh) | I1: Créditos mês corrente (kWh) | J1: Fatura Enel (R$) | K1: Total (R$) | L1: Fatura Zeta (R$) | M1: Desconto total (R$) | N1: Desconto 10% (R$) | O1: Desconto bandeira (R$) | P1: Valor eletricidade (R$/kWh)
A2: 44986 | B2: 3231 | F2: 1.10433 | G2: =H2+I2 -> 3131 | H2: 0 | I2: 3131 | J2: 557.47 | K2: =B2*F2 -> 3568.0902 | L2: =90%*K2-J2 -> 2653.8112 | M2: =SUM(N2:O2) -> 356.80902 | N2: =K2*0.1 -> 356.80902 | P2: =L2/G2 -> 0.84759221 | Q2: =P2/F2 -> 0.76751715
A3: 45017 | B3: 2601 | F3: 1.19467 | G3: =H3+I3 -> 2470 | H3: 1266 | I3: 1204 | J3: 612.19 | K3: =B3*F3 -> 3107.3367 | L3: =90%*K3-J3 -> 2184.413 | M3: =SUM(N3:O3) -> 310.73367 | N3: =K3*0.1 -> 310.73367 | P3: =L3/G3 -> 0.88437773 | Q3: =P3/F3 -> 0.74026948
A4: 45047 | B4: 2742 | F4: 1.16343 | G4: =H4+I4 -> 2642 | H4: 1607 | I4: 1035 | J4: 621.26 | K4: =B4*F4 -> 3190.1251 | L4: =90%*K4-J4 -> 2249.8526 | M4: =SUM(N4:O4) -> 319.01251 | N4: =K4*0.1 -> 319.01251 | P4: =L4/G4 -> 0.85157175 | Q4: =P4/F4 -> 0.73194928
A5: 45078 | B5: 2435 | F5: 1.21338 | G5: =H5+I5 -> 2335 | H5: 1321 | I5: 1014 | J5: 534.61 | K5: =B5*F5 -> 2954.5803 | L5: =90%*K5-J5 -> 2124.5123 | M5: =SUM(N5:O5) -> 295.45803 | N5: =K5*0.1 -> 295.45803 | P5: =L5/G5 -> 0.90985536 | Q5: =P5/F5 -> 0.74985195
A6: 45108 | B6: 2198 | F6: 1.2028 | G6: =H6+I6 -> 1781 | H6: 534 | I6: 1247 | J6: 868.7 | K6: =B6*F6 -> 2643.7544 | L6: =90%*K6-J6 -> 1510.679 | M6: =SUM(N6:O6) -> 264.37544 | N6: =K6*0.1 -> 264.37544 | P6: =L6/G6 -> 0.84821952 | Q6: =P6/F6 -> 0.70520412
A7: 45139 | B7: 2601 | F7: 1.18275 | G7: =H7+I7 -> 2501 | H7: 0 | I7: 2501 | J7: 632.26 | K7: =B7*F7 -> 3076.3328 | L7: =90%*K7-J7 -> 2136.4395 | M7: =SUM(N7:O7) -> 307.63328 | N7: =K7*0.1 -> 307.63328 | P7: =L7/G7 -> 0.8542341 | Q7: =P7/F7 -> 0.722244
A8: 45170 | B8: 2888 | F8: 1.22094 | G8: =H8+I8 -> 2787 | H8: 1913 | I8: 874 | J8: 678.12 | K8: =B8*F8 -> 3526.0747 | L8: =90%*K8-J8 -> 2495.3472 | M8: =SUM(N8:O8) -> 352.60747 | N8: =K8*0.1 -> 352.60747 | P8: =L8/G8 -> 0.89535244 | Q8: =P8/F8 -> 0.73333042
A9: 45200 | B9: 2967 | F9: 1.18716 | G9: =H9+I9 -> 2867 | H9: 2867 | I9: 0 | J9: 672.09 | K9: =B9*F9 -> 3522.3037 | L9: =90%*K9-J9 -> 2497.9833 | M9: =SUM(N9:O9) -> 352.23037 | N9: =K9*0.1 -> 352.23037 | P9: =L9/G9 -> 0.87128823 | Q9: =P9/F9 -> 0.73392654
A10: 45231 | B10: 2711 | F10: 1.18485 | G10: =H10+I10 -> 2611 | H10: 2611 | I10: 0 | J10: 635.31 | K10: =B10*F10 -> 3212.1283 | L10: =90%*K10-J10 -> 2255.6055 | M10: =SUM(N10:O10) -> 321.21284 | N10: =K10*0.1 -> 321.21284 | P10: =L10/G10 -> 0.86388568 | Q10: =P10/F10 -> 0.72910975
A11: 45261 | B11: 2575 | F11: 1.22969 | G11: =H11+I11 -> 2475 | H11: 2475 | I11: 0 | J11: 566.72 | K11: =B11*F11 -> 3166.4517 | L11: =90%*K11-J11 -> 2283.0866 | M11: =SUM(N11:O11) -> 316.64517 | N11: =K11*0.1 -> 316.64517 | P11: =L11/G11 -> 0.92245922 | Q11: =P11/F11 -> 0.75015591
A12: 45292 | B12: 3038 | F12: 1.22 | G12: 2938 | J12: 703.09 | K12: =B12*F12 -> 3706.36 | L12: =90%*K12-J12 -> 2632.634 | M12: =SUM(N12:O12) -> 370.636 | N12: =K12*0.1 -> 370.636 | P12: =L12/G12 -> 0.89606331 | Q12: =P12/F12 -> 0.73447812
A13: 45323 | B13: 2815 | F13: 1.217 | G13: 2715 | J13: 673.64 | K13: =B13*F13 -> 3425.855 | L13: =90%*K13-J13 -> 2409.6295 | M13: =SUM(N13:O13) -> 342.5855 | N13: =K13*0.1 -> 342.5855 | P13: =L13/G13 -> 0.88752468 | Q13: =P13/F13 -> 0.72927254
A14: 45352 | B14: 2975 | F14: 1.1903 | G14: =H14+I14 -> 2875 | H14: 2875 | I14: 0 | J14: 697.63 | K14: =B14*F14 -> 3541.1425 | L14: =90%*K14-J14 -> 2489.3983 | M14: =SUM(N14:O14) -> 354.11425 | N14: =K14*0.1 -> 354.11425 | P14: =L14/G14 -> 0.86587765 | Q14: =P14/F14 -> 0.72744489
A15: 45383 | B15: 2631 | F15: 1.25118 | G15: =H15+I15 -> 2531 | H15: 2531 | I15: 0 | J15: 698.11 | K15: =B15*F15 -> 3291.8546 | L15: =90%*K15-J15 -> 2264.5591 | M15: =SUM(N15:O15) -> 329.18546 | N15: =K15*0.1 -> 329.18546 | P15: =L15/G15 -> 0.89472901 | Q15: =P15/F15 -> 0.71510815
A16: 45413 | B16: 2568 | F16: 1.23503 | G16: =H16+I16 -> 2468 | H16: 2468 | I16: 0 | J16: 697.11 | K16: =B16*F16 -> 3171.557 | L16: =90%*K16-J16 -> 2157.2913 | M16: =SUM(N16:O16) -> 317.1557 | N16: =K16*0.1 -> 317.1557 | P16: =L16/G16 -> 0.87410508 | Q16: =P16/F16 -> 0.7077602
A17: 45444 | B17: 2396 | F17: 1.275 | G17: 2296 | J17: 677.3 | K17: =B17*F17 -> 3054.9 | L17: =90%*K17-J17 -> 2072.11 | M17: =SUM(N17:O17) -> 305.49 | N17: =K17*0.1 -> 305.49 | P17: =L17/G17 -> 0.90248693 | Q17: =P17/F17 -> 0.70783289
A18: 45474 | B18: 2092 | C18: 0.40549 | D18: 0.8571 | E18: 0.01649 | F18: =C18+D18 -> 1.26259 | G18: =H18+I18 -> 1991 | H18: 1768 | I18: 223 | J18: 612.18 | K18: =B18*F18 -> 2641.3383 | L18: =90%*K18-J18-O18 -> 1730.5274 | M18: =SUM(N18:O18) -> 298.63091 | N18: =K18*0.1 -> 264.13383 | O18: =B18*E18 -> 34.49708 | P18: =L18/G18 -> 0.86917497 | Q18: =P18/F18 -> 0.68840635
A19: 45505 | B19: 2125 | C19: 0.40062 | D19: 0.84679 | E19: 0.00965 | F19: =C19+D19+E19 -> 1.25706 | G19: =H19+I19 -> 2025 | H19: =416+1233+2 -> 1651 | I19: 374 | J19: 608 | K19: =B19*F19 -> 2671.2525 | L19: =90%*K19-J19-O19 -> 1776.586 | M19: =SUM(N19:O19) -> 286.6665 | N19: =K19*0.1 -> 267.12525 | O19: =G19*E19 -> 19.54125 | P19: =L19/G19 -> 0.87732642 | Q19: =P19/F19 -> 0.69791929
A20: 45536 | B20: 2603 | C20: 0.40803 | D20: 0.86246 | E20: 0.03933 | F20: =C20+D20+E20 -> 1.30982 | G20: =H20+I20 -> 2501 | H20: =829+1190 -> 2019 | I20: 482 | J20: 719.2 | K20: =B20*F20 -> 3409.4615 | L20: =90%*K20-J20-O20 -> 2250.951 | M20: =SUM(N20:O20) -> 439.31048 | N20: =K20*0.1 -> 340.94615 | O20: =G20*E20 -> 98.36433 | P20: =L20/G20 -> 0.90002039 | Q20: =P20/F20 -> 0.68713288
A21: 45566 | B21: 2813 | C21: 0.40903 | D21: 0.86456 | E21: 0.09351 | F21: =C21+D21+E21 -> 1.3671 | G21: =H21+I21 -> 2712 | H21: 2293 | I21: 419 | J21: 772 | K21: =B21*F21 -> 3845.6523 | L21: =90%*K21-J21-O21 -> 2435.488 | M21: =SUM(N21:O21) -> 638.16435 | N21: =K21*0.1 -> 384.56523 | O21: =G21*E21 -> 253.59912 | P21: =L21/G21 -> 0.89804128 | Q21: =P21/F21 -> 0.65689509
A22: 45597 | B22: 2786 | C22: 0.40334 | D22: 0.85254 | E22: =0.03494+0.01756 -> 0.0525 | F22: =C22+D22+E22 -> 1.30838 | G22: =H22+I22 -> 2685 | H22: =803+1460 -> 2263 | I22: 422 | J22: 753.63 | K22: =B22*F22 -> 3645.1467 | L22: =90%*K22-J22-O22 -> 2386.0395 | M22: =SUM(N22:O22) -> 505.47717 | N22: =K22*0.1 -> 364.51467 | O22: =G22*E22 -> 140.9625 | P22: =L22/G22 -> 0.88865531 | Q22: =P22/F22 -> 0.67920276
A23: 45627 | B23: 2874 | C23: 0.40233 | D23: 0.85041 | E23: 0.00861 | F23: =C23+D23+E23 -> 1.26135 | G23: =H23+I23 -> 2772 | H23: =794+1507 -> 2301 | I23: 471 | J23: 751.3 | K23: =B23*F23 -> 3625.1199 | L23: =90%*K23-J23-O23 -> 2487.441 | M23: =SUM(N23:O23) -> 386.37891 | N23: =K23*0.1 -> 362.51199 | O23: =G23*E23 -> 23.86692 | P23: =L23/G23 -> 0.89734523 | Q23: =P23/F23 -> 0.71141653
A24: 45658 | B24: 3293 | C24: 0.41266 | D24: 0.87224 | E24: 0 | F24: =C24+D24+E24 -> 1.2849 | G24: =H24+I24 -> 3193 | H24: 2596.5 | I24: 596.5 | J24: 859.31 | K24: =B24*F24 -> 4231.1757 | L24: =90%*K24-J24-O24 -> 2948.7481 | M24: =SUM(N24:O24) -> 423.11757 | N24: =K24*0.1 -> 423.11757 | O24: =G24*E24 -> 0 | P24: =L24/G24 -> 0.92350396 | Q24: =P24/F24 -> 0.71873605
A25: 45689 | B25: 3441 | C25: 0.41479 | D25: 0.87675 | E25: 0 | F25: =C25+D25+E25 -> 1.29154 | G25: =H25+I25 -> 3340 | H25: =2307+385 -> 2692 | I25: 648 | J25: 891.18 | K25: =B25*F25 -> 4444.1891 | L25: =90%*K25-J25-O25 -> 3108.5902 | M25: =SUM(N25:O25) -> 444.41891 | N25: =K25*0.1 -> 444.41891 | O25: =G25*E25 -> 0 | P25: =L25/G25 -> 0.93071564 | Q25: =P25/F25 -> 0.72062471
A26: 45717 | B26: 3026 | C26: 0.38768 | D26: 0.8231 | E26: 0 | F26: =C26+D26+E26 -> 1.21078 | G26: =H26+I26 -> 2925 | H26: 2334 | I26: 591 | J26: 758.06 | K26: =B26*F26 -> 3663.8203 | L26: =90%*K26-J26-O26 -> 2539.3783 | M26: =SUM(N26:O26) -> 366.38203 | N26: =K26*0.1 -> 366.38203 | O26: =G26*E26 -> 0 | P26: =L26/G26 -> 0.8681635 | Q26: =P26/F26 -> 0.71702828
A27: 45748 | B27: 2633 | C27: 0.3947 | D27: 0.85016 | E27: 0 | F27: =C27+D27+E27 -> 1.24486 | G27: =H27+I27 -> 2533 | H27: =958+1268+2 -> 2228 | I27: =305 -> 305 | J27: 700.51 | K27: =B27*F27 -> 3277.7164 | L27: =90%*K27-J27-O27 -> 2249.4347 | M27: =SUM(N27:O27) -> 327.77164 | N27: =K27*0.1 -> 327.77164 | O27: =G27*E27 -> 0 | P27: =L27/G27 -> 0.88805162 | Q27: =P27/F27 -> 0.71337469
A28: 45778 | B28: 2454 | C28: 0.41709 | D28: 0.89838 | E28: 0.01728 | F28: =C28+D28+E28 -> 1.33275 | G28: =H28+I28 -> 2354 | H28: =1228+795+2 -> 2025 | I28: 329 | J28: 700.01 | K28: =B28*F28 -> 3270.5685 | L28: =90%*K28-J28-O28 -> 2202.8245 | M28: =SUM(N28:O28) -> 367.73397 | N28: =K28*0.1 -> 327.05685 | O28: =G28*E28 -> 40.67712 | P28: =L28/G28 -> 0.93577932 | Q28: =P28/F28 -> 0.70214168
A29: 45809 | B29: 2331 | C29: 0.41424 | D29: 0.89221 | E29: =0.04064+0.00944 -> 0.05008 | F29: =C29+D29+E29 -> 1.35653 | G29: =H29+I29 -> 2231 | H29: 2231 | I29: 0 | J29: 672.55 | K29: =B29*F29 -> 3162.0714 | L29: =90%*K29-J29-O29 -> 2061.5858 | M29: =SUM(N29:O29) -> 427.93562 | N29: =K29*0.1 -> 316.20714 | O29: =G29*E29 -> 111.72848 | P29: =L29/G29 -> 0.92406356 | Q29: =P29/F29 -> 0.68119655
A30: 45839 | B30: 2150 | C30: 0.406 | D30: 0.87448 | E30: 0.06174 | F30: =C30+D30+E30 -> 1.34222 | G30: =H30+I30 -> 2070 | H30: 2070 | I30: 0 | J30: 601.07 | K30: =B30*F30 -> 2885.773 | L30: =90%*K30-J30-O30 -> 1868.3239 | M30: =SUM(N30:O30) -> 416.3791 | N30: =K30*0.1 -> 288.5773 | O30: =G30*E30 -> 127.8018 | P30: =L30/G30 -> 0.90257193 | Q30: =P30/F30 -> 0.67244709
A31: 45870 | B31: 2139 | C31: 0.39747 | D31: 0.85611 | E31: 0.09127 | F31: =C31+D31+E31 -> 1.34485 | G31: =H31+I31 -> 2039 | H31: 2039 | I31: 0 | J31: 602.8 | K31: =B31*F31 -> 2876.6341 | L31: =90%*K31-J31-O31 -> 1800.0712 | M31: =SUM(N31:O31) -> 473.76295 | N31: =K31*0.1 -> 287.66341 | O31: =G31*E31 -> 186.09953 | P31: =L31/G31 -> 0.8828206 | Q31: =P31/F31 -> 0.6564454
A32: 45901 | B32: 2314 | C32: 0.4114 | D32: 0.8862 | E32: 0.11045 | F32: =C32+D32+E32 -> 1.40805 | G32: =H32+I32 -> 2214 | H32: 2214 | I32: 0 | J32: 670.92 | K32: =B32*F32 -> 3258.2277 | L32: =90%*K32-J32-O32 -> 2016.9486 | M32: =SUM(N32:O32) -> 570.35907 | N32: =K32*0.1 -> 325.82277 | O32: =G32*E32 -> 244.5363 | P32: =L32/G32 -> 0.91099757 | Q32: =P32/F32 -> 0.64699235

Sheet Faturamento Icaraí
